{
  "type": "Feature",
  "properties": {
    "gn:admin1_code":"8.0",
    "gn:asciiname":"hin Shen",
    "gn:country_code":"AM",
    "gn:dem":1120,
    "gn:feature_class":"P",
    "gn:feature_code":"PPL",
    "gn:name":"hin Shen",
    "gn:population":0,
    "gn:timezone":"Asia/Yerevan",
    "iso:country":"AM",
    "name:hye_x_preferred":[
        "hin Shen"
    ],
    "name:hye_x_variant":[
        "\u0540\u056b\u0576 \u0547\u0565\u0576"
    ],
    "wof:name":"hin Shen",
    "wof:placetype":"locality"
},
  "geometry": {"coordinates":[46.44452,39.49451],"type":"Point"}
}