{
  "type": "Feature",
  "properties": {
    "gn:admin1_code":"07",
    "gn:asciiname":"Jajurr",
    "gn:country_code":"AM",
    "gn:dem":1696,
    "gn:feature_class":"P",
    "gn:feature_code":"PPL",
    "gn:name":"Jajurr",
    "gn:population":0,
    "gn:timezone":"Asia/Yerevan",
    "iso:country":"AM",
    "name:hye_x_preferred":[
        "Jajurr"
    ],
    "name:hye_x_variant":[
        "\u054b\u0561\u057b\u0578\u0582\u057c"
    ],
    "name:und_x_variant":[
        "Dzhadzhur",
        "Jajur"
    ],
    "wof:name":"Jajurr",
    "wof:placetype":"locality"
},
  "geometry": {"coordinates":[43.95338,40.85154],"type":"Point"}
}