{
  "type": "Feature",
  "properties": {
    "gn:admin1_code":"9.0",
    "gn:asciiname":"Hin Poghpat",
    "gn:country_code":"AM",
    "gn:dem":1585,
    "gn:feature_class":"P",
    "gn:feature_code":"PPL",
    "gn:name":"Hin Poghpat",
    "gn:population":0,
    "gn:timezone":"Asia/Yerevan",
    "iso:country":"AM",
    "name:hye_x_preferred":[
        "Hin Poghpat"
    ],
    "name:hye_x_variant":[
        "\u0540\u056b\u0576 \u054a\u0578\u0572\u057a\u0561\u057f"
    ],
    "wof:name":"Hin Poghpat",
    "wof:placetype":"locality"
},
  "geometry": {"coordinates":[45.00848,40.66669],"type":"Point"}
}