{
  "type": "Feature",
  "properties": {
    "gn:admin1_code":"09",
    "gn:asciiname":"Golovino",
    "gn:country_code":"AM",
    "gn:dem":1534,
    "gn:feature_class":"P",
    "gn:feature_code":"PPL",
    "gn:name":"Golovino",
    "gn:population":0,
    "gn:timezone":"Asia/Yerevan",
    "iso:country":"AM",
    "name:fas_x_preferred":[
        "\u06af\u0648\u0644\u0648\u0648\u06cc\u0646\u0648"
    ],
    "wof:name":"Golovino",
    "wof:placetype":"locality"
},
  "geometry": {"coordinates":[44.84944,40.71306],"type":"Point"}
}