{
  "type": "Feature",
  "properties": {
    "gn:admin1_code":"9.0",
    "gn:asciiname":"Tsakageghi",
    "gn:country_code":"AM",
    "gn:dem":706,
    "gn:feature_class":"P",
    "gn:feature_code":"PPL",
    "gn:name":"Tsakageghi",
    "gn:population":0,
    "gn:timezone":"Asia/Yerevan",
    "iso:country":"AM",
    "name:hye_x_preferred":[
        "Tsakageghi"
    ],
    "name:hye_x_variant":[
        "\u053e\u0561\u056f\u0561\u0563\u0565\u0572\u056b"
    ],
    "wof:name":"Tsakageghi",
    "wof:placetype":"locality"
},
  "geometry": {"coordinates":[45.17651,41.03192],"type":"Point"}
}