{
  "type": "Feature",
  "properties": {
    "gn:admin1_code":"9.0",
    "gn:asciiname":"Isharats",
    "gn:country_code":"AM",
    "gn:dem":1292,
    "gn:feature_class":"P",
    "gn:feature_code":"PPL",
    "gn:name":"Isharats",
    "gn:population":0,
    "gn:timezone":"Asia/Yerevan",
    "iso:country":"AM",
    "name:hye_x_preferred":[
        "Isharats"
    ],
    "name:hye_x_variant":[
        "\u053b\u0577\u0561\u0580\u0561\u056e"
    ],
    "wof:name":"Isharats",
    "wof:placetype":"locality"
},
  "geometry": {"coordinates":[45.09729,40.91949],"type":"Point"}
}