{
  "type": "Feature",
  "properties": {
    "gn:admin1_code":"6.0",
    "gn:asciiname":"Arroghjaranin Kits'",
    "gn:country_code":"AM",
    "gn:dem":720,
    "gn:feature_class":"P",
    "gn:feature_code":"PPL",
    "gn:name":"Arroghjaranin Kits\u2019",
    "gn:population":0,
    "gn:timezone":"Asia/Yerevan",
    "iso:country":"AM",
    "name:hye_x_preferred":[
        "Arroghjaranin Kits\u2019"
    ],
    "name:hye_x_variant":[
        "\u0531\u057c\u0578\u0572\u057b\u0561\u0580\u0561\u0576\u056b\u0576 \u056f\u056b\u0581"
    ],
    "wof:name":"Arroghjaranin Kits'",
    "wof:placetype":"locality"
},
  "geometry": {"coordinates":[44.78888,41.1543],"type":"Point"}
}