{
  "type": "Feature",
  "properties": {
    "gn:admin1_code":"6.0",
    "gn:asciiname":"Kalategher",
    "gn:country_code":"AM",
    "gn:dem":1304,
    "gn:feature_class":"P",
    "gn:feature_code":"PPL",
    "gn:name":"Kalategher",
    "gn:population":0,
    "gn:timezone":"Asia/Yerevan",
    "iso:country":"AM",
    "name:hye_x_preferred":[
        "Kalategher"
    ],
    "name:hye_x_variant":[
        "\u053f\u0561\u056c\u0561\u057f\u0565\u0572\u0565\u0580"
    ],
    "wof:name":"Kalategher",
    "wof:placetype":"locality"
},
  "geometry": {"coordinates":[44.56671,40.92792],"type":"Point"}
}