{
  "type": "Feature",
  "properties": {
    "gn:asciiname":"Kamo Kaghak",
    "gn:country_code":"AM",
    "gn:dem":1961,
    "gn:feature_class":"P",
    "gn:feature_code":"PPL",
    "gn:name":"Kamo Kaghak",
    "gn:population":0,
    "gn:timezone":"Asia/Yerevan",
    "iso:country":"AM",
    "wof:name":"Kamo Kaghak",
    "wof:placetype":"locality"
},
  "geometry": {"coordinates":[45.13333,40.3504],"type":"Point"}
}