{
  "type": "Feature",
  "properties": {
    "gn:admin1_code":"1.0",
    "gn:asciiname":"Aghberak",
    "gn:country_code":"AM",
    "gn:dem":2040,
    "gn:feature_class":"P",
    "gn:feature_code":"PPL",
    "gn:name":"Aghberak",
    "gn:population":0,
    "gn:timezone":"Asia/Yerevan",
    "iso:country":"AM",
    "name:hye_x_preferred":[
        "Aghberak"
    ],
    "name:hye_x_variant":[
        "\u0531\u0572\u0562\u0565\u0580\u0561\u056f"
    ],
    "wof:name":"Aghberak",
    "wof:placetype":"locality"
},
  "geometry": {"coordinates":[44.28607,40.38068],"type":"Point"}
}