{
  "type": "Feature",
  "properties": {
    "gn:admin1_code":"6.0",
    "gn:asciiname":"Tap'is",
    "gn:country_code":"AM",
    "gn:dem":1496,
    "gn:feature_class":"P",
    "gn:feature_code":"PPL",
    "gn:name":"Tap\u2019is",
    "gn:population":0,
    "gn:timezone":"Asia/Yerevan",
    "iso:country":"AM",
    "name:hye_x_preferred":[
        "Tap\u2019is"
    ],
    "name:hye_x_variant":[
        "\u054f\u0561\u0583\u056b\u057d"
    ],
    "wof:name":"Tap'is",
    "wof:placetype":"locality"
},
  "geometry": {"coordinates":[44.48187,41.0307],"type":"Point"}
}