{
  "type": "Feature",
  "properties": {
    "gn:admin1_code":"08",
    "gn:asciiname":"Jrakhor",
    "gn:country_code":"AM",
    "gn:dem":1166,
    "gn:feature_class":"P",
    "gn:feature_code":"PPL",
    "gn:name":"Jrakhor",
    "gn:population":0,
    "gn:timezone":"Asia/Yerevan",
    "iso:country":"AM",
    "name:hye_x_preferred":[
        "Jrakhor"
    ],
    "name:hye_x_variant":[
        "\u054b\u0580\u0561\u056d\u0578\u0580"
    ],
    "name:und_x_variant":[
        "Dzhrakhof",
        "Dzhrakhor",
        "Razvaliny Dzhrakhor"
    ],
    "wof:name":"Jrakhor",
    "wof:placetype":"locality"
},
  "geometry": {"coordinates":[46.29169,39.21948],"type":"Point"}
}