{
  "type": "Feature",
  "properties": {
    "gn:admin1_code":"5.0",
    "gn:asciiname":"Dalar",
    "gn:country_code":"AM",
    "gn:dem":1655,
    "gn:feature_class":"P",
    "gn:feature_code":"PPL",
    "gn:name":"Dalar",
    "gn:population":0,
    "gn:timezone":"Asia/Yerevan",
    "iso:country":"AM",
    "name:ceb_x_preferred":[
        "Dalar"
    ],
    "name:hye_x_preferred":[
        "Dalar"
    ],
    "name:hye_x_variant":[
        "\u0534\u0561\u056c\u0561\u0580"
    ],
    "name:swe_x_preferred":[
        "Dalar"
    ],
    "wof:name":"Dalar",
    "wof:placetype":"locality"
},
  "geometry": {"coordinates":[44.59448,40.48889000000001],"type":"Point"}
}