{
  "type": "Feature",
  "properties": {
    "gn:admin1_code":"2.0",
    "gn:asciiname":"Khach'oyi Surb",
    "gn:country_code":"AM",
    "gn:dem":842,
    "gn:feature_class":"P",
    "gn:feature_code":"PPL",
    "gn:name":"Khach\u2019oyi Surb",
    "gn:population":0,
    "gn:timezone":"Asia/Yerevan",
    "iso:country":"AM",
    "name:hye_x_preferred":[
        "Khach\u2019oyi Surb"
    ],
    "name:hye_x_variant":[
        "\u053d\u0561\u0579\u0578\u0575\u056b \u054d\u0578\u0582\u0580\u0562"
    ],
    "wof:name":"Khach'oyi Surb",
    "wof:placetype":"locality"
},
  "geometry": {"coordinates":[44.52087,39.98889000000001],"type":"Point"}
}