{
  "type": "Feature",
  "properties": {
    "gn:admin1_code":"9.0",
    "gn:asciiname":"Handart Bats'at",
    "gn:country_code":"AM",
    "gn:dem":1557,
    "gn:feature_class":"P",
    "gn:feature_code":"PPL",
    "gn:name":"Handart Bats\u2019at",
    "gn:population":0,
    "gn:timezone":"Asia/Baku",
    "iso:country":"AM",
    "name:hye_x_preferred":[
        "Handart Bats\u2019at"
    ],
    "name:hye_x_variant":[
        "\u0540\u0561\u0576\u0564\u0561\u0580\u057f \u0562\u0561\u0581\u0561\u057f"
    ],
    "wof:name":"Handart Bats'at",
    "wof:placetype":"locality"
},
  "geometry": {"coordinates":[45.46252,40.75293],"type":"Point"}
}