{
  "type": "Feature",
  "properties": {
    "gn:admin1_code":"6.0",
    "gn:asciiname":"Tohmaberd",
    "gn:country_code":"AM",
    "gn:dem":724,
    "gn:feature_class":"P",
    "gn:feature_code":"PPL",
    "gn:name":"Tohmaberd",
    "gn:population":0,
    "gn:timezone":"Asia/Yerevan",
    "iso:country":"AM",
    "name:hye_x_preferred":[
        "Tohmaberd"
    ],
    "name:hye_x_variant":[
        "\u054f\u0578\u0570\u0574\u0561\u0562\u0565\u0580\u0564"
    ],
    "wof:name":"Tohmaberd",
    "wof:placetype":"locality"
},
  "geometry": {"coordinates":[44.75848,41.13611],"type":"Point"}
}