{
  "type": "Feature",
  "properties": {
    "gn:admin1_code":"1.0",
    "gn:asciiname":"T'alin",
    "gn:country_code":"AM",
    "gn:dem":2419,
    "gn:feature_class":"P",
    "gn:feature_code":"PPL",
    "gn:name":"T\u2019alin",
    "gn:population":0,
    "gn:timezone":"Asia/Yerevan",
    "iso:country":"AM",
    "name:hye_x_preferred":[
        "T\u2019alin"
    ],
    "name:hye_x_variant":[
        "\u0539\u0561\u056c\u056b\u0576"
    ],
    "wof:name":"T'alin",
    "wof:placetype":"locality"
},
  "geometry": {"coordinates":[44.01947,40.43048],"type":"Point"}
}