{
  "type": "Feature",
  "properties": {
    "gn:admin1_code":"9.0",
    "gn:asciiname":"Aygehovti",
    "gn:country_code":"AM",
    "gn:dem":1524,
    "gn:feature_class":"P",
    "gn:feature_code":"PPL",
    "gn:name":"Aygehovti",
    "gn:population":0,
    "gn:timezone":"Asia/Yerevan",
    "iso:country":"AM",
    "name:hye_x_preferred":[
        "Aygehovti"
    ],
    "name:hye_x_variant":[
        "\u0531\u0575\u0563\u0565\u0570\u0578\u057e\u057f\u056b"
    ],
    "wof:name":"Aygehovti",
    "wof:placetype":"locality"
},
  "geometry": {"coordinates":[45.23749,40.94031],"type":"Point"}
}