{
  "type": "Feature",
  "properties": {
    "gn:admin1_code":"10",
    "gn:asciiname":"Zorats'",
    "gn:country_code":"AM",
    "gn:dem":2218,
    "gn:feature_class":"P",
    "gn:feature_code":"PPL",
    "gn:name":"Zorats\u2019",
    "gn:population":0,
    "gn:timezone":"Asia/Yerevan",
    "iso:country":"AM",
    "name:hye_x_preferred":[
        "Zorats\u2019"
    ],
    "name:hye_x_variant":[
        "\u0536\u0578\u0580\u0561\u0581"
    ],
    "wof:name":"Zorats'",
    "wof:placetype":"locality"
},
  "geometry": {"coordinates":[45.36389000000001,39.62231],"type":"Point"}
}