{
  "type": "Feature",
  "properties": {
    "gn:admin1_code":"8.0",
    "gn:asciiname":"Khravand",
    "gn:country_code":"AM",
    "gn:dem":1114,
    "gn:feature_class":"P",
    "gn:feature_code":"PPL",
    "gn:name":"Khravand",
    "gn:population":0,
    "gn:timezone":"Asia/Yerevan",
    "iso:country":"AM",
    "name:hye_x_preferred":[
        "Khravand"
    ],
    "name:hye_x_variant":[
        "\u053d\u0580\u0561\u057e\u0561\u0576\u0564"
    ],
    "wof:name":"Khravand",
    "wof:placetype":"locality"
},
  "geometry": {"coordinates":[46.46393,39.08893],"type":"Point"}
}