{
  "type": "Feature",
  "properties": {
    "gn:admin1_code":"09",
    "gn:asciiname":"Hovk'",
    "gn:country_code":"AM",
    "gn:dem":1155,
    "gn:feature_class":"P",
    "gn:feature_code":"PPL",
    "gn:name":"Hovk\u2019",
    "gn:population":0,
    "gn:timezone":"Asia/Yerevan",
    "iso:country":"AM",
    "name:hye_x_preferred":[
        "Hovk\u2019"
    ],
    "name:hye_x_variant":[
        "\u0540\u0578\u057e\u0584"
    ],
    "name:und_x_variant":[
        "Akhkikhlu",
        "Akhkikhli"
    ],
    "wof:name":"Hovk'",
    "wof:placetype":"locality"
},
  "geometry": {"coordinates":[45.03332,40.78748],"type":"Point"}
}