{
  "type": "Feature",
  "properties": {
    "gn:admin1_code":"04",
    "gn:asciiname":"Khach'aghbyur",
    "gn:country_code":"AM",
    "gn:dem":1952,
    "gn:feature_class":"P",
    "gn:feature_code":"PPL",
    "gn:name":"Khach\u2019aghbyur",
    "gn:population":0,
    "gn:timezone":"Asia/Yerevan",
    "iso:country":"AM",
    "name:hye_x_preferred":[
        "\u053d\u0561\u0579\u0561\u0572\u0562\u0575\u0578\u0582\u0580"
    ],
    "name:und_x_variant":[
        "Sovetakert",
        "Chakhyrlu",
        "Chakhrlu",
        "Khachagbyur",
        "Khach\u2019aghbyur"
    ],
    "wof:name":"Khach'aghbyur",
    "wof:placetype":"locality"
},
  "geometry": {"coordinates":[45.69259,40.16808],"type":"Point"}
}