{
  "type": "Feature",
  "properties": {
    "gn:admin1_code":"04",
    "gn:asciiname":"Dzoravank'",
    "gn:country_code":"AM",
    "gn:dem":1170,
    "gn:feature_class":"P",
    "gn:feature_code":"PPL",
    "gn:name":"Dzoravank\u2019",
    "gn:population":0,
    "gn:timezone":"Asia/Yerevan",
    "iso:country":"AM",
    "name:aze_x_preferred":[
        "Qaraqaya"
    ],
    "name:hye_x_preferred":[
        "\u0541\u0578\u0580\u0561\u057e\u0561\u0576\u0584"
    ],
    "name:und_x_variant":[
        "Karakaya",
        "Dzoravank\u2019"
    ],
    "wof:name":"Dzoravank'",
    "wof:placetype":"locality"
},
  "geometry": {"coordinates":[45.10577,40.69918],"type":"Point"}
}