{
  "type": "Feature",
  "properties": {
    "gn:admin1_code":"04",
    "gn:asciiname":"Dzoravank'",
    "gn:country_code":"AM",
    "gn:dem":1170,
    "gn:feature_class":"P",
    "gn:feature_code":"PPL",
    "gn:name":"Dzoravank\u2019",
    "gn:population":0,
    "gn:timezone":"Asia/Yerevan",
    "iso:country":"AM",
    "name:aze_x_preferred":[
        "Qaraqaya"
    ],
    "name:che_x_preferred":[
        "\u0414\u0437\u043e\u0440\u0430\u0432\u0430\u043d\u043a"
    ],
    "name:fas_x_preferred":[
        "\u062f\u0632\u0648\u0631\u0627\u0648\u0627\u0646\u06a9"
    ],
    "name:fra_x_preferred":[
        "Dzoravank"
    ],
    "name:hye_x_preferred":[
        "\u0541\u0578\u0580\u0561\u057e\u0561\u0576\u0584"
    ],
    "name:ita_x_preferred":[
        "Dzoravanq"
    ],
    "name:kat_x_preferred":[
        "\u10eb\u10dd\u10e0\u10d0\u10d5\u10d0\u10dc\u10e5\u10d8"
    ],
    "name:msa_x_preferred":[
        "Dzoravank"
    ],
    "name:sco_x_preferred":[
        "Dzoravank"
    ],
    "name:spa_x_preferred":[
        "Dzoravank"
    ],
    "name:ukr_x_preferred":[
        "\u0414\u0437\u043e\u0440\u0430\u0432\u0430\u043d\u043a"
    ],
    "name:und_x_variant":[
        "Karakaya",
        "Dzoravank\u2019"
    ],
    "wof:name":"Dzoravank'",
    "wof:placetype":"locality"
},
  "geometry": {"coordinates":[45.10577,40.69918],"type":"Point"}
}