{
  "type": "Feature",
  "properties": {
    "iso:country":"AM",
    "name:arm_x_preferred":[
        "\u0532\u0565\u0580\u0564\u0561\u057e\u0561\u0576"
    ],
    "name:aze_x_preferred":[
        "Qala\u00e7a"
    ],
    "name:cat_x_preferred":[
        "Berdavan"
    ],
    "name:che_x_preferred":[
        "\u0411\u0435\u0440\u0434\u0430\u0432\u0430\u043d"
    ],
    "name:dut_x_preferred":[
        "Berdavan"
    ],
    "name:eng_x_preferred":[
        "Berdavan"
    ],
    "name:fas_x_preferred":[
        "\u0628\u0631\u062f\u0627\u0648\u0627\u0646"
    ],
    "name:fra_x_preferred":[
        "Berdavan"
    ],
    "name:fre_x_preferred":[
        "Berdavan"
    ],
    "name:geo_x_preferred":[
        "\u10d1\u10d4\u10e0\u10d3\u10d0\u10d5\u10d0\u10dc\u10d8"
    ],
    "name:ger_x_preferred":[
        "Berdawan"
    ],
    "name:hye_x_preferred":[
        "\u0532\u0565\u0580\u0564\u0561\u057e\u0561\u0576"
    ],
    "name:ita_x_preferred":[
        "Berdavan"
    ],
    "name:kat_x_preferred":[
        "\u10d1\u10d4\u10e0\u10d3\u10d0\u10d5\u10d0\u10dc\u10d8"
    ],
    "name:may_x_preferred":[
        "Berdavan"
    ],
    "name:msa_x_preferred":[
        "Berdavan"
    ],
    "name:nan_x_preferred":[
        "Berdavan"
    ],
    "name:oci_x_preferred":[
        "Berdavan"
    ],
    "name:per_x_preferred":[
        "\u0628\u0631\u062f\u0627\u0648\u0627\u0646"
    ],
    "name:rus_x_preferred":[
        "\u0411\u0435\u0440\u0434\u0430\u0432\u0430\u043d"
    ],
    "name:sco_x_preferred":[
        "Berdavan"
    ],
    "name:vie_x_preferred":[
        "Berdavan"
    ],
    "name:zho_min_nan_x_preferred":[
        "Berdavan"
    ],
    "qs:gn_country":"AM",
    "qs:gn_fcode":"PPL",
    "qs:gn_pop":3150,
    "qs:name":"Berdavan",
    "qs:name_adm0":"Armenia",
    "qs:name_adm1":"Tavush",
    "qs:photos":0,
    "qs:photos_1k":0,
    "qs:photos_9k":1,
    "qs:photos_9r":1,
    "qs:photos_all":9,
    "qs:photos_sr":0,
    "qs:placetype":"Town",
    "qs:pop_sr":"4",
    "qs:woe_adm0":23424743,
    "wd:wordcount":60,
    "wof:name":"Berdavan",
    "wof:placetype":"locality",
    "wof:population":3150
},
  "geometry": {"coordinates":[44.99967,41.20503],"type":"Point"}
}