{
  "type": "Feature",
  "properties": {
    "gn:admin1_code":"4.0",
    "gn:asciiname":"Barkis",
    "gn:country_code":"AM",
    "gn:dem":2550,
    "gn:feature_class":"P",
    "gn:feature_code":"PPL",
    "gn:name":"Barkis",
    "gn:population":0,
    "gn:timezone":"Asia/Yerevan",
    "iso:country":"AM",
    "name:hye_x_preferred":[
        "Barkis"
    ],
    "name:hye_x_variant":[
        "\u0532\u0561\u0580\u056f\u056b\u057d"
    ],
    "wof:name":"Barkis",
    "wof:placetype":"locality"
},
  "geometry": {"coordinates":[45.71668,40.06952],"type":"Point"}
}