{
  "type": "Feature",
  "properties": {
    "gn:admin1_code":"09",
    "gn:asciiname":"Papanino",
    "gn:country_code":"AM",
    "gn:dem":1300,
    "gn:feature_class":"P",
    "gn:feature_code":"PPL",
    "gn:name":"Papanino",
    "gn:population":0,
    "gn:timezone":"Asia/Yerevan",
    "iso:country":"AM",
    "wof:name":"Papanino",
    "wof:placetype":"locality"
},
  "geometry": {"coordinates":[44.84528,40.74194],"type":"Point"}
}