{
  "type": "Feature",
  "properties": {
    "gn:admin1_code":"4.0",
    "gn:asciiname":"Jali K'it'",
    "gn:country_code":"AM",
    "gn:dem":1904,
    "gn:feature_class":"P",
    "gn:feature_code":"PPL",
    "gn:name":"Jali K\u2019it\u2019",
    "gn:population":0,
    "gn:timezone":"Asia/Yerevan",
    "iso:country":"AM",
    "name:hye_x_preferred":[
        "Jali K\u2019it\u2019"
    ],
    "name:hye_x_variant":[
        "\u054b\u0561\u056c\u056b \u0584\u056b\u0569"
    ],
    "wof:name":"Jali K'it'",
    "wof:placetype":"locality"
},
  "geometry": {"coordinates":[45.05011,40.48749],"type":"Point"}
}