{
  "type": "Feature",
  "properties": {
    "iso:country":"AM",
    "name:ara_x_preferred":[
        "\u0628\u0627\u0631\u0627\u0648\u0627\u0643\u0627\u0631"
    ],
    "name:aze_x_preferred":[
        "Paravakar"
    ],
    "name:ceb_x_preferred":[
        "Parravak'ar"
    ],
    "name:che_x_preferred":[
        "\u041f\u0430\u0440\u0430\u0432\u0430\u043a\u0430\u0440"
    ],
    "name:ell_x_preferred":[
        "\u03a0\u03b1\u03c1\u03b1\u03b2\u03b1\u03ba\u03ac\u03c1"
    ],
    "name:eng_x_preferred":[
        "Parravak'ar"
    ],
    "name:eng_x_variant":[
        "Paravakar"
    ],
    "name:fas_x_preferred":[
        "\u067e\u0627\u0631\u0627\u0648\u0627\u06a9\u0627\u0631"
    ],
    "name:fra_x_preferred":[
        "Paravakar"
    ],
    "name:hye_x_preferred":[
        "\u054a\u0561\u057c\u0561\u057e\u0561\u0584\u0561\u0580"
    ],
    "name:ita_x_preferred":[
        "Paravakar"
    ],
    "name:kat_x_preferred":[
        "\u10de\u10d0\u10e0\u10d0\u10d5\u10d0\u10e5\u10d0\u10e0\u10d8"
    ],
    "name:msa_x_preferred":[
        "Paravakar"
    ],
    "name:nan_x_preferred":[
        "Paravakar"
    ],
    "name:nld_x_preferred":[
        "Paravakar"
    ],
    "name:rus_x_preferred":[
        "\u041f\u0430\u0440\u0430\u0432\u0430\u043a\u0430\u0440"
    ],
    "name:sco_x_preferred":[
        "Paravakar"
    ],
    "name:spa_x_preferred":[
        "Paravakar"
    ],
    "name:swe_x_preferred":[
        "Parravak'ar"
    ],
    "name:und_x_variant":[
        "Paravaker"
    ],
    "name:vie_x_preferred":[
        "Paravakar"
    ],
    "name:zho_min_nan_x_preferred":[
        "Paravakar"
    ],
    "name:zho_x_preferred":[
        "\u5e15\u62c9\u74e6\u5361\u5c14"
    ],
    "qs:gn_country":"AM",
    "qs:gn_fcode":"PPL",
    "qs:gn_pop":1637,
    "qs:name":"Parravak'ar",
    "qs:name_adm0":"Armenia",
    "qs:name_adm1":"Tavush",
    "qs:photos":0,
    "qs:photos_1k":0,
    "qs:photos_9k":1,
    "qs:photos_9r":1,
    "qs:photos_all":1,
    "qs:photos_sr":0,
    "qs:placetype":"Town",
    "qs:pop_sr":"3",
    "qs:woe_adm0":23424743,
    "wd:wordcount":59,
    "wof:name":"Parravak'ar",
    "wof:placetype":"locality",
    "wof:population":1637
},
  "geometry": {"coordinates":[45.367,40.98154],"type":"Point"}
}