{
  "type": "Feature",
  "properties": {
    "gn:country":"AM",
    "gn:fcode":"PPL",
    "gn:pop":1111,
    "iso:country":"AM",
    "name:aze_x_preferred":[
        "\u00c7otur"
    ],
    "name:eng_x_preferred":[
        "Saramej"
    ],
    "name:fas_x_preferred":[
        "\u0633\u0627\u0631\u0627\u0645\u062c"
    ],
    "name:fra_x_preferred":[
        "Saramej"
    ],
    "name:hye_x_preferred":[
        "Saramej"
    ],
    "name:hye_x_variant":[
        "\u054d\u0561\u0580\u0561\u0574\u0565\u057b"
    ],
    "name:ita_x_preferred":[
        "Saramech"
    ],
    "name:kat_x_preferred":[
        "\u10e1\u10d0\u10e0\u10d0\u10db\u10d4\u10ef\u10d8"
    ],
    "name:msa_x_preferred":[
        "Saramej"
    ],
    "name:nan_x_preferred":[
        "Saramej"
    ],
    "name:nld_x_preferred":[
        "Saramej"
    ],
    "name:rus_x_preferred":[
        "\u0421\u0430\u0440\u0430\u043c\u0435\u0447"
    ],
    "name:swe_x_preferred":[
        "Saramech"
    ],
    "name:unk_x_variant":[
        "Chotur"
    ],
    "qs:name":"Saramech",
    "qs:photos_9r":0,
    "qs:photos_sr":0,
    "qs:pop_sr":"3",
    "wd:wordcount":65,
    "wof:name":"Saramech",
    "wof:placetype":"locality",
    "wof:population":1111
},
  "geometry": {"coordinates":[44.2222,40.77487],"type":"Point"}
}