{
  "type": "Feature",
  "properties": {
    "gn:admin1_code":"1.0",
    "gn:asciiname":"Zoravar",
    "gn:country_code":"AM",
    "gn:dem":2024,
    "gn:feature_class":"P",
    "gn:feature_code":"PPL",
    "gn:name":"Zoravar",
    "gn:population":0,
    "gn:timezone":"Asia/Yerevan",
    "iso:country":"AM",
    "name:hye_x_preferred":[
        "Zoravar"
    ],
    "name:hye_x_variant":[
        "\u0536\u0578\u0580\u0561\u057e\u0561\u0580"
    ],
    "wof:name":"Zoravar",
    "wof:placetype":"locality"
},
  "geometry": {"coordinates":[44.32788,40.63751],"type":"Point"}
}