{
  "type": "Feature",
  "properties": {
    "gn:admin1_code":"01",
    "gn:asciiname":"Aragatsotn",
    "gn:country_code":"AM",
    "gn:dem":1884,
    "gn:feature_class":"P",
    "gn:feature_code":"PPL",
    "gn:name":"Aragatsotn",
    "gn:population":0,
    "gn:timezone":"Asia/Yerevan",
    "iso:country":"AM",
    "name:heb_x_preferred":[
        "\u05d0\u05e8\u05d2\u05d0\u05d8\u05e1\u05d5\u05d8\u05df"
    ],
    "name:hye_x_preferred":[
        "Aragatsotn"
    ],
    "name:hye_x_variant":[
        "\u0531\u0580\u0561\u0563\u0561\u056e\u0578\u057f\u0576"
    ],
    "name:und_x_variant":[
        "Koytu",
        "Razvaliny Aragatsotn",
        "Koytul"
    ],
    "wof:name":"Aragatsotn",
    "wof:placetype":"locality"
},
  "geometry": {"coordinates":[44.20007,40.34448],"type":"Point"}
}