{
  "type": "Feature",
  "properties": {
    "gn:admin1_code":"4.0",
    "gn:asciiname":"Andzav",
    "gn:country_code":"AM",
    "gn:dem":2179,
    "gn:feature_class":"P",
    "gn:feature_code":"PPL",
    "gn:name":"Andzav",
    "gn:population":0,
    "gn:timezone":"Asia/Yerevan",
    "iso:country":"AM",
    "name:hye_x_preferred":[
        "Andzav"
    ],
    "name:hye_x_variant":[
        "\u0531\u0576\u0571\u0561\u057e"
    ],
    "wof:name":"Andzav",
    "wof:placetype":"locality"
},
  "geometry": {"coordinates":[45.15289,40.26111],"type":"Point"}
}