{
  "type": "Feature",
  "properties": {
    "gn:admin1_code":"9.0",
    "gn:asciiname":"Spitak Jur",
    "gn:country_code":"AM",
    "gn:dem":1042,
    "gn:feature_class":"P",
    "gn:feature_code":"PPL",
    "gn:name":"Spitak Jur",
    "gn:population":0,
    "gn:timezone":"Asia/Yerevan",
    "iso:country":"AM",
    "name:hye_x_preferred":[
        "Spitak Jur"
    ],
    "name:hye_x_variant":[
        "\u054d\u057a\u056b\u057f\u0561\u056f \u057b\u0578\u0582\u0580"
    ],
    "wof:name":"Spitak Jur",
    "wof:placetype":"locality"
},
  "geometry": {"coordinates":[45.1029,40.85553],"type":"Point"}
}