{
  "type": "Feature",
  "properties": {
    "gn:admin1_code":"08",
    "gn:asciiname":"Verin Girat'agh",
    "gn:country_code":"AM",
    "gn:dem":1703,
    "gn:feature_class":"P",
    "gn:feature_code":"PPL",
    "gn:name":"Verin Girat\u2019agh",
    "gn:population":0,
    "gn:timezone":"Asia/Yerevan",
    "iso:country":"AM",
    "name:hye_x_preferred":[
        "Verin Girat\u2019agh"
    ],
    "name:hye_x_variant":[
        "\u054e\u0565\u0580\u056b\u0576 \u0533\u056b\u0580\u0561\u0569\u0561\u0572"
    ],
    "name:und_x_variant":[
        "Verin Giratakh",
        "Verkhniy Giratag"
    ],
    "wof:name":"Verin Girat'agh",
    "wof:placetype":"locality"
},
  "geometry": {"coordinates":[46.26672,39.2417],"type":"Point"}
}