{
  "type": "Feature",
  "properties": {
    "gn:admin1_code":"9.0",
    "gn:asciiname":"Lghots' Bats'at",
    "gn:country_code":"AM",
    "gn:dem":1017,
    "gn:feature_class":"P",
    "gn:feature_code":"PPL",
    "gn:name":"Lghots\u2019 Bats\u2019at",
    "gn:population":0,
    "gn:timezone":"Asia/Yerevan",
    "iso:country":"AM",
    "name:hye_x_preferred":[
        "Lghots\u2019 Bats\u2019at"
    ],
    "name:hye_x_variant":[
        "\u053c\u0572\u0578\u0581 \u0562\u0561\u0581\u0561\u057f"
    ],
    "wof:name":"Lghots' Bats'at",
    "wof:placetype":"locality"
},
  "geometry": {"coordinates":[45.12793,40.83209],"type":"Point"}
}