{
  "type": "Feature",
  "properties": {
    "gn:admin1_code":"8.0",
    "gn:asciiname":"Katar",
    "gn:country_code":"AM",
    "gn:dem":2606,
    "gn:feature_class":"P",
    "gn:feature_code":"PPL",
    "gn:name":"Katar",
    "gn:population":0,
    "gn:timezone":"Asia/Yerevan",
    "iso:country":"AM",
    "name:bar_x_preferred":[
        "Katar"
    ],
    "name:ceb_x_preferred":[
        "Katar"
    ],
    "name:ces_x_preferred":[
        "Katar"
    ],
    "name:deu_x_preferred":[
        "Katar"
    ],
    "name:epo_x_preferred":[
        "Kataro"
    ],
    "name:heb_x_preferred":[
        "\u05e7\u05d8\u05e8"
    ],
    "name:hye_x_preferred":[
        "Katar"
    ],
    "name:hye_x_variant":[
        "\u053f\u0561\u057f\u0561\u0580"
    ],
    "name:jpn_x_preferred":[
        "\u30ab\u30bf\u30fc\u30eb"
    ],
    "name:pol_x_preferred":[
        "Katar"
    ],
    "name:rus_x_preferred":[
        "\u041a\u0430\u0442\u0430\u0440"
    ],
    "name:slk_x_preferred":[
        "Katar"
    ],
    "name:swe_x_preferred":[
        "Katar"
    ],
    "name:ukr_x_preferred":[
        "\u041a\u0430\u0442\u0430\u0440"
    ],
    "wof:name":"Katar",
    "wof:placetype":"locality"
},
  "geometry": {"coordinates":[46.08069,39.30548],"type":"Point"}
}