{
  "type": "Feature",
  "properties": {
    "gn:admin1_code":"8.0",
    "gn:asciiname":"Katar",
    "gn:country_code":"AM",
    "gn:dem":2606,
    "gn:feature_class":"P",
    "gn:feature_code":"PPL",
    "gn:name":"Katar",
    "gn:population":0,
    "gn:timezone":"Asia/Yerevan",
    "iso:country":"AM",
    "name:hye_x_preferred":[
        "Katar"
    ],
    "name:hye_x_variant":[
        "\u053f\u0561\u057f\u0561\u0580"
    ],
    "wof:name":"Katar",
    "wof:placetype":"locality"
},
  "geometry": {"coordinates":[46.08069,39.30548],"type":"Point"}
}