{
  "type": "Feature",
  "properties": {
    "gn:admin1_code":"08",
    "gn:asciiname":"Alvank",
    "gn:country_code":"AM",
    "gn:dem":606,
    "gn:feature_class":"P",
    "gn:feature_code":"PPL",
    "gn:name":"Alvank",
    "gn:population":0,
    "gn:timezone":"Asia/Yerevan",
    "iso:country":"AM",
    "name:aze_x_preferred":[
        "Ald\u0259r\u0259"
    ],
    "name:che_x_preferred":[
        "\u0410\u043b\u0434\u0430\u0440\u0430"
    ],
    "name:fas_x_preferred":[
        "\u0622\u0644\u0648\u0627\u0646\u06a9"
    ],
    "name:fra_x_preferred":[
        "Alvank"
    ],
    "name:hye_x_preferred":[
        "\u0531\u056c\u057e\u0561\u0576\u0584"
    ],
    "name:ita_x_preferred":[
        "Alvanq"
    ],
    "name:kat_x_preferred":[
        "\u10d0\u10da\u10d5\u10d0\u10dc\u10e5\u10d8"
    ],
    "name:msa_x_preferred":[
        "Alvanq"
    ],
    "name:nld_x_preferred":[
        "Alvank"
    ],
    "name:sco_x_preferred":[
        "Alvanq"
    ],
    "name:spa_x_preferred":[
        "Alvank"
    ],
    "name:und_x_variant":[
        "Alvanq"
    ],
    "name:vie_x_preferred":[
        "Alvanq"
    ],
    "wof:name":"Alvank",
    "wof:placetype":"locality"
},
  "geometry": {"coordinates":[46.34657,38.9349],"type":"Point"}
}