{
  "type": "Feature",
  "properties": {
    "gn:admin1_code":"08",
    "gn:asciiname":"Alvank",
    "gn:country_code":"AM",
    "gn:dem":606,
    "gn:feature_class":"P",
    "gn:feature_code":"PPL",
    "gn:name":"Alvank",
    "gn:population":0,
    "gn:timezone":"Asia/Yerevan",
    "iso:country":"AM",
    "name:und_x_variant":[
        "Alvanq"
    ],
    "wof:name":"Alvank",
    "wof:placetype":"locality"
},
  "geometry": {"coordinates":[46.34657,38.9349],"type":"Point"}
}