{
  "type": "Feature",
  "properties": {
    "gn:admin1_code":"8.0",
    "gn:asciiname":"Shghardi Areg",
    "gn:country_code":"AM",
    "gn:dem":1006,
    "gn:feature_class":"P",
    "gn:feature_code":"PPL",
    "gn:name":"Shghardi Areg",
    "gn:population":0,
    "gn:timezone":"Asia/Yerevan",
    "iso:country":"AM",
    "name:hye_x_preferred":[
        "Shghardi Areg"
    ],
    "name:hye_x_variant":[
        "\u0547\u0572\u0561\u0580\u0564\u056b \u0561\u0580\u0565\u0563"
    ],
    "wof:name":"Shghardi Areg",
    "wof:placetype":"locality"
},
  "geometry": {"coordinates":[46.20007,38.92511],"type":"Point"}
}