{
  "type": "Feature",
  "properties": {
    "gn:admin1_code":"8.0",
    "gn:asciiname":"Zevu",
    "gn:country_code":"AM",
    "gn:dem":1275,
    "gn:feature_class":"P",
    "gn:feature_code":"PPL",
    "gn:name":"Zevu",
    "gn:population":0,
    "gn:timezone":"Asia/Yerevan",
    "iso:country":"AM",
    "name:hye_x_preferred":[
        "Zevu"
    ],
    "name:hye_x_variant":[
        "\u0536\u0587\u0578\u0582"
    ],
    "wof:name":"Zevu",
    "wof:placetype":"locality"
},
  "geometry": {"coordinates":[46.25568,39.19733],"type":"Point"}
}