{
  "type": "Feature",
  "properties": {
    "gn:admin1_code":"7.0",
    "gn:asciiname":"Gndak'ar",
    "gn:country_code":"AM",
    "gn:dem":1928,
    "gn:feature_class":"P",
    "gn:feature_code":"PPL",
    "gn:name":"Gndak\u2019ar",
    "gn:population":0,
    "gn:timezone":"Asia/Yerevan",
    "iso:country":"AM",
    "name:hye_x_preferred":[
        "Gndak\u2019ar"
    ],
    "name:hye_x_variant":[
        "\u0533\u0576\u0564\u0561\u0584\u0561\u0580"
    ],
    "wof:name":"Gndak'ar",
    "wof:placetype":"locality"
},
  "geometry": {"coordinates":[43.90008,40.50568],"type":"Point"}
}