{
  "type": "Feature",
  "properties": {
    "gn:admin1_code":"2.0",
    "gn:asciiname":"Daghnig",
    "gn:country_code":"AM",
    "gn:dem":1618,
    "gn:feature_class":"P",
    "gn:feature_code":"PPL",
    "gn:name":"Daghnig",
    "gn:population":0,
    "gn:timezone":"Asia/Yerevan",
    "iso:country":"AM",
    "name:hye_x_preferred":[
        "Daghnig"
    ],
    "name:hye_x_variant":[
        "\u0534\u0561\u0572\u0576\u056b\u0563"
    ],
    "wof:name":"Daghnig",
    "wof:placetype":"locality"
},
  "geometry": {"coordinates":[44.90008,39.90692],"type":"Point"}
}