{
  "type": "Feature",
  "properties": {
    "gn:admin1_code":"08",
    "gn:asciiname":"Baharlu",
    "gn:country_code":"AM",
    "gn:dem":1391,
    "gn:feature_class":"P",
    "gn:feature_code":"PPL",
    "gn:name":"Baharlu",
    "gn:population":0,
    "gn:timezone":"Asia/Yerevan",
    "iso:country":"AM",
    "name:aze_x_preferred":[
        "Baharl\u0131"
    ],
    "name:und_x_variant":[
        "Bagarlu",
        "Baharlu"
    ],
    "wof:name":"Baharlu",
    "wof:placetype":"locality"
},
  "geometry": {"coordinates":[46.21941,39.22064],"type":"Point"}
}