{
  "type": "Feature",
  "properties": {
    "gn:admin1_code":"6.0",
    "gn:asciiname":"Jghrner",
    "gn:country_code":"AM",
    "gn:dem":1451,
    "gn:feature_class":"P",
    "gn:feature_code":"PPL",
    "gn:name":"Jghrner",
    "gn:population":0,
    "gn:timezone":"Asia/Yerevan",
    "iso:country":"AM",
    "name:hye_x_preferred":[
        "Jghrner"
    ],
    "name:hye_x_variant":[
        "\u054b\u0572\u0580\u0576\u0565\u0580"
    ],
    "wof:name":"Jghrner",
    "wof:placetype":"locality"
},
  "geometry": {"coordinates":[44.80011,40.93329],"type":"Point"}
}