{
  "type": "Feature",
  "properties": {
    "gn:admin1_code":"2.0",
    "gn:asciiname":"Vranatak",
    "gn:country_code":"AM",
    "gn:dem":2160,
    "gn:feature_class":"P",
    "gn:feature_code":"PPL",
    "gn:name":"Vranatak",
    "gn:population":0,
    "gn:timezone":"Asia/Yerevan",
    "iso:country":"AM",
    "name:hye_x_preferred":[
        "Vranatak"
    ],
    "name:hye_x_variant":[
        "\u054e\u0580\u0561\u0576\u0561\u057f\u0561\u056f"
    ],
    "wof:name":"Vranatak",
    "wof:placetype":"locality"
},
  "geometry": {"coordinates":[45.02789,40.02789],"type":"Point"}
}