{
  "type": "Feature",
  "properties": {
    "gn:admin1_code":"09",
    "gn:asciiname":"Lchkadzor",
    "gn:country_code":"AM",
    "gn:dem":679,
    "gn:feature_class":"P",
    "gn:feature_code":"PPL",
    "gn:name":"Lchkadzor",
    "gn:population":0,
    "gn:timezone":"Asia/Yerevan",
    "iso:country":"AM",
    "name:hye_x_preferred":[
        "\u053c\u0573\u056f\u0561\u0571\u0578\u0580"
    ],
    "name:und_x_variant":[
        "Lichadzar",
        "Lichkadzor"
    ],
    "wof:name":"Lchkadzor",
    "wof:placetype":"locality"
},
  "geometry": {"coordinates":[44.9064,41.17736],"type":"Point"}
}