{
  "type": "Feature",
  "properties": {
    "gn:admin1_code":"6.0",
    "gn:asciiname":"Ach'ajur",
    "gn:country_code":"AM",
    "gn:dem":1758,
    "gn:feature_class":"P",
    "gn:feature_code":"PPL",
    "gn:name":"Ach\u2019ajur",
    "gn:population":0,
    "gn:timezone":"Asia/Yerevan",
    "iso:country":"AM",
    "name:hye_x_preferred":[
        "Ach\u2019ajur"
    ],
    "name:hye_x_variant":[
        "\u0531\u0579\u0561\u057b\u0578\u0582\u0580"
    ],
    "wof:name":"Ach'ajur",
    "wof:placetype":"locality"
},
  "geometry": {"coordinates":[44.7403,40.75708],"type":"Point"}
}