{
  "type": "Feature",
  "properties": {
    "gn:admin1_code":"4.0",
    "gn:asciiname":"Melk'oni",
    "gn:country_code":"AM",
    "gn:dem":1926,
    "gn:feature_class":"P",
    "gn:feature_code":"PPL",
    "gn:name":"Melk\u2019oni",
    "gn:population":0,
    "gn:timezone":"Asia/Yerevan",
    "iso:country":"AM",
    "name:hye_x_preferred":[
        "Melk\u2019oni"
    ],
    "name:hye_x_variant":[
        "\u0544\u0565\u056c\u0584\u0578\u0576\u056b"
    ],
    "wof:name":"Melk'oni",
    "wof:placetype":"locality"
},
  "geometry": {"coordinates":[45.69592,40.19031],"type":"Point"}
}