{
  "type": "Feature",
  "properties": {
    "gn:admin1_code":"7.0",
    "gn:asciiname":"Tsil",
    "gn:country_code":"AM",
    "gn:dem":1464,
    "gn:feature_class":"P",
    "gn:feature_code":"PPL",
    "gn:name":"Tsil",
    "gn:population":0,
    "gn:timezone":"Asia/Yerevan",
    "iso:country":"AM",
    "name:hye_x_preferred":[
        "Tsil"
    ],
    "name:hye_x_variant":[
        "\u053e\u056b\u056c"
    ],
    "wof:name":"Tsil",
    "wof:placetype":"locality"
},
  "geometry": {"coordinates":[43.64172,40.52368],"type":"Point"}
}