{
  "type": "Feature",
  "properties": {
    "gn:admin1_code":"5.0",
    "gn:asciiname":"Chluti",
    "gn:country_code":"AM",
    "gn:dem":1490,
    "gn:feature_class":"P",
    "gn:feature_code":"PPL",
    "gn:name":"Chluti",
    "gn:population":0,
    "gn:timezone":"Asia/Yerevan",
    "iso:country":"AM",
    "name:hye_x_preferred":[
        "Chluti"
    ],
    "name:hye_x_variant":[
        "\u0543\u056c\u0578\u0582\u057f\u056b"
    ],
    "wof:name":"Chluti",
    "wof:placetype":"locality"
},
  "geometry": {"coordinates":[44.55292,40.3515],"type":"Point"}
}