{
  "type": "Feature",
  "properties": {
    "gn:admin1_code":"6.0",
    "gn:asciiname":"Kartsakh",
    "gn:country_code":"AM",
    "gn:dem":716,
    "gn:feature_class":"P",
    "gn:feature_code":"PPL",
    "gn:name":"Kartsakh",
    "gn:population":0,
    "gn:timezone":"Asia/Yerevan",
    "iso:country":"AM",
    "name:hye_x_preferred":[
        "Kartsakh"
    ],
    "name:hye_x_variant":[
        "\u053f\u0561\u0580\u056e\u0561\u056d"
    ],
    "wof:name":"Kartsakh",
    "wof:placetype":"locality"
},
  "geometry": {"coordinates":[44.84308,41.12793],"type":"Point"}
}