{
  "type": "Feature",
  "properties": {
    "gn:admin1_code":"8.0",
    "gn:asciiname":"Aghats' Arti",
    "gn:country_code":"AM",
    "gn:dem":1580,
    "gn:feature_class":"P",
    "gn:feature_code":"PPL",
    "gn:name":"Aghats\u2019 Arti",
    "gn:population":0,
    "gn:timezone":"Asia/Yerevan",
    "iso:country":"AM",
    "name:hye_x_preferred":[
        "Aghats\u2019 Arti"
    ],
    "name:hye_x_variant":[
        "\u0531\u0572\u0561\u0581 \u0561\u0580\u057f\u056b"
    ],
    "wof:name":"Aghats' Arti",
    "wof:placetype":"locality"
},
  "geometry": {"coordinates":[46.18469,38.97229],"type":"Point"}
}