{
  "type": "Feature",
  "properties": {
    "gn:admin1_code":"6.0",
    "gn:asciiname":"K'arak'os",
    "gn:country_code":"AM",
    "gn:dem":2151,
    "gn:feature_class":"P",
    "gn:feature_code":"PPL",
    "gn:name":"K\u2019arak\u2019os",
    "gn:population":0,
    "gn:timezone":"Asia/Yerevan",
    "iso:country":"AM",
    "name:hye_x_preferred":[
        "K\u2019arak\u2019os"
    ],
    "name:hye_x_variant":[
        "\u0554\u0561\u0580\u0561\u0584\u0578\u057d"
    ],
    "wof:name":"K'arak'os",
    "wof:placetype":"locality"
},
  "geometry": {"coordinates":[44.54169,40.8653],"type":"Point"}
}