{
  "type": "Feature",
  "properties": {
    "gn:admin1_code":"02",
    "gn:asciiname":"Dashtak'ar",
    "gn:country_code":"AM",
    "gn:dem":968,
    "gn:feature_class":"P",
    "gn:feature_code":"PPL",
    "gn:name":"Dashtak\u2019ar",
    "gn:population":0,
    "gn:timezone":"Asia/Yerevan",
    "iso:country":"AM",
    "name:hye_x_preferred":[
        "Dashtak\u2019ar"
    ],
    "name:hye_x_variant":[
        "\u0534\u0561\u0577\u057f\u0561\u0584\u0561\u0580"
    ],
    "name:und_x_variant":[
        "Dashtakar",
        "Dashlu"
    ],
    "wof:name":"Dashtak'ar",
    "wof:placetype":"locality"
},
  "geometry": {"coordinates":[44.75568,39.9223],"type":"Point"}
}