{
  "type": "Feature",
  "properties": {
    "gn:admin1_code":"02",
    "gn:asciiname":"Dashtak'ar",
    "gn:country_code":"AM",
    "gn:dem":968,
    "gn:feature_class":"P",
    "gn:feature_code":"PPL",
    "gn:name":"Dashtak\u2019ar",
    "gn:population":0,
    "gn:timezone":"Asia/Yerevan",
    "iso:country":"AM",
    "name:ara_x_preferred":[
        "\u062f\u0627\u0634\u062a\u0627\u0643\u0627\u0631"
    ],
    "name:aze_x_preferred":[
        "Da\u015fl\u0131"
    ],
    "name:che_x_preferred":[
        "\u0414\u0430\u0448\u0442\u0430\u043a\u0430\u0440"
    ],
    "name:fas_x_preferred":[
        "\u062f\u0627\u0634\u062a\u0627\u06a9\u0627\u0631"
    ],
    "name:fra_x_preferred":[
        "Dashtakar"
    ],
    "name:hye_x_preferred":[
        "Dashtak\u2019ar"
    ],
    "name:hye_x_variant":[
        "\u0534\u0561\u0577\u057f\u0561\u0584\u0561\u0580"
    ],
    "name:ita_x_preferred":[
        "Da\u0161taqar"
    ],
    "name:kat_x_preferred":[
        "\u10d3\u10d0\u10e8\u10e2\u10d0\u10e5\u10d0\u10e0\u10d8"
    ],
    "name:msa_x_preferred":[
        "Dashtakar"
    ],
    "name:spa_x_preferred":[
        "Dashtakar"
    ],
    "name:ukr_x_preferred":[
        "\u0414\u0430\u0448\u0442\u0430\u043a\u0430\u0440"
    ],
    "name:und_x_variant":[
        "Dashlu"
    ],
    "name:vie_x_preferred":[
        "Dashtaqar"
    ],
    "wof:name":"Dashtak'ar",
    "wof:placetype":"locality"
},
  "geometry": {"coordinates":[44.75568,39.9223],"type":"Point"}
}