{
  "type": "Feature",
  "properties": {
    "gn:admin1_code":"7.0",
    "gn:asciiname":"Chapkani",
    "gn:country_code":"AM",
    "gn:dem":2612,
    "gn:feature_class":"P",
    "gn:feature_code":"PPL",
    "gn:name":"Chapkani",
    "gn:population":0,
    "gn:timezone":"Asia/Yerevan",
    "iso:country":"AM",
    "name:hye_x_preferred":[
        "Chapkani"
    ],
    "name:hye_x_variant":[
        "\u0543\u0561\u057a\u056f\u0561\u0576\u056b"
    ],
    "wof:name":"Chapkani",
    "wof:placetype":"locality"
},
  "geometry": {"coordinates":[43.91107,41.15973],"type":"Point"}
}