{
  "type": "Feature",
  "properties": {
    "gn:admin1_code":"07",
    "gn:asciiname":"T'orosgyugh",
    "gn:country_code":"AM",
    "gn:dem":1902,
    "gn:feature_class":"P",
    "gn:feature_code":"PPL",
    "gn:name":"T\u2019orosgyugh",
    "gn:population":0,
    "gn:timezone":"Asia/Yerevan",
    "iso:country":"AM",
    "name:hye_x_preferred":[
        "\u0539\u0578\u0580\u0578\u057d\u0563\u0575\u0578\u0582\u0572"
    ],
    "name:und_x_variant":[
        "Torosgyukh",
        "T\u2019orosgyugh"
    ],
    "wof:name":"T'orosgyugh",
    "wof:placetype":"locality"
},
  "geometry": {"coordinates":[43.87305,40.93446],"type":"Point"}
}