{
  "type": "Feature",
  "properties": {
    "gn:admin1_code":"6.0",
    "gn:asciiname":"Jrhor",
    "gn:country_code":"AM",
    "gn:dem":1162,
    "gn:feature_class":"P",
    "gn:feature_code":"PPL",
    "gn:name":"Jrhor",
    "gn:population":0,
    "gn:timezone":"Asia/Yerevan",
    "iso:country":"AM",
    "name:hye_x_preferred":[
        "Jrhor"
    ],
    "name:hye_x_variant":[
        "\u054b\u0580\u0570\u0578\u0580"
    ],
    "wof:name":"Jrhor",
    "wof:placetype":"locality"
},
  "geometry": {"coordinates":[44.64728,40.99451],"type":"Point"}
}