{
  "type": "Feature",
  "properties": {
    "gn:admin1_code":"4.0",
    "gn:asciiname":"Shirimk'",
    "gn:country_code":"AM",
    "gn:dem":2079,
    "gn:feature_class":"P",
    "gn:feature_code":"PPL",
    "gn:name":"Shirimk\u2019",
    "gn:population":0,
    "gn:timezone":"Asia/Yerevan",
    "iso:country":"AM",
    "name:hye_x_preferred":[
        "Shirimk\u2019"
    ],
    "name:hye_x_variant":[
        "\u0547\u056b\u0580\u056b\u0574\u0584"
    ],
    "wof:name":"Shirimk'",
    "wof:placetype":"locality"
},
  "geometry": {"coordinates":[45.52649,40.38751],"type":"Point"}
}