{
  "type": "Feature",
  "properties": {
    "gn:admin1_code":"06",
    "gn:asciiname":"Jrarrat",
    "gn:country_code":"AM",
    "gn:dem":1811,
    "gn:feature_class":"P",
    "gn:feature_code":"PPL",
    "gn:name":"Jrarrat",
    "gn:population":0,
    "gn:timezone":"Asia/Yerevan",
    "iso:country":"AM",
    "name:fra_x_preferred":[
        "Jrarat"
    ],
    "name:hye_x_preferred":[
        "\u054b\u0580\u0561\u057c\u0561\u057f"
    ],
    "name:ita_x_preferred":[
        "Jrarat"
    ],
    "name:sco_x_preferred":[
        "Jrarat"
    ],
    "name:ukr_x_preferred":[
        "\u0414\u0436\u0440\u0430\u0440\u0430\u0442"
    ],
    "name:und_x_variant":[
        "Chrakhli",
        "Dzhrarat",
        "Jrarrat"
    ],
    "wof:name":"Jrarrat",
    "wof:placetype":"locality"
},
  "geometry": {"coordinates":[44.02725,40.73922],"type":"Point"}
}