{
  "type": "Feature",
  "properties": {
    "gn:admin1_code":"7.0",
    "gn:asciiname":"Andzavik",
    "gn:country_code":"AM",
    "gn:dem":1786,
    "gn:feature_class":"P",
    "gn:feature_code":"PPL",
    "gn:name":"Andzavik",
    "gn:population":0,
    "gn:timezone":"Asia/Yerevan",
    "iso:country":"AM",
    "name:hye_x_preferred":[
        "Andzavik"
    ],
    "name:hye_x_variant":[
        "\u0531\u0576\u0571\u0561\u057e\u056b\u056f"
    ],
    "wof:name":"Andzavik",
    "wof:placetype":"locality"
},
  "geometry": {"coordinates":[44.01111,40.70007],"type":"Point"}
}