{
  "type": "Feature",
  "properties": {
    "gn:admin1_code":"5.0",
    "gn:asciiname":"Vranateghi",
    "gn:country_code":"AM",
    "gn:dem":2327,
    "gn:feature_class":"P",
    "gn:feature_code":"PPL",
    "gn:name":"Vranateghi",
    "gn:population":0,
    "gn:timezone":"Asia/Yerevan",
    "iso:country":"AM",
    "name:hye_x_preferred":[
        "Vranateghi"
    ],
    "name:hye_x_variant":[
        "\u054e\u0580\u0561\u0576\u0561\u057f\u0565\u0572\u056b"
    ],
    "wof:name":"Vranateghi",
    "wof:placetype":"locality"
},
  "geometry": {"coordinates":[44.56671,40.48608],"type":"Point"}
}