{
  "type": "Feature",
  "properties": {
    "gn:admin1_code":"2.0",
    "gn:asciiname":"Aghjots'",
    "gn:country_code":"AM",
    "gn:dem":1680,
    "gn:feature_class":"P",
    "gn:feature_code":"PPL",
    "gn:name":"Aghjots\u2019",
    "gn:population":0,
    "gn:timezone":"Asia/Yerevan",
    "iso:country":"AM",
    "name:hye_x_preferred":[
        "Aghjots\u2019"
    ],
    "name:hye_x_variant":[
        "\u0531\u0572\u057b\u0578\u0581"
    ],
    "wof:name":"Aghjots'",
    "wof:placetype":"locality"
},
  "geometry": {"coordinates":[44.81811,40.09448],"type":"Point"}
}