{
  "type": "Feature",
  "properties": {
    "gn:admin1_code":"9.0",
    "gn:asciiname":"Chyughavran",
    "gn:country_code":"AM",
    "gn:dem":1687,
    "gn:feature_class":"P",
    "gn:feature_code":"PPL",
    "gn:name":"Chyughavran",
    "gn:population":0,
    "gn:timezone":"Asia/Yerevan",
    "iso:country":"AM",
    "name:hye_x_preferred":[
        "Chyughavran"
    ],
    "name:hye_x_variant":[
        "\u0543\u0575\u0578\u0582\u0572\u0561\u057e\u0580\u0561\u0576"
    ],
    "wof:name":"Chyughavran",
    "wof:placetype":"locality"
},
  "geometry": {"coordinates":[45.24872,40.78332],"type":"Point"}
}