{
  "type": "Feature",
  "properties": {
    "gn:admin1_code":"6.0",
    "gn:asciiname":"Shuriki Gomer",
    "gn:country_code":"AM",
    "gn:dem":1712,
    "gn:feature_class":"P",
    "gn:feature_code":"PPL",
    "gn:name":"Shuriki Gomer",
    "gn:population":0,
    "gn:timezone":"Asia/Yerevan",
    "iso:country":"AM",
    "name:hye_x_preferred":[
        "Shuriki Gomer"
    ],
    "name:hye_x_variant":[
        "\u0547\u0578\u0582\u0580\u056b\u056f\u056b \u0563\u0578\u0574\u0565\u0580"
    ],
    "wof:name":"Shuriki Gomer",
    "wof:placetype":"locality"
},
  "geometry": {"coordinates":[44.8125,40.95288],"type":"Point"}
}