{
  "type": "Feature",
  "properties": {
    "gn:admin1_code":"9.0",
    "gn:asciiname":"Sevk'ar",
    "gn:country_code":"AM",
    "gn:dem":1389,
    "gn:feature_class":"P",
    "gn:feature_code":"PPL",
    "gn:name":"Sevk\u2019ar",
    "gn:population":0,
    "gn:timezone":"Asia/Yerevan",
    "iso:country":"AM",
    "name:hye_x_preferred":[
        "Sevk\u2019ar"
    ],
    "name:hye_x_variant":[
        "\u054d\u0587\u0584\u0561\u0580"
    ],
    "wof:name":"Sevk'ar",
    "wof:placetype":"locality"
},
  "geometry": {"coordinates":[45.01947,40.88751],"type":"Point"}
}