{
  "type": "Feature",
  "properties": {
    "gn:admin1_code":"2.0",
    "gn:asciiname":"P'ok'r Hayaberd",
    "gn:country_code":"AM",
    "gn:dem":1377,
    "gn:feature_class":"P",
    "gn:feature_code":"PPL",
    "gn:name":"P\u2019ok\u2019r Hayaberd",
    "gn:population":0,
    "gn:timezone":"Asia/Yerevan",
    "iso:country":"AM",
    "name:hye_x_preferred":[
        "P\u2019ok\u2019r Hayaberd"
    ],
    "name:hye_x_variant":[
        "\u0553\u0578\u0584\u0580 \u0540\u0561\u0575\u0561\u0562\u0565\u0580\u0564"
    ],
    "wof:name":"P'ok'r Hayaberd",
    "wof:placetype":"locality"
},
  "geometry": {"coordinates":[44.98749,39.79871],"type":"Point"}
}