{
  "type": "Feature",
  "properties": {
    "iso:country":"AM",
    "name:ara_x_preferred":[
        "\u064a\u063a\u0648\u0627\u0631\u062f"
    ],
    "name:azb_x_preferred":[
        "\u06cc\u063a\u0648\u0627\u0631\u062f"
    ],
    "name:aze_x_preferred":[
        "Ye\u011fvard"
    ],
    "name:bel_x_preferred":[
        "\u0413\u043e\u0440\u0430\u0434 \u0415\u0433\u0432\u0430\u0440\u0434"
    ],
    "name:bul_x_preferred":[
        "\u0415\u0433\u0432\u0430\u0440\u0434"
    ],
    "name:ceb_x_preferred":[
        "Yeghvard"
    ],
    "name:che_x_preferred":[
        "\u0415\u0433\u0432\u0430\u0440\u0434"
    ],
    "name:deu_x_preferred":[
        "Jeghward"
    ],
    "name:ell_x_preferred":[
        "\u0393\u03b5\u03b3\u03b2\u03ac\u03c1\u03bd\u03c4"
    ],
    "name:eng_x_preferred":[
        "Yeghvard"
    ],
    "name:fas_x_preferred":[
        "\u06cc\u063a\u0648\u0627\u0631\u062f"
    ],
    "name:fin_x_preferred":[
        "Jegvard"
    ],
    "name:fra_x_preferred":[
        "Eghvard"
    ],
    "name:hsb_x_preferred":[
        "Jegward"
    ],
    "name:hye_x_preferred":[
        "\u0535\u0572\u057e\u0561\u0580\u0564"
    ],
    "name:hye_x_variant":[
        "Yeghvard"
    ],
    "name:ind_x_preferred":[
        "Yeghvard"
    ],
    "name:ita_x_preferred":[
        "Yeghvard"
    ],
    "name:kat_x_preferred":[
        "\u10d4\u10e6\u10d5\u10d0\u10e0\u10d3\u10d8"
    ],
    "name:lit_x_preferred":[
        "Jegvardas"
    ],
    "name:msa_x_preferred":[
        "Yeghvard"
    ],
    "name:mzn_x_preferred":[
        "\u06cc\u063a\u0648\u0627\u0631\u062f"
    ],
    "name:nan_x_preferred":[
        "Eghvard"
    ],
    "name:nld_x_preferred":[
        "Jegvard"
    ],
    "name:nld_x_variant":[
        "Yeghvard"
    ],
    "name:pol_x_preferred":[
        "Jeghward"
    ],
    "name:pol_x_variant":[
        "Jegward"
    ],
    "name:ron_x_preferred":[
        "Ehvard"
    ],
    "name:ron_x_variant":[
        "Yeghvard"
    ],
    "name:rus_x_preferred":[
        "\u0415\u0433\u0432\u0430\u0440\u0434"
    ],
    "name:sco_x_preferred":[
        "Yeghvard"
    ],
    "name:spa_x_preferred":[
        "Yeghvard"
    ],
    "name:srp_x_preferred":[
        "\u0408\u0435\u0433\u0432\u0430\u0440\u0434"
    ],
    "name:swe_x_preferred":[
        "Yeghvard"
    ],
    "name:ukr_x_preferred":[
        "\u0404\u0433\u0432\u0430\u0440\u0434"
    ],
    "name:urd_x_preferred":[
        "\u06cc\u063a\u0648\u0631\u062f"
    ],
    "name:vie_x_preferred":[
        "Yeghvard"
    ],
    "name:zho_min_nan_x_preferred":[
        "Eghvard"
    ],
    "qs:gn_country":"AM",
    "qs:gn_fcode":"PPL",
    "qs:gn_pop":10705,
    "qs:name":"Yegvard",
    "qs:name_adm0":"Armenia",
    "qs:name_adm1":"Kotayk'",
    "qs:photos":20,
    "qs:photos_1k":4,
    "qs:photos_9k":1,
    "qs:photos_9r":1,
    "qs:photos_all":20,
    "qs:photos_sr":1,
    "qs:placetype":"Town",
    "qs:pop_sr":"6",
    "qs:woe_adm0":23424743,
    "wd:wordcount":327,
    "wof:name":"Yegvard",
    "wof:placetype":"locality",
    "wof:population":10705
},
  "geometry": {"coordinates":[44.48138,40.32053],"type":"Point"}
}