{
  "type": "Feature",
  "properties": {
    "gn:admin1_code":"9.0",
    "gn:asciiname":"Khach'vacharr",
    "gn:country_code":"AM",
    "gn:dem":1043,
    "gn:feature_class":"P",
    "gn:feature_code":"PPL",
    "gn:name":"Khach\u2019vacharr",
    "gn:population":0,
    "gn:timezone":"Asia/Yerevan",
    "iso:country":"AM",
    "name:hye_x_preferred":[
        "Khach\u2019vacharr"
    ],
    "name:hye_x_variant":[
        "\u053d\u0561\u0579\u057e\u0561\u0573\u0561\u057c"
    ],
    "wof:name":"Khach'vacharr",
    "wof:placetype":"locality"
},
  "geometry": {"coordinates":[45.17511,40.85431],"type":"Point"}
}