{
  "type": "Feature",
  "properties": {
    "gn:admin1_code":"8.0",
    "gn:asciiname":"Aghvanadzor",
    "gn:country_code":"AM",
    "gn:dem":1635,
    "gn:feature_class":"P",
    "gn:feature_code":"PPL",
    "gn:name":"Aghvanadzor",
    "gn:population":0,
    "gn:timezone":"Asia/Yerevan",
    "iso:country":"AM",
    "name:hye_x_preferred":[
        "Aghvanadzor"
    ],
    "name:hye_x_variant":[
        "\u0531\u0572\u057e\u0561\u0576\u0561\u0571\u0578\u0580"
    ],
    "wof:name":"Aghvanadzor",
    "wof:placetype":"locality"
},
  "geometry": {"coordinates":[46.3111,38.98889000000001],"type":"Point"}
}