{
  "type": "Feature",
  "properties": {
    "gn:admin1_code":"10",
    "gn:asciiname":"Rrindi",
    "gn:country_code":"AM",
    "gn:dem":1307,
    "gn:feature_class":"P",
    "gn:feature_code":"PPL",
    "gn:name":"Rrindi",
    "gn:population":0,
    "gn:timezone":"Asia/Yerevan",
    "iso:country":"AM",
    "name:hye_x_preferred":[
        "Rrindi"
    ],
    "name:hye_x_variant":[
        "\u054c\u056b\u0576\u0564\u056b"
    ],
    "wof:name":"Rrindi",
    "wof:placetype":"locality"
},
  "geometry": {"coordinates":[45.16669,39.76672],"type":"Point"}
}