{
  "type": "Feature",
  "properties": {
    "gn:admin1_code":"07",
    "gn:asciiname":"Hayrenyats'",
    "gn:country_code":"AM",
    "gn:dem":1586,
    "gn:feature_class":"P",
    "gn:feature_code":"PPL",
    "gn:name":"Hayrenyats\u2019",
    "gn:population":0,
    "gn:timezone":"Asia/Yerevan",
    "iso:country":"AM",
    "name:aze_x_preferred":[
        "Sonqurlu"
    ],
    "name:bul_x_preferred":[
        "\u0410\u0439\u0440\u0435\u043d\u044f\u0446"
    ],
    "name:che_x_preferred":[
        "\u0410\u0439\u0440\u0435\u043d\u044f\u0446"
    ],
    "name:fas_x_preferred":[
        "\u0647\u0627\u06cc\u0631\u0646\u06cc\u0627\u062a\u0633"
    ],
    "name:fra_x_preferred":[
        "Hayrenyats"
    ],
    "name:hye_x_preferred":[
        "\u0540\u0561\u0575\u0580\u0565\u0576\u0575\u0561\u0581"
    ],
    "name:ita_x_preferred":[
        "Hayrenyac"
    ],
    "name:kat_x_preferred":[
        "\u10d0\u10d8\u10e0\u10d4\u10dc\u10d8\u10d0\u10ea\u10d8"
    ],
    "name:msa_x_preferred":[
        "Hayrenyats"
    ],
    "name:rus_x_preferred":[
        "\u0410\u0439\u0440\u0435\u043d\u044f\u0446"
    ],
    "name:sco_x_preferred":[
        "Hayrenyats"
    ],
    "name:spa_x_preferred":[
        "Hayrenyats"
    ],
    "name:und_x_variant":[
        "Songyurlu",
        "Songyur",
        "Ayrenyats",
        "Hayrenyats\u2019"
    ],
    "wof:name":"Hayrenyats'",
    "wof:placetype":"locality"
},
  "geometry": {"coordinates":[43.8727,40.63074],"type":"Point"}
}