{
  "type": "Feature",
  "properties": {
    "gn:admin1_code":"07",
    "gn:asciiname":"Hayrenyats'",
    "gn:country_code":"AM",
    "gn:dem":1586,
    "gn:feature_class":"P",
    "gn:feature_code":"PPL",
    "gn:name":"Hayrenyats\u2019",
    "gn:population":0,
    "gn:timezone":"Asia/Yerevan",
    "iso:country":"AM",
    "name:hye_x_preferred":[
        "\u0540\u0561\u0575\u0580\u0565\u0576\u0575\u0561\u0581"
    ],
    "name:und_x_variant":[
        "Songyurlu",
        "Songyur",
        "Ayrenyats",
        "Hayrenyats\u2019"
    ],
    "wof:name":"Hayrenyats'",
    "wof:placetype":"locality"
},
  "geometry": {"coordinates":[43.8727,40.63074],"type":"Point"}
}