{
  "type": "Feature",
  "properties": {
    "gn:admin1_code":"9.0",
    "gn:asciiname":"Chermakavan",
    "gn:country_code":"AM",
    "gn:dem":1599,
    "gn:feature_class":"P",
    "gn:feature_code":"PPL",
    "gn:name":"Chermakavan",
    "gn:population":0,
    "gn:timezone":"Asia/Yerevan",
    "iso:country":"AM",
    "name:aze_x_preferred":[
        "A\u011fkils\u0259"
    ],
    "name:fas_x_preferred":[
        "\u0686\u0631\u0645\u0627\u06a9\u0627\u0648\u0627\u0646"
    ],
    "name:hye_x_preferred":[
        "Chermakavan"
    ],
    "name:hye_x_variant":[
        "\u0543\u0565\u0580\u0574\u0561\u056f\u0561\u057e\u0561\u0576"
    ],
    "name:kat_x_preferred":[
        "\u10ed\u10d4\u10e0\u10db\u10d0\u10d9\u10d0\u10d5\u10d0\u10dc\u10d8"
    ],
    "name:sco_x_preferred":[
        "Chermakavan"
    ],
    "wof:name":"Chermakavan",
    "wof:placetype":"locality"
},
  "geometry": {"coordinates":[45.0293,40.70709],"type":"Point"}
}