{
  "type": "Feature",
  "properties": {
    "gn:admin1_code":"8.0",
    "gn:asciiname":"Lerrnagorts",
    "gn:country_code":"AM",
    "gn:dem":783,
    "gn:feature_class":"P",
    "gn:feature_code":"PPL",
    "gn:name":"Lerrnagorts",
    "gn:population":0,
    "gn:timezone":"Asia/Yerevan",
    "iso:country":"AM",
    "name:hye_x_preferred":[
        "Lerrnagorts"
    ],
    "name:hye_x_variant":[
        "\u053c\u0565\u057c\u0576\u0561\u0563\u0578\u0580\u056e"
    ],
    "wof:name":"Lerrnagorts",
    "wof:placetype":"locality"
},
  "geometry": {"coordinates":[46.4043,39.20709],"type":"Point"}
}