{
  "type": "Feature",
  "properties": {
    "gn:admin1_code":"7.0",
    "gn:asciiname":"Nerk'in Bandivan",
    "gn:country_code":"AM",
    "gn:dem":1869,
    "gn:feature_class":"P",
    "gn:feature_code":"PPL",
    "gn:name":"Nerk\u2019in Bandivan",
    "gn:population":0,
    "gn:timezone":"Asia/Yerevan",
    "iso:country":"AM",
    "name:hye_x_preferred":[
        "Nerk\u2019in Bandivan"
    ],
    "name:hye_x_variant":[
        "\u0546\u0565\u0580\u0584\u056b\u0576 \u0532\u0561\u0576\u0564\u056b\u057e\u0561\u0576"
    ],
    "wof:name":"Nerk'in Bandivan",
    "wof:placetype":"locality"
},
  "geometry": {"coordinates":[43.79449,40.95428],"type":"Point"}
}