{
  "type": "Feature",
  "properties": {
    "gn:admin1_code":"04",
    "gn:asciiname":"Mets Argichi",
    "gn:country_code":"AM",
    "gn:dem":2281,
    "gn:feature_class":"P",
    "gn:feature_code":"PPL",
    "gn:name":"Mets Argichi",
    "gn:population":0,
    "gn:timezone":"Asia/Yerevan",
    "iso:country":"AM",
    "name:hye_x_preferred":[
        "Mets Argichi"
    ],
    "name:hye_x_variant":[
        "\u0544\u0565\u056e \u0531\u0580\u0563\u056b\u0573\u056b"
    ],
    "wof:name":"Mets Argichi",
    "wof:placetype":"locality"
},
  "geometry": {"coordinates":[45.15289,40.00012],"type":"Point"}
}