{
  "type": "Feature",
  "properties": {
    "gn:admin1_code":"8.0",
    "gn:asciiname":"Yekeghets'i",
    "gn:country_code":"AM",
    "gn:dem":1508,
    "gn:feature_class":"P",
    "gn:feature_code":"PPL",
    "gn:name":"Yekeghets\u2019i",
    "gn:population":0,
    "gn:timezone":"Asia/Yerevan",
    "iso:country":"AM",
    "name:hye_x_preferred":[
        "Yekeghets\u2019i"
    ],
    "name:hye_x_variant":[
        "\u0535\u056f\u0565\u0572\u0565\u0581\u056b"
    ],
    "wof:name":"Yekeghets'i",
    "wof:placetype":"locality"
},
  "geometry": {"coordinates":[46.12512,39.44171],"type":"Point"}
}