{
  "type": "Feature",
  "properties": {
    "gn:admin1_code":"11.0",
    "gn:asciiname":"T'umanyan H.",
    "gn:country_code":"AM",
    "gn:dem":1014,
    "gn:feature_class":"P",
    "gn:feature_code":"PPL",
    "gn:name":"T\u2019umanyan H.",
    "gn:population":0,
    "gn:timezone":"Asia/Yerevan",
    "iso:country":"AM",
    "name:hye_x_preferred":[
        "T\u2019umanyan H."
    ],
    "name:hye_x_variant":[
        "\u0539\u0578\u0582\u0574\u0561\u0576\u0575\u0561\u0576 \u0540."
    ],
    "wof:name":"T'umanyan H.",
    "wof:placetype":"locality"
},
  "geometry": {"coordinates":[44.51111,40.1875],"type":"Point"}
}