{
  "type": "Feature",
  "properties": {
    "iso:country":"AM",
    "name:ara_x_preferred":[
        "\u0645\u0627\u0631\u0627\u0644\u064a\u0643"
    ],
    "name:arm_x_preferred":[
        "\u0544\u0561\u0580\u0561\u056c\u056b\u056f"
    ],
    "name:aze_x_preferred":[
        "Molla G\u00f6y\u00e7\u0259"
    ],
    "name:bel_x_preferred":[
        "\u0413\u043e\u0440\u0430\u0434 \u041c\u0430\u0440\u0430\u043b\u0456\u043a"
    ],
    "name:bul_x_preferred":[
        "\u041c\u0430\u0440\u0430\u043b\u0438\u043a"
    ],
    "name:ceb_x_preferred":[
        "Maralik"
    ],
    "name:che_x_preferred":[
        "\u041c\u0430\u0440\u0430\u043b\u0438\u043a"
    ],
    "name:dut_x_preferred":[
        "Maralik"
    ],
    "name:eng_x_preferred":[
        "Maralik"
    ],
    "name:epo_x_preferred":[
        "Maralik"
    ],
    "name:est_x_preferred":[
        "Maralik"
    ],
    "name:fas_x_preferred":[
        "\u0645\u0627\u0631\u0627\u0644\u06cc\u06a9"
    ],
    "name:fra_x_preferred":[
        "Maralik"
    ],
    "name:fre_x_preferred":[
        "Maralik"
    ],
    "name:geo_x_preferred":[
        "\u10db\u10d0\u10e0\u10d0\u10da\u10d8\u10d9\u10d8"
    ],
    "name:hye_x_preferred":[
        "\u0544\u0561\u0580\u0561\u056c\u056b\u056f"
    ],
    "name:ind_x_preferred":[
        "Maralik"
    ],
    "name:ita_x_preferred":[
        "Maralik"
    ],
    "name:kat_x_preferred":[
        "\u10db\u10d0\u10e0\u10d0\u10da\u10d8\u10d9\u10d8"
    ],
    "name:lit_x_preferred":[
        "Maralikas"
    ],
    "name:may_x_preferred":[
        "Maralik"
    ],
    "name:msa_x_preferred":[
        "Maralik"
    ],
    "name:mzn_x_preferred":[
        "\u0645\u0627\u0631\u0627\u0644\u06cc\u06a9"
    ],
    "name:nan_x_preferred":[
        "Maralik"
    ],
    "name:nld_x_preferred":[
        "Maralik"
    ],
    "name:per_x_preferred":[
        "\u0645\u0627\u0631\u0627\u0644\u06cc\u06a9"
    ],
    "name:ron_x_preferred":[
        "Maralik"
    ],
    "name:rum_x_preferred":[
        "Maralik"
    ],
    "name:rus_x_preferred":[
        "\u041c\u0430\u0440\u0430\u043b\u0438\u043a"
    ],
    "name:sco_x_preferred":[
        "Maralik"
    ],
    "name:spa_x_preferred":[
        "Maralik"
    ],
    "name:srp_x_preferred":[
        "\u041c\u0430\u0440\u0430\u043b\u0438\u043a"
    ],
    "name:swa_x_preferred":[
        "Maralik"
    ],
    "name:swe_x_preferred":[
        "Maralik"
    ],
    "name:ukr_x_preferred":[
        "\u041c\u0430\u0440\u0430\u043b\u0456\u043a"
    ],
    "name:unk_x_variant":[
        "Molla G\u00ebkcha"
    ],
    "name:vie_x_preferred":[
        "Maralik"
    ],
    "name:zho_min_nan_x_preferred":[
        "Maralik"
    ],
    "qs:gn_country":"AM",
    "qs:gn_fcode":"PPL",
    "qs:gn_pop":4959,
    "qs:name":"Maralik",
    "qs:name_adm0":"Armenia",
    "qs:name_adm1":"Shirak",
    "qs:photos":0,
    "qs:photos_1k":0,
    "qs:photos_9k":0,
    "qs:photos_9r":0,
    "qs:photos_all":0,
    "qs:photos_sr":0,
    "qs:placetype":"Town",
    "qs:pop_sr":"4",
    "qs:woe_adm0":23424743,
    "wd:wordcount":317,
    "wof:name":"Maralik",
    "wof:placetype":"locality",
    "wof:population":4959
},
  "geometry": {"coordinates":[43.86862,40.57453],"type":"Point"}
}