{
  "type": "Feature",
  "properties": {
    "gn:admin1_code":"4.0",
    "gn:asciiname":"Hamoyi",
    "gn:country_code":"AM",
    "gn:dem":1542,
    "gn:feature_class":"P",
    "gn:feature_code":"PPL",
    "gn:name":"Hamoyi",
    "gn:population":0,
    "gn:timezone":"Asia/Yerevan",
    "iso:country":"AM",
    "name:hye_x_preferred":[
        "Hamoyi"
    ],
    "name:hye_x_variant":[
        "\u0540\u0561\u0574\u0578\u0575\u056b"
    ],
    "wof:name":"Hamoyi",
    "wof:placetype":"locality"
},
  "geometry": {"coordinates":[45.22931,40.6723],"type":"Point"}
}