{
  "type": "Feature",
  "properties": {
    "gn:country":"AM",
    "gn:fcode":"PPL",
    "gn:pop":2354,
    "iso:country":"AM",
    "name:ara_x_preferred":[
        "\u0623\u0631\u0627\u0644\u064a\u0632\u060c \u0623\u0631\u0627\u0631\u0627\u062a"
    ],
    "name:ara_x_variant":[
        "\u0623\u0631\u0627\u0644\u064a\u0632"
    ],
    "name:aze_x_preferred":[
        "Qaralar"
    ],
    "name:bel_x_preferred":[
        "\u0421\u044f\u043b\u043e \u0410\u0440\u0430\u043b\u0435\u0437"
    ],
    "name:ceb_x_preferred":[
        "Aralez"
    ],
    "name:eng_x_preferred":[
        "Aralez"
    ],
    "name:fas_x_preferred":[
        "\u0622\u0631\u0627\u0644\u0632"
    ],
    "name:fra_x_preferred":[
        "Aralez"
    ],
    "name:hye_x_preferred":[
        "\u0531\u0580\u0561\u056c\u0565\u0566"
    ],
    "name:ita_x_preferred":[
        "Aralez"
    ],
    "name:kat_x_preferred":[
        "\u10d0\u10e0\u10d0\u10da\u10d4\u10d6\u10d8"
    ],
    "name:msa_x_preferred":[
        "Aralez"
    ],
    "name:nan_x_preferred":[
        "Aralez"
    ],
    "name:nld_x_preferred":[
        "Aralez"
    ],
    "name:rus_x_preferred":[
        "\u0410\u0440\u0430\u043b\u0435\u0437"
    ],
    "name:spa_x_preferred":[
        "Aralez"
    ],
    "name:swe_x_preferred":[
        "Aralez"
    ],
    "name:ukr_x_preferred":[
        "\u0410\u0440\u0430\u043b\u0435\u0437"
    ],
    "name:unk_x_variant":[
        "Aralek"
    ],
    "name:vie_x_preferred":[
        "Aralez"
    ],
    "qs:name":"Aralez",
    "qs:photos_9r":0,
    "qs:photos_sr":0,
    "qs:pop_sr":"4",
    "wd:wordcount":51,
    "wof:name":"Aralez",
    "wof:placetype":"locality",
    "wof:population":2354
},
  "geometry": {"coordinates":[44.6514,39.90195],"type":"Point"}
}