{
  "type": "Feature",
  "properties": {
    "gn:admin1_code":"1.0",
    "gn:asciiname":"Oskechyugh",
    "gn:country_code":"AM",
    "gn:dem":2519,
    "gn:feature_class":"P",
    "gn:feature_code":"PPL",
    "gn:name":"Oskechyugh",
    "gn:population":0,
    "gn:timezone":"Asia/Yerevan",
    "iso:country":"AM",
    "name:hye_x_preferred":[
        "Oskechyugh"
    ],
    "name:hye_x_variant":[
        "\u0548\u057d\u056f\u0565\u0573\u0575\u0578\u0582\u0572"
    ],
    "wof:name":"Oskechyugh",
    "wof:placetype":"locality"
},
  "geometry": {"coordinates":[44.49451,40.59308],"type":"Point"}
}