{
  "type": "Feature",
  "properties": {
    "gn:admin1_code":"9.0",
    "gn:asciiname":"Ach'ak'ar",
    "gn:country_code":"AM",
    "gn:dem":1768,
    "gn:feature_class":"P",
    "gn:feature_code":"PPL",
    "gn:name":"Ach\u2019ak\u2019ar",
    "gn:population":0,
    "gn:timezone":"Asia/Yerevan",
    "iso:country":"AM",
    "name:hye_x_preferred":[
        "Ach\u2019ak\u2019ar"
    ],
    "name:hye_x_variant":[
        "\u0531\u0579\u0561\u0584\u0561\u0580"
    ],
    "wof:name":"Ach'ak'ar",
    "wof:placetype":"locality"
},
  "geometry": {"coordinates":[45.0639,40.88611],"type":"Point"}
}