{
  "type": "Feature",
  "properties": {
    "gn:admin1_code":"0.0",
    "gn:asciiname":"Ts'lik",
    "gn:country_code":"AM",
    "gn:dem":1486,
    "gn:feature_class":"P",
    "gn:feature_code":"PPL",
    "gn:name":"Ts\u2019lik",
    "gn:population":0,
    "gn:timezone":"Asia/Yerevan",
    "iso:country":"AM",
    "name:hye_x_preferred":[
        "Ts\u2019lik"
    ],
    "name:hye_x_variant":[
        "\u0551\u056c\u056b\u056f"
    ],
    "wof:name":"Ts'lik",
    "wof:placetype":"locality"
},
  "geometry": {"coordinates":[46.2279,39.16949],"type":"Point"}
}