{
  "type": "Feature",
  "properties": {
    "gn:admin1_code":"07",
    "gn:asciiname":"Aravet",
    "gn:country_code":"AM",
    "gn:dem":2010,
    "gn:feature_class":"P",
    "gn:feature_code":"PPL",
    "gn:name":"Aravet",
    "gn:population":0,
    "gn:timezone":"Asia/Yerevan",
    "iso:country":"AM",
    "name:aze_x_preferred":[
        "\u0130lanl\u0131"
    ],
    "name:bul_x_preferred":[
        "\u0410\u0440\u0430\u0432\u0435\u0442"
    ],
    "name:che_x_preferred":[
        "\u0410\u0440\u0430\u0432\u0435\u0442"
    ],
    "name:fas_x_preferred":[
        "\u0622\u0631\u0627\u0648\u062a"
    ],
    "name:hye_x_preferred":[
        "\u0531\u0580\u0561\u057e\u0565\u057f"
    ],
    "name:kat_x_preferred":[
        "\u10d0\u10e0\u10d0\u10d5\u10d4\u10e2\u10d8"
    ],
    "name:rus_x_preferred":[
        "\u0410\u0440\u0430\u0432\u0435\u0442"
    ],
    "name:und_x_variant":[
        "Ilanli",
        "Ilanly",
        "Chaybasar",
        "Aravet"
    ],
    "wof:name":"Aravet",
    "wof:placetype":"locality"
},
  "geometry": {"coordinates":[43.77766,41.04774000000001],"type":"Point"}
}