{
  "type": "Feature",
  "properties": {
    "gn:admin1_code":"3.0",
    "gn:asciiname":"Amenayn Hayots' Kat'oghikos Minas A Aknets'i",
    "gn:country_code":"AM",
    "gn:dem":870,
    "gn:feature_class":"P",
    "gn:feature_code":"PPL",
    "gn:name":"Amenayn Hayots\u2019 Kat\u2019oghikos Minas A Aknets\u2019i",
    "gn:population":0,
    "gn:timezone":"Asia/Yerevan",
    "iso:country":"AM",
    "name:hye_x_preferred":[
        "Amenayn Hayots\u2019 Kat\u2019oghikos Minas A Aknets\u2019i"
    ],
    "name:hye_x_variant":[
        "\u0531\u0574\u0565\u0576\u0561\u0575\u0576 \u0570\u0561\u0575\u0578\u0581 \u056f\u0561\u0569\u0578\u0572\u056b\u056f\u0578\u057d \u0544\u056b\u0576\u0561\u057d \u0531 \u0531\u056f\u0576\u0565\u0581\u056b"
    ],
    "wof:name":"Amenayn Hayots' Kat'oghikos Minas A Aknets'i",
    "wof:placetype":"locality"
},
  "geometry": {"coordinates":[44.29309,40.15832],"type":"Point"}
}