{
  "type": "Feature",
  "properties": {
    "gn:admin1_code":"1.0",
    "gn:asciiname":"Surb Gort",
    "gn:country_code":"AM",
    "gn:dem":1477,
    "gn:feature_class":"P",
    "gn:feature_code":"PPL",
    "gn:name":"Surb Gort",
    "gn:population":0,
    "gn:timezone":"Asia/Yerevan",
    "iso:country":"AM",
    "name:hye_x_preferred":[
        "Surb Gort"
    ],
    "name:hye_x_variant":[
        "\u054d\u0578\u0582\u0580\u0562 \u0563\u0578\u0580\u057f"
    ],
    "wof:name":"Surb Gort",
    "wof:placetype":"locality"
},
  "geometry": {"coordinates":[43.7251,40.38892],"type":"Point"}
}