{
  "type": "Feature",
  "properties": {
    "gn:admin1_code":"5.0",
    "gn:asciiname":"Gerezmank'",
    "gn:country_code":"AM",
    "gn:dem":1841,
    "gn:feature_class":"P",
    "gn:feature_code":"PPL",
    "gn:name":"Gerezmank\u2019",
    "gn:population":0,
    "gn:timezone":"Asia/Yerevan",
    "iso:country":"AM",
    "name:hye_x_preferred":[
        "Gerezmank\u2019"
    ],
    "name:hye_x_variant":[
        "\u0533\u0565\u0580\u0565\u0566\u0574\u0561\u0576\u0584"
    ],
    "wof:name":"Gerezmank'",
    "wof:placetype":"locality"
},
  "geometry": {"coordinates":[44.69873,40.58472],"type":"Point"}
}