{
  "type": "Feature",
  "properties": {
    "gn:admin1_code":"10",
    "gn:asciiname":"Alikhan-Payasy",
    "gn:country_code":"AM",
    "gn:dem":1359,
    "gn:feature_class":"P",
    "gn:feature_code":"PPL",
    "gn:name":"Alikhan-Payasy",
    "gn:population":0,
    "gn:timezone":"Asia/Yerevan",
    "iso:country":"AM",
    "wof:name":"Alikhan-Payasy",
    "wof:placetype":"locality"
},
  "geometry": {"coordinates":[45.29111,39.81278],"type":"Point"}
}