{
  "type": "Feature",
  "properties": {
    "gn:admin1_code":"03",
    "gn:asciiname":"Verin Zeyva",
    "gn:country_code":"AM",
    "gn:dem":851,
    "gn:feature_class":"P",
    "gn:feature_code":"PPL",
    "gn:name":"Verin Zeyva",
    "gn:population":0,
    "gn:timezone":"Asia/Yerevan",
    "iso:country":"AM",
    "name:und_x_variant":[
        "Malaya Zeyva",
        "Verin Zeyva"
    ],
    "wof:name":"Verin Zeyva",
    "wof:placetype":"locality"
},
  "geometry": {"coordinates":[44.20007,40.13348],"type":"Point"}
}