{
  "type": "Feature",
  "properties": {
    "gn:admin1_code":"3.0",
    "gn:asciiname":"Mokhrablur",
    "gn:country_code":"AM",
    "gn:dem":847,
    "gn:feature_class":"P",
    "gn:feature_code":"PPL",
    "gn:name":"Mokhrablur",
    "gn:population":0,
    "gn:timezone":"Asia/Yerevan",
    "iso:country":"AM",
    "name:hye_x_preferred":[
        "Mokhrablur"
    ],
    "name:hye_x_variant":[
        "\u0544\u0578\u056d\u0580\u0561\u0562\u056c\u0578\u0582\u0580"
    ],
    "wof:name":"Mokhrablur",
    "wof:placetype":"locality"
},
  "geometry": {"coordinates":[44.27789,40.12231],"type":"Point"}
}