{
  "type": "Feature",
  "properties": {
    "gn:admin1_code":"11.0",
    "gn:asciiname":"Armenakyan A.",
    "gn:country_code":"AM",
    "gn:dem":1153,
    "gn:feature_class":"P",
    "gn:feature_code":"PPL",
    "gn:name":"Armenakyan A.",
    "gn:population":0,
    "gn:timezone":"Asia/Yerevan",
    "iso:country":"AM",
    "name:hye_x_preferred":[
        "Armenakyan A."
    ],
    "name:hye_x_variant":[
        "\u0531\u0580\u0574\u0565\u0576\u0561\u056f\u0575\u0561\u0576 \u0531."
    ],
    "wof:name":"Armenakyan A.",
    "wof:placetype":"locality"
},
  "geometry": {"coordinates":[44.53949,40.1875],"type":"Point"}
}