{
  "type": "Feature",
  "properties": {
    "gn:admin1_code":"02",
    "gn:asciiname":"K'aghts'rashen",
    "gn:country_code":"AM",
    "gn:dem":939,
    "gn:feature_class":"P",
    "gn:feature_code":"PPL",
    "gn:name":"K\u2019aghts\u2019rashen",
    "gn:population":0,
    "gn:timezone":"Asia/Yerevan",
    "iso:country":"AM",
    "name:ara_x_preferred":[
        "\u0643\u0627\u063a\u062a\u0633\u0631\u0627\u0634\u064a\u0646"
    ],
    "name:aze_x_preferred":[
        "Kaxtsra\u015fen"
    ],
    "name:che_x_preferred":[
        "\u041a\u0430\u0445\u0446\u0440\u0430\u0448\u0435\u043d"
    ],
    "name:fas_x_preferred":[
        "\u06a9\u0627\u063a\u062a\u0633\u0631\u0627\u0634\u0646"
    ],
    "name:fra_x_preferred":[
        "Kaghtsrashen"
    ],
    "name:hye_x_preferred":[
        "K\u2019aghts\u2019rashen"
    ],
    "name:hye_x_variant":[
        "\u0554\u0561\u0572\u0581\u0580\u0561\u0577\u0565\u0576"
    ],
    "name:ita_x_preferred":[
        "Qaghtsra\u0161en"
    ],
    "name:kat_x_preferred":[
        "\u10e5\u10d0\u10e6\u10ea\u10e0\u10d0\u10e8\u10d4\u10dc\u10d8"
    ],
    "name:msa_x_preferred":[
        "Kaghtsrashen"
    ],
    "name:spa_x_preferred":[
        "Kaghtsrashen"
    ],
    "name:ukr_x_preferred":[
        "\u041a\u0430\u0445\u0446\u0440\u0430\u0448\u0435\u043d"
    ],
    "name:und_x_variant":[
        "Kakhtsrashen"
    ],
    "name:vie_x_preferred":[
        "Kaghtsrashen"
    ],
    "wof:name":"K'aghts'rashen",
    "wof:placetype":"locality"
},
  "geometry": {"coordinates":[44.62512,39.98053],"type":"Point"}
}