{
  "type": "Feature",
  "properties": {
    "gn:admin1_code":"02",
    "gn:asciiname":"K'aghts'rashen",
    "gn:country_code":"AM",
    "gn:dem":939,
    "gn:feature_class":"P",
    "gn:feature_code":"PPL",
    "gn:name":"K\u2019aghts\u2019rashen",
    "gn:population":0,
    "gn:timezone":"Asia/Yerevan",
    "iso:country":"AM",
    "name:hye_x_preferred":[
        "K\u2019aghts\u2019rashen"
    ],
    "name:hye_x_variant":[
        "\u0554\u0561\u0572\u0581\u0580\u0561\u0577\u0565\u0576"
    ],
    "name:und_x_variant":[
        "Kaghtsrashen",
        "Kakhtsrashen"
    ],
    "wof:name":"K'aghts'rashen",
    "wof:placetype":"locality"
},
  "geometry": {"coordinates":[44.62512,39.98053],"type":"Point"}
}