{
  "type": "Feature",
  "properties": {
    "gn:admin1_code":"1.0",
    "gn:asciiname":"K'arap'i",
    "gn:country_code":"AM",
    "gn:dem":1269,
    "gn:feature_class":"P",
    "gn:feature_code":"PPL",
    "gn:name":"K\u2019arap\u2019i",
    "gn:population":0,
    "gn:timezone":"Asia/Yerevan",
    "iso:country":"AM",
    "name:hye_x_preferred":[
        "K\u2019arap\u2019i"
    ],
    "name:hye_x_variant":[
        "\u0554\u0561\u0580\u0561\u0583\u056b"
    ],
    "wof:name":"K'arap'i",
    "wof:placetype":"locality"
},
  "geometry": {"coordinates":[44.10828,40.30689],"type":"Point"}
}