{
  "type": "Feature",
  "properties": {
    "gn:admin1_code":"1.0",
    "gn:asciiname":"Khoch'er",
    "gn:country_code":"AM",
    "gn:dem":1651,
    "gn:feature_class":"P",
    "gn:feature_code":"PPL",
    "gn:name":"Khoch\u2019er",
    "gn:population":0,
    "gn:timezone":"Asia/Yerevan",
    "iso:country":"AM",
    "name:hye_x_preferred":[
        "Khoch\u2019er"
    ],
    "name:hye_x_variant":[
        "\u053d\u0578\u0579\u0565\u0580"
    ],
    "wof:name":"Khoch'er",
    "wof:placetype":"locality"
},
  "geometry": {"coordinates":[44.10828,40.34448],"type":"Point"}
}