{
  "type": "Feature",
  "properties": {
    "gn:admin1_code":"6.0",
    "gn:asciiname":"Krrvategh",
    "gn:country_code":"AM",
    "gn:dem":1828,
    "gn:feature_class":"P",
    "gn:feature_code":"PPL",
    "gn:name":"Krrvategh",
    "gn:population":0,
    "gn:timezone":"Asia/Yerevan",
    "iso:country":"AM",
    "name:hye_x_preferred":[
        "Krrvategh"
    ],
    "name:hye_x_variant":[
        "\u053f\u057c\u057e\u0561\u057f\u0565\u0572"
    ],
    "wof:name":"Krrvategh",
    "wof:placetype":"locality"
},
  "geometry": {"coordinates":[44.69592,40.89172],"type":"Point"}
}