{
  "type": "Feature",
  "properties": {
    "iso:country":"AM",
    "label:eng_x_preferred_longname":[
        "Masis Shrjan"
    ],
    "label:eng_x_preferred_placetype":[
        "shrjan"
    ],
    "name:eng_x_preferred":[
        "Masis"
    ],
    "name:eng_x_variant":[
        "Masis Shrjan"
    ],
    "qs:gn_pop":0,
    "qs:name":"Masis Shrjan",
    "qs:name_adm0":"Armenia",
    "qs:name_adm1":"Yerevan",
    "qs:photos":561,
    "qs:photos_1k":114,
    "qs:photos_9k":24,
    "qs:photos_9r":14,
    "qs:photos_all":5493,
    "qs:photos_sr":8,
    "qs:placetype":"County",
    "qs:pop_sr":"0",
    "qs:woe_adm0":23424743,
    "wof:name":"Masis",
    "wof:placetype":"county",
    "wof:placetype_local":"shrjan"
},
  "geometry": {"coordinates":[44.478149,40.229218],"type":"Point"}
}