{
  "type": "Feature",
  "properties": {
    "gn:admin1_code":"6.0",
    "gn:asciiname":"Kts'agomer",
    "gn:country_code":"AM",
    "gn:dem":895,
    "gn:feature_class":"P",
    "gn:feature_code":"PPL",
    "gn:name":"Kts\u2019agomer",
    "gn:population":0,
    "gn:timezone":"Asia/Yerevan",
    "iso:country":"AM",
    "name:hye_x_preferred":[
        "Kts\u2019agomer"
    ],
    "name:hye_x_variant":[
        "\u053f\u0581\u0561\u0563\u0578\u0574\u0565\u0580"
    ],
    "wof:name":"Kts'agomer",
    "wof:placetype":"locality"
},
  "geometry": {"coordinates":[44.65289,40.9917],"type":"Point"}
}