{
  "type": "Feature",
  "properties": {
    "gn:admin1_code":"07",
    "gn:asciiname":"Getik",
    "gn:country_code":"AM",
    "gn:dem":1962,
    "gn:feature_class":"P",
    "gn:feature_code":"PPL",
    "gn:name":"Getik",
    "gn:population":0,
    "gn:timezone":"Asia/Yerevan",
    "iso:country":"AM",
    "name:hye_x_preferred":[
        "\u0533\u0565\u057f\u056b\u056f"
    ],
    "name:und_x_variant":[
        "Alikhan",
        "Getik"
    ],
    "wof:name":"Getik",
    "wof:placetype":"locality"
},
  "geometry": {"coordinates":[44.05856,40.91531],"type":"Point"}
}