{
  "type": "Feature",
  "properties": {
    "gn:admin1_code":"2.0",
    "gn:asciiname":"Urmia",
    "gn:country_code":"AM",
    "gn:dem":798,
    "gn:feature_class":"P",
    "gn:feature_code":"PPL",
    "gn:name":"Urmia",
    "gn:population":0,
    "gn:timezone":"Asia/Yerevan",
    "iso:country":"AM",
    "name:hye_x_preferred":[
        "Urmia"
    ],
    "name:hye_x_variant":[
        "\u0548\u0552\u0580\u0574\u056b\u0561"
    ],
    "wof:name":"Urmia",
    "wof:placetype":"locality"
},
  "geometry": {"coordinates":[44.77087,39.71808],"type":"Point"}
}