{
  "type": "Feature",
  "properties": {
    "gn:admin1_code":"2.0",
    "gn:asciiname":"Mets Egherrni Zoherin",
    "gn:country_code":"AM",
    "gn:dem":828,
    "gn:feature_class":"P",
    "gn:feature_code":"PPL",
    "gn:name":"Mets Egherrni Zoherin",
    "gn:population":0,
    "gn:timezone":"Asia/Yerevan",
    "iso:country":"AM",
    "name:hye_x_preferred":[
        "Mets Egherrni Zoherin"
    ],
    "name:hye_x_variant":[
        "\u0544\u0565\u056e \u0565\u0572\u0565\u057c\u0576\u056b \u0566\u0578\u0570\u0565\u0580\u056b\u0576"
    ],
    "wof:name":"Mets Egherrni Zoherin",
    "wof:placetype":"locality"
},
  "geometry": {"coordinates":[44.66949,39.83209],"type":"Point"}
}