{
  "type": "Feature",
  "properties": {
    "gn:admin1_code":"6.0",
    "gn:asciiname":"Samsoni",
    "gn:country_code":"AM",
    "gn:dem":2020,
    "gn:feature_class":"P",
    "gn:feature_code":"PPL",
    "gn:name":"Samsoni",
    "gn:population":0,
    "gn:timezone":"Asia/Yerevan",
    "iso:country":"AM",
    "name:hye_x_preferred":[
        "Samsoni"
    ],
    "name:hye_x_variant":[
        "\u054d\u0561\u0574\u057d\u0578\u0576\u056b"
    ],
    "wof:name":"Samsoni",
    "wof:placetype":"locality"
},
  "geometry": {"coordinates":[44.65289,40.82092],"type":"Point"}
}