{
  "type": "Feature",
  "properties": {
    "gn:admin1_code":"4.0",
    "gn:asciiname":"Azati",
    "gn:country_code":"AM",
    "gn:dem":1922,
    "gn:feature_class":"P",
    "gn:feature_code":"PPL",
    "gn:name":"Azati",
    "gn:population":0,
    "gn:timezone":"Asia/Yerevan",
    "iso:country":"AM",
    "name:hye_x_preferred":[
        "Azati"
    ],
    "name:hye_x_variant":[
        "\u0531\u0566\u0561\u057f\u056b"
    ],
    "wof:name":"Azati",
    "wof:placetype":"locality"
},
  "geometry": {"coordinates":[45.10553,40.41949],"type":"Point"}
}