{
  "type": "Feature",
  "properties": {
    "gn:admin1_code":"7.0",
    "gn:asciiname":"Nor Gyughateghi",
    "gn:country_code":"AM",
    "gn:dem":1896,
    "gn:feature_class":"P",
    "gn:feature_code":"PPL",
    "gn:name":"Nor Gyughateghi",
    "gn:population":0,
    "gn:timezone":"Asia/Yerevan",
    "iso:country":"AM",
    "name:hye_x_preferred":[
        "Nor Gyughateghi"
    ],
    "name:hye_x_variant":[
        "\u0546\u0578\u0580 \u0563\u0575\u0578\u0582\u0572\u0561\u057f\u0565\u0572\u056b"
    ],
    "wof:name":"Nor Gyughateghi",
    "wof:placetype":"locality"
},
  "geometry": {"coordinates":[43.95972,40.88348],"type":"Point"}
}