{
  "type": "Feature",
  "properties": {
    "gn:admin1_code":"04",
    "gn:asciiname":"Nerin-Chambarak",
    "gn:country_code":"AM",
    "gn:dem":1799,
    "gn:feature_class":"P",
    "gn:feature_code":"PPL",
    "gn:name":"Nerin-Chambarak",
    "gn:population":0,
    "gn:timezone":"Asia/Yerevan",
    "iso:country":"AM",
    "name:und_x_variant":[
        "Nizhniy Chambarak",
        "Nerin-Chambarak"
    ],
    "wof:name":"Nerin-Chambarak",
    "wof:placetype":"locality"
},
  "geometry": {"coordinates":[45.33803,40.6237],"type":"Point"}
}