{
  "type": "Feature",
  "properties": {
    "gn:admin1_code":"10",
    "gn:asciiname":"Averk'",
    "gn:country_code":"AM",
    "gn:dem":1930,
    "gn:feature_class":"P",
    "gn:feature_code":"PPL",
    "gn:name":"Averk\u2019",
    "gn:population":0,
    "gn:timezone":"Asia/Yerevan",
    "iso:country":"AM",
    "name:hye_x_preferred":[
        "Averk\u2019"
    ],
    "name:hye_x_variant":[
        "\u0531\u057e\u0565\u0580\u0584"
    ],
    "wof:name":"Averk'",
    "wof:placetype":"locality"
},
  "geometry": {"coordinates":[45.46808,39.58612],"type":"Point"}
}