{
  "type": "Feature",
  "properties": {
    "gn:admin1_code":"6.0",
    "gn:asciiname":"Bado",
    "gn:country_code":"AM",
    "gn:dem":2355,
    "gn:feature_class":"P",
    "gn:feature_code":"PPL",
    "gn:name":"Bado",
    "gn:population":0,
    "gn:timezone":"Asia/Yerevan",
    "iso:country":"AM",
    "name:ceb_x_preferred":[
        "Bado"
    ],
    "name:deu_x_preferred":[
        "Bado"
    ],
    "name:hye_x_preferred":[
        "Bado"
    ],
    "name:hye_x_variant":[
        "\u0532\u0561\u0564\u0578"
    ],
    "name:swe_x_preferred":[
        "Bado"
    ],
    "wof:name":"Bado",
    "wof:placetype":"locality"
},
  "geometry": {"coordinates":[44.24731,40.91107],"type":"Point"}
}