{
  "type": "Feature",
  "properties": {
    "gn:admin1_code":"7.0",
    "gn:asciiname":"Dashuyn",
    "gn:country_code":"AM",
    "gn:dem":2126,
    "gn:feature_class":"P",
    "gn:feature_code":"PPL",
    "gn:name":"Dashuyn",
    "gn:population":0,
    "gn:timezone":"Asia/Yerevan",
    "iso:country":"AM",
    "name:hye_x_preferred":[
        "Dashuyn"
    ],
    "name:hye_x_variant":[
        "\u0534\u0561\u0577\u0578\u0582\u0575\u0576"
    ],
    "wof:name":"Dashuyn",
    "wof:placetype":"locality"
},
  "geometry": {"coordinates":[43.69873,41.09168],"type":"Point"}
}