{
  "type": "Feature",
  "properties": {
    "gn:admin1_code":"07",
    "gn:asciiname":"Tsaghkut",
    "gn:country_code":"AM",
    "gn:dem":2044,
    "gn:feature_class":"P",
    "gn:feature_code":"PPL",
    "gn:name":"Tsaghkut",
    "gn:population":0,
    "gn:timezone":"Asia/Yerevan",
    "iso:country":"AM",
    "name:hye_x_preferred":[
        "\u053e\u0561\u0572\u056f\u0578\u0582\u057f"
    ],
    "name:und_x_variant":[
        "Gyullidzha",
        "Gyullija",
        "Tsaghkut"
    ],
    "wof:name":"Tsaghkut",
    "wof:placetype":"locality"
},
  "geometry": {"coordinates":[43.62211,41.09668],"type":"Point"}
}