{
  "type": "Feature",
  "properties": {
    "gn:admin1_code":"07",
    "gn:asciiname":"Tsaghkut",
    "gn:country_code":"AM",
    "gn:dem":2044,
    "gn:feature_class":"P",
    "gn:feature_code":"PPL",
    "gn:name":"Tsaghkut",
    "gn:population":0,
    "gn:timezone":"Asia/Yerevan",
    "iso:country":"AM",
    "name:aze_x_preferred":[
        "G\u00fcll\u00fcc\u0259"
    ],
    "name:bul_x_preferred":[
        "\u0426\u0430\u0433\u043a\u0443\u0442"
    ],
    "name:ell_x_preferred":[
        "\u03a4\u03c3\u03b1\u03b3\u03ba\u03bf\u03cd\u03c4"
    ],
    "name:fas_x_preferred":[
        "\u062a\u0633\u0627\u063a\u06a9\u0648\u062a"
    ],
    "name:fra_x_preferred":[
        "Tsaghkut"
    ],
    "name:hye_x_preferred":[
        "\u053e\u0561\u0572\u056f\u0578\u0582\u057f"
    ],
    "name:ita_x_preferred":[
        "Tsaghkut"
    ],
    "name:kat_x_preferred":[
        "\u10ec\u10d0\u10e6\u10d9\u10e3\u10e2\u10d8"
    ],
    "name:msa_x_preferred":[
        "Tsaghkut"
    ],
    "name:spa_x_preferred":[
        "Tsaghkut"
    ],
    "name:und_x_variant":[
        "Gyullidzha",
        "Gyullija"
    ],
    "name:vie_x_preferred":[
        "Tsaghkut"
    ],
    "wof:name":"Tsaghkut",
    "wof:placetype":"locality"
},
  "geometry": {"coordinates":[43.62211,41.09668],"type":"Point"}
}