{
  "type": "Feature",
  "properties": {
    "gn:admin1_code":"11.0",
    "gn:asciiname":"Gyughateghi",
    "gn:country_code":"AM",
    "gn:dem":1234,
    "gn:feature_class":"P",
    "gn:feature_code":"PPL",
    "gn:name":"Gyughateghi",
    "gn:population":0,
    "gn:timezone":"Asia/Yerevan",
    "iso:country":"AM",
    "name:hye_x_preferred":[
        "Gyughateghi"
    ],
    "name:hye_x_variant":[
        "\u0533\u0575\u0578\u0582\u0572\u0561\u057f\u0565\u0572\u056b"
    ],
    "wof:name":"Gyughateghi",
    "wof:placetype":"locality"
},
  "geometry": {"coordinates":[44.5473,40.19311],"type":"Point"}
}