{
  "type": "Feature",
  "properties": {
    "gn:admin1_code":"02",
    "gn:asciiname":"Ipakly",
    "gn:cc2":"AM",
    "gn:country_code":"AM",
    "gn:dem":844,
    "gn:feature_class":"P",
    "gn:feature_code":"PPL",
    "gn:name":"Ipakly",
    "gn:population":0,
    "gn:timezone":"Asia/Yerevan",
    "iso:country":"AM",
    "name:aze_x_preferred":[
        "\u0130p\u0259kli"
    ],
    "name:und_x_variant":[
        "Ipakli",
        "Eylas",
        "Ipakly"
    ],
    "wof:name":"Ipakly",
    "wof:placetype":"locality"
},
  "geometry": {"coordinates":[44.41444,40.10861],"type":"Point"}
}