{
  "type": "Feature",
  "properties": {
    "gn:admin1_code":"01",
    "gn:asciiname":"Charchakis",
    "gn:country_code":"AM",
    "gn:dem":2127,
    "gn:feature_class":"P",
    "gn:feature_code":"PPL",
    "gn:name":"Charchakis",
    "gn:population":0,
    "gn:timezone":"Asia/Yerevan",
    "iso:country":"AM",
    "name:eng_x_preferred":[
        "Derek"
    ],
    "name:hye_x_preferred":[
        "Charchakis"
    ],
    "name:hye_x_variant":[
        "\u0543\u0561\u0580\u0573\u0561\u056f\u056b\u057d"
    ],
    "name:rus_x_preferred":[
        "\u0414\u0435\u0440\u0435\u043a"
    ],
    "name:und_x_variant":[
        "Dzhardzharis"
    ],
    "wof:name":"Charchakis",
    "wof:placetype":"locality"
},
  "geometry": {"coordinates":[44.32398,40.69974000000001],"type":"Point"}
}