{
  "type": "Feature",
  "properties": {
    "gn:admin1_code":"6.0",
    "gn:asciiname":"Tsanr Vran",
    "gn:country_code":"AM",
    "gn:dem":2012,
    "gn:feature_class":"P",
    "gn:feature_code":"PPL",
    "gn:name":"Tsanr Vran",
    "gn:population":0,
    "gn:timezone":"Asia/Yerevan",
    "iso:country":"AM",
    "name:hye_x_preferred":[
        "Tsanr Vran"
    ],
    "name:hye_x_variant":[
        "\u053e\u0561\u0576\u0580 \u057e\u0580\u0561\u0576"
    ],
    "wof:name":"Tsanr Vran",
    "wof:placetype":"locality"
},
  "geometry": {"coordinates":[44.70831,40.76111],"type":"Point"}
}