{
  "type": "Feature",
  "properties": {
    "gn:admin1_code":"04",
    "gn:asciiname":"Atdash",
    "gn:country_code":"AM",
    "gn:dem":2368,
    "gn:feature_class":"P",
    "gn:feature_code":"PPL",
    "gn:name":"Atdash",
    "gn:population":0,
    "gn:timezone":"Asia/Yerevan",
    "iso:country":"AM",
    "name:fas_x_preferred":[
        "\u0622\u062a\u062f\u0627\u0634"
    ],
    "wof:name":"Atdash",
    "wof:placetype":"locality"
},
  "geometry": {"coordinates":[45.18972,40.035],"type":"Point"}
}