{
  "type": "Feature",
  "properties": {
    "gn:admin1_code":"10.0",
    "gn:asciiname":"Knevank'",
    "gn:country_code":"AM",
    "gn:dem":1661,
    "gn:feature_class":"P",
    "gn:feature_code":"PPL",
    "gn:name":"Knevank\u2019",
    "gn:population":0,
    "gn:timezone":"Asia/Yerevan",
    "iso:country":"AM",
    "name:hye_x_preferred":[
        "Knevank\u2019"
    ],
    "wof:name":"Knevank'",
    "wof:placetype":"locality"
},
  "geometry": {"coordinates":[45.40973,39.87372],"type":"Point"}
}