{
  "type": "Feature",
  "properties": {
    "gn:admin1_code":"5.0",
    "gn:asciiname":"Babajur",
    "gn:country_code":"AM",
    "gn:dem":2141,
    "gn:feature_class":"P",
    "gn:feature_code":"PPL",
    "gn:name":"Babajur",
    "gn:population":0,
    "gn:timezone":"Asia/Yerevan",
    "iso:country":"AM",
    "name:hye_x_preferred":[
        "Babajur"
    ],
    "name:hye_x_variant":[
        "\u0532\u0561\u0562\u0561\u057b\u0578\u0582\u0580"
    ],
    "wof:name":"Babajur",
    "wof:placetype":"locality"
},
  "geometry": {"coordinates":[44.71112,40.30408],"type":"Point"}
}