{
  "type": "Feature",
  "properties": {
    "gn:admin1_code":"10.0",
    "gn:asciiname":"Saloramayri",
    "gn:country_code":"AM",
    "gn:dem":1517,
    "gn:feature_class":"P",
    "gn:feature_code":"PPL",
    "gn:name":"Saloramayri",
    "gn:population":0,
    "gn:timezone":"Asia/Yerevan",
    "iso:country":"AM",
    "name:hye_x_preferred":[
        "Saloramayri"
    ],
    "name:hye_x_variant":[
        "\u054d\u0561\u056c\u0578\u0580\u0561\u0574\u0561\u0575\u0580\u056b"
    ],
    "wof:name":"Saloramayri",
    "wof:placetype":"locality"
},
  "geometry": {"coordinates":[45.26111,39.86108],"type":"Point"}
}