{
  "type": "Feature",
  "properties": {
    "gn:admin1_code":"4.0",
    "gn:asciiname":"Borborraghbyur",
    "gn:country_code":"AM",
    "gn:dem":2418,
    "gn:feature_class":"P",
    "gn:feature_code":"PPL",
    "gn:name":"Borborraghbyur",
    "gn:population":0,
    "gn:timezone":"Asia/Yerevan",
    "iso:country":"AM",
    "name:hye_x_preferred":[
        "Borborraghbyur"
    ],
    "name:hye_x_variant":[
        "\u0532\u0578\u0580\u0562\u0578\u057c\u0561\u0572\u0562\u0575\u0578\u0582\u0580"
    ],
    "wof:name":"Borborraghbyur",
    "wof:placetype":"locality"
},
  "geometry": {"coordinates":[45.12793,40.07233],"type":"Point"}
}