{
  "type": "Feature",
  "properties": {
    "gn:admin1_code":"5.0",
    "gn:asciiname":"Geghavan",
    "gn:country_code":"AM",
    "gn:dem":1785,
    "gn:feature_class":"P",
    "gn:feature_code":"PPL",
    "gn:name":"Geghavan",
    "gn:population":0,
    "gn:timezone":"Asia/Yerevan",
    "iso:country":"AM",
    "name:hye_x_preferred":[
        "Geghavan"
    ],
    "name:hye_x_variant":[
        "\u0533\u0565\u0572\u0561\u057e\u0561\u0576"
    ],
    "wof:name":"Geghavan",
    "wof:placetype":"locality"
},
  "geometry": {"coordinates":[44.53332,40.4361],"type":"Point"}
}