{
  "type": "Feature",
  "properties": {
    "gn:admin1_code":"02",
    "gn:asciiname":"Mankuk",
    "gn:country_code":"AM",
    "gn:dem":1961,
    "gn:feature_class":"P",
    "gn:feature_code":"PPL",
    "gn:name":"Mankuk",
    "gn:population":0,
    "gn:timezone":"Asia/Yerevan",
    "iso:country":"AM",
    "name:hye_x_preferred":[
        "\u0544\u0561\u0576\u056f\u0578\u0582\u056f"
    ],
    "name:und_x_variant":[
        "Razvaliny Mankuk"
    ],
    "wof:name":"Mankuk",
    "wof:placetype":"locality"
},
  "geometry": {"coordinates":[45.00785,40.00836],"type":"Point"}
}