{
  "type": "Feature",
  "properties": {
    "gn:admin1_code":"4.0",
    "gn:asciiname":"Hanesi",
    "gn:country_code":"AM",
    "gn:dem":1508,
    "gn:feature_class":"P",
    "gn:feature_code":"PPL",
    "gn:name":"Hanesi",
    "gn:population":0,
    "gn:timezone":"Asia/Yerevan",
    "iso:country":"AM",
    "name:hye_x_preferred":[
        "Hanesi"
    ],
    "name:hye_x_variant":[
        "\u0540\u0561\u0576\u0565\u057d\u056b"
    ],
    "wof:name":"Hanesi",
    "wof:placetype":"locality"
},
  "geometry": {"coordinates":[45.15289,40.70288],"type":"Point"}
}