{
  "type": "Feature",
  "properties": {
    "gn:admin1_code":"05",
    "gn:asciiname":"Zovk'",
    "gn:country_code":"AM",
    "gn:dem":1674,
    "gn:feature_class":"P",
    "gn:feature_code":"PPL",
    "gn:name":"Zovk\u2019",
    "gn:population":0,
    "gn:timezone":"Asia/Yerevan",
    "iso:country":"AM",
    "name:hye_x_preferred":[
        "Zovk\u2019"
    ],
    "name:hye_x_variant":[
        "\u0536\u0578\u057e\u0584"
    ],
    "name:und_x_variant":[
        "Kyulludzha"
    ],
    "wof:name":"Zovk'",
    "wof:placetype":"locality"
},
  "geometry": {"coordinates":[44.69328,40.20542],"type":"Point"}
}