{
  "type": "Feature",
  "properties": {
    "gn:admin1_code":"05",
    "gn:asciiname":"Zovk'",
    "gn:country_code":"AM",
    "gn:dem":1674,
    "gn:feature_class":"P",
    "gn:feature_code":"PPL",
    "gn:name":"Zovk\u2019",
    "gn:population":0,
    "gn:timezone":"Asia/Yerevan",
    "iso:country":"AM",
    "name:aze_x_preferred":[
        "G\u00fcll\u00fcc\u0259"
    ],
    "name:fas_x_preferred":[
        "\u0632\u0648\u0648\u06a9"
    ],
    "name:fra_x_preferred":[
        "Zovk"
    ],
    "name:hye_x_preferred":[
        "Zovk\u2019"
    ],
    "name:hye_x_variant":[
        "\u0536\u0578\u057e\u0584"
    ],
    "name:ita_x_preferred":[
        "Zovk"
    ],
    "name:kat_x_preferred":[
        "\u10d6\u10dd\u10d5\u10e5\u10d8"
    ],
    "name:msa_x_preferred":[
        "Zovk"
    ],
    "name:sco_x_preferred":[
        "Zovk"
    ],
    "name:spa_x_preferred":[
        "Zovk"
    ],
    "name:und_x_variant":[
        "Kyulludzha"
    ],
    "name:vie_x_preferred":[
        "Zovk"
    ],
    "wof:name":"Zovk'",
    "wof:placetype":"locality"
},
  "geometry": {"coordinates":[44.69328,40.20542],"type":"Point"}
}