{
  "type": "Feature",
  "properties": {
    "gn:admin1_code":"7.0",
    "gn:asciiname":"Are",
    "gn:country_code":"AM",
    "gn:dem":1583,
    "gn:feature_class":"P",
    "gn:feature_code":"PPL",
    "gn:name":"Are",
    "gn:population":0,
    "gn:timezone":"Asia/Yerevan",
    "iso:country":"AM",
    "name:hye_x_preferred":[
        "Are"
    ],
    "name:hye_x_variant":[
        "\u0531\u0580\u0565"
    ],
    "wof:name":"Are",
    "wof:placetype":"locality"
},
  "geometry": {"coordinates":[43.94031,40.80829],"type":"Point"}
}