{
  "type": "Feature",
  "properties": {
    "gn:admin1_code":"10.0",
    "gn:asciiname":"Arrataghbyur",
    "gn:country_code":"AM",
    "gn:dem":2265,
    "gn:feature_class":"P",
    "gn:feature_code":"PPL",
    "gn:name":"Arrataghbyur",
    "gn:population":0,
    "gn:timezone":"Asia/Yerevan",
    "iso:country":"AM",
    "name:hye_x_preferred":[
        "Arrataghbyur"
    ],
    "name:hye_x_variant":[
        "\u0531\u057c\u0561\u057f\u0561\u0572\u0562\u0575\u0578\u0582\u0580"
    ],
    "wof:name":"Arrataghbyur",
    "wof:placetype":"locality"
},
  "geometry": {"coordinates":[45.65008,39.64728],"type":"Point"}
}