{
  "type": "Feature",
  "properties": {
    "gn:admin1_code":"02",
    "gn:asciiname":"Jghun",
    "gn:country_code":"AM",
    "gn:dem":1790,
    "gn:feature_class":"P",
    "gn:feature_code":"PPL",
    "gn:name":"Jghun",
    "gn:population":0,
    "gn:timezone":"Asia/Yerevan",
    "iso:country":"AM",
    "name:hye_x_preferred":[
        "Jghun"
    ],
    "name:hye_x_variant":[
        "\u054b\u0572\u0578\u0582\u0576"
    ],
    "wof:name":"Jghun",
    "wof:placetype":"locality"
},
  "geometry": {"coordinates":[45.02508,39.95569],"type":"Point"}
}