{
  "type": "Feature",
  "properties": {
    "gn:country":"AM",
    "gn:fcode":"PPL",
    "gn:pop":1045,
    "iso:country":"AM",
    "name:deu_x_preferred":[
        "Artabuynk"
    ],
    "name:hye_x_preferred":[
        "Yeghegis"
    ],
    "name:hye_x_variant":[
        "\u0535\u0572\u0565\u0563\u056b\u057d"
    ],
    "name:unk_x_variant":[
        "Yekhegis"
    ],
    "qs:name":"Yeghegis",
    "qs:photos_9r":0,
    "qs:photos_sr":0,
    "qs:pop_sr":"3",
    "wd:wordcount":140,
    "wof:name":"Yeghegis",
    "wof:placetype":"locality",
    "wof:population":1045
},
  "geometry": {"coordinates":[45.36002,39.87181],"type":"Point"}
}