{
  "type": "Feature",
  "properties": {
    "gn:country":"AM",
    "gn:fcode":"PPL",
    "gn:population":1045,
    "iso:country":"AM",
    "name:aze_x_preferred":[
        "\u018fl\u0259y\u0259z"
    ],
    "name:ceb_x_preferred":[
        "Yeghegis"
    ],
    "name:deu_x_preferred":[
        "Artabuynk"
    ],
    "name:deu_x_variant":[
        "Jeghegis"
    ],
    "name:eng_x_preferred":[
        "Yeghegis"
    ],
    "name:fas_x_preferred":[
        "\u06cc\u063a\u06af\u06cc\u0633"
    ],
    "name:fra_x_preferred":[
        "Eghegis"
    ],
    "name:hye_x_preferred":[
        "Yeghegis"
    ],
    "name:hye_x_variant":[
        "\u0535\u0572\u0565\u0563\u056b\u057d"
    ],
    "name:ita_x_preferred":[
        "Yeghegis"
    ],
    "name:kat_x_preferred":[
        "\u10d4\u10e6\u10d4\u10d2\u10d8\u10e1\u10d8"
    ],
    "name:msa_x_preferred":[
        "Yeghegis"
    ],
    "name:nan_x_preferred":[
        "Eghegis"
    ],
    "name:nld_x_preferred":[
        "Yeghegis"
    ],
    "name:rus_x_preferred":[
        "\u0415\u0445\u0435\u0433\u0438\u0441"
    ],
    "name:sco_x_preferred":[
        "Yeghegis"
    ],
    "name:spa_x_preferred":[
        "Yeghegis"
    ],
    "name:swe_x_preferred":[
        "Yeghegis"
    ],
    "name:ukr_x_preferred":[
        "\u0404\u0445\u0435\u0491\u0456\u0441"
    ],
    "name:und_x_variant":[
        "Yekhegis"
    ],
    "name:urd_x_preferred":[
        "\u06cc\u063a\u06af\u0633"
    ],
    "qs:name":"Yeghegis",
    "qs:photos_9r":0,
    "qs:photos_sr":0,
    "qs:pop_sr":"3",
    "wd:wordcount":140,
    "wof:name":"Yeghegis",
    "wof:placetype":"locality",
    "wof:population":1045
},
  "geometry": {"coordinates":[45.36002,39.87181],"type":"Point"}
}