{
  "type": "Feature",
  "properties": {
    "gn:admin1_code":"10",
    "gn:asciiname":"Khndzorut",
    "gn:country_code":"AM",
    "gn:dem":1922,
    "gn:feature_class":"P",
    "gn:feature_code":"PPL",
    "gn:name":"Khndzorut",
    "gn:population":0,
    "gn:timezone":"Asia/Yerevan",
    "iso:country":"AM",
    "name:hye_x_preferred":[
        "Khndzorut"
    ],
    "name:hye_x_variant":[
        "\u053d\u0576\u0571\u0578\u0580\u0578\u0582\u057f"
    ],
    "name:ukr_x_preferred":[
        "\u0425\u043d\u0434\u0437\u043e\u0440\u0443\u0442"
    ],
    "wof:name":"Khndzorut",
    "wof:placetype":"locality"
},
  "geometry": {"coordinates":[45.1167,39.84168],"type":"Point"}
}