{
  "type": "Feature",
  "properties": {
    "gn:admin1_code":"8.0",
    "gn:asciiname":"Vernatun",
    "gn:country_code":"AM",
    "gn:dem":1391,
    "gn:feature_class":"P",
    "gn:feature_code":"PPL",
    "gn:name":"Vernatun",
    "gn:population":0,
    "gn:timezone":"Asia/Yerevan",
    "iso:country":"AM",
    "name:hye_x_preferred":[
        "Vernatun"
    ],
    "name:hye_x_variant":[
        "\u054e\u0565\u0580\u0576\u0561\u057f\u0578\u0582\u0576"
    ],
    "wof:name":"Vernatun",
    "wof:placetype":"locality"
},
  "geometry": {"coordinates":[46.39313,39.60828],"type":"Point"}
}