{
  "type": "Feature",
  "properties": {
    "gn:admin1_code":"03",
    "gn:asciiname":"Metsamori",
    "gn:country_code":"AM",
    "gn:dem":930,
    "gn:feature_class":"P",
    "gn:feature_code":"PPL",
    "gn:name":"Metsamori",
    "gn:population":0,
    "gn:timezone":"Asia/Yerevan",
    "iso:country":"AM",
    "name:hye_x_preferred":[
        "Metsamori"
    ],
    "name:und_x_variant":[
        "Metsamor"
    ],
    "wof:name":"Metsamori",
    "wof:placetype":"locality"
},
  "geometry": {"coordinates":[44.15333,40.18083],"type":"Point"}
}