{
  "type": "Feature",
  "properties": {
    "gn:admin1_code":"08",
    "gn:asciiname":"P'khrut",
    "gn:country_code":"AM",
    "gn:dem":2038,
    "gn:feature_class":"P",
    "gn:feature_code":"PPL",
    "gn:name":"P\u2019khrut",
    "gn:population":0,
    "gn:timezone":"Asia/Yerevan",
    "iso:country":"AM",
    "name:aze_x_preferred":[
        "P\u0131xrut"
    ],
    "name:fas_x_preferred":[
        "\u067e\u062e\u0631\u0648\u062a"
    ],
    "name:hye_x_preferred":[
        "P\u2019khrut"
    ],
    "name:hye_x_variant":[
        "\u0553\u056d\u0580\u0578\u0582\u057f"
    ],
    "name:und_x_variant":[
        "Pykhrut",
        "Pkhrut"
    ],
    "wof:name":"P'khrut",
    "wof:placetype":"locality"
},
  "geometry": {"coordinates":[46.22229,39.14728],"type":"Point"}
}