{
  "type": "Feature",
  "properties": {
    "gn:admin1_code":"3.0",
    "gn:asciiname":"Sardarapati Chakatamarti",
    "gn:country_code":"AM",
    "gn:dem":913,
    "gn:feature_class":"P",
    "gn:feature_code":"PPL",
    "gn:name":"Sardarapati Chakatamarti",
    "gn:population":0,
    "gn:timezone":"Asia/Yerevan",
    "iso:country":"AM",
    "name:hye_x_preferred":[
        "Sardarapati Chakatamarti"
    ],
    "name:hye_x_variant":[
        "\u054d\u0561\u0580\u0564\u0561\u0580\u0561\u057a\u0561\u057f\u056b \u0573\u0561\u056f\u0561\u057f\u0561\u0574\u0561\u0580\u057f\u056b"
    ],
    "wof:name":"Sardarapati Chakatamarti",
    "wof:placetype":"locality"
},
  "geometry": {"coordinates":[43.95148,40.09308],"type":"Point"}
}