{
  "type": "Feature",
  "properties": {
    "gn:admin1_code":"05",
    "gn:asciiname":"Kat'naghbyur",
    "gn:country_code":"AM",
    "gn:dem":1446,
    "gn:feature_class":"P",
    "gn:feature_code":"PPL",
    "gn:name":"Kat\u2019naghbyur",
    "gn:population":0,
    "gn:timezone":"Asia/Yerevan",
    "iso:country":"AM",
    "name:hye_x_preferred":[
        "Kat\u2019naghbyur"
    ],
    "name:hye_x_variant":[
        "\u053f\u0561\u0569\u0576\u0561\u0572\u0562\u0575\u0578\u0582\u0580"
    ],
    "name:und_x_variant":[
        "Agadzor",
        "Katnakhpyur"
    ],
    "wof:name":"Kat'naghbyur",
    "wof:placetype":"locality"
},
  "geometry": {"coordinates":[44.67792,40.25848],"type":"Point"}
}