{
  "type": "Feature",
  "properties": {
    "gn:admin1_code":"1.0",
    "gn:asciiname":"Ambrots'i Gyugh",
    "gn:country_code":"AM",
    "gn:dem":1904,
    "gn:feature_class":"P",
    "gn:feature_code":"PPL",
    "gn:name":"Ambrots\u2019i Gyugh",
    "gn:population":0,
    "gn:timezone":"Asia/Yerevan",
    "iso:country":"AM",
    "name:hye_x_preferred":[
        "Ambrots\u2019i Gyugh"
    ],
    "name:hye_x_variant":[
        "\u0531\u0574\u0562\u0580\u0578\u0581\u056b \u0563\u0575\u0578\u0582\u0572"
    ],
    "wof:name":"Ambrots'i Gyugh",
    "wof:placetype":"locality"
},
  "geometry": {"coordinates":[44.36108,40.44733],"type":"Point"}
}