{
  "type": "Feature",
  "properties": {
    "gn:admin1_code":"02",
    "gn:asciiname":"Vardashen",
    "gn:country_code":"AM",
    "gn:dem":907,
    "gn:feature_class":"P",
    "gn:feature_code":"PPL",
    "gn:name":"Vardashen",
    "gn:population":0,
    "gn:timezone":"Asia/Yerevan",
    "iso:country":"AM",
    "name:ara_x_preferred":[
        "\u0641\u0627\u0631\u062f\u0627\u0634\u064a\u0646"
    ],
    "name:aze_x_preferred":[
        "Mehrabl\u0131"
    ],
    "name:bel_x_preferred":[
        "\u0412\u0430\u0440\u0434\u0430\u0448\u044d\u043d"
    ],
    "name:fas_x_preferred":[
        "\u0648\u0627\u0631\u062f\u0627\u0634\u0646"
    ],
    "name:fra_x_preferred":[
        "Vardashen"
    ],
    "name:hye_x_preferred":[
        "Vardashen"
    ],
    "name:hye_x_variant":[
        "\u054e\u0561\u0580\u0564\u0561\u0577\u0565\u0576"
    ],
    "name:ita_x_preferred":[
        "Vardashen"
    ],
    "name:kat_x_preferred":[
        "\u10d5\u10d0\u10e0\u10d3\u10d0\u10e8\u10d4\u10dc\u10d8"
    ],
    "name:msa_x_preferred":[
        "Vardashen"
    ],
    "name:spa_x_preferred":[
        "Vardashen"
    ],
    "name:ukr_x_preferred":[
        "\u0412\u0430\u0440\u0434\u0430\u0448\u0435\u043d"
    ],
    "name:und_x_variant":[
        "Megrablu"
    ],
    "name:vie_x_preferred":[
        "Vardashen"
    ],
    "wof:name":"Vardashen",
    "wof:placetype":"locality"
},
  "geometry": {"coordinates":[44.55276,40.0328],"type":"Point"}
}