{
  "type": "Feature",
  "properties": {
    "gn:admin1_code":"6.0",
    "gn:asciiname":"Shavrugh",
    "gn:country_code":"AM",
    "gn:dem":1725,
    "gn:feature_class":"P",
    "gn:feature_code":"PPL",
    "gn:name":"Shavrugh",
    "gn:population":0,
    "gn:timezone":"Asia/Yerevan",
    "iso:country":"AM",
    "name:hye_x_preferred":[
        "Shavrugh"
    ],
    "name:hye_x_variant":[
        "\u0547\u0561\u057e\u0580\u0578\u0582\u0572"
    ],
    "wof:name":"Shavrugh",
    "wof:placetype":"locality"
},
  "geometry": {"coordinates":[44.74591,40.71948],"type":"Point"}
}