{
  "type": "Feature",
  "properties": {
    "gn:admin1_code":"6.0",
    "gn:asciiname":"Geghategh",
    "gn:country_code":"AM",
    "gn:dem":1853,
    "gn:feature_class":"P",
    "gn:feature_code":"PPL",
    "gn:name":"Geghategh",
    "gn:population":0,
    "gn:timezone":"Asia/Yerevan",
    "iso:country":"AM",
    "name:hye_x_preferred":[
        "Geghategh"
    ],
    "name:hye_x_variant":[
        "\u0533\u0565\u0572\u0561\u057f\u0565\u0572"
    ],
    "wof:name":"Geghategh",
    "wof:placetype":"locality"
},
  "geometry": {"coordinates":[44.57788,40.81952],"type":"Point"}
}