{
  "type": "Feature",
  "properties": {
    "gn:admin1_code":"9.0",
    "gn:asciiname":"Ch'akhch'akh",
    "gn:country_code":"AM",
    "gn:dem":1683,
    "gn:feature_class":"P",
    "gn:feature_code":"PPL",
    "gn:name":"Ch\u2019akhch\u2019akh",
    "gn:population":0,
    "gn:timezone":"Asia/Yerevan",
    "iso:country":"AM",
    "name:hye_x_preferred":[
        "Ch\u2019akhch\u2019akh"
    ],
    "name:hye_x_variant":[
        "\u0549\u0561\u056d\u0579\u0561\u056d"
    ],
    "wof:name":"Ch'akhch'akh",
    "wof:placetype":"locality"
},
  "geometry": {"coordinates":[45.40008,40.7403],"type":"Point"}
}