{
  "type": "Feature",
  "properties": {
    "gn:admin1_code":"8.0",
    "gn:asciiname":"Masrik",
    "gn:country_code":"AM",
    "gn:dem":1999,
    "gn:feature_class":"P",
    "gn:feature_code":"PPL",
    "gn:name":"Masrik",
    "gn:population":0,
    "gn:timezone":"Asia/Yerevan",
    "iso:country":"AM",
    "name:hye_x_preferred":[
        "Masrik"
    ],
    "name:hye_x_variant":[
        "\u0544\u0561\u057d\u0580\u056b\u056f"
    ],
    "name:sco_x_preferred":[
        "Masrik"
    ],
    "wof:name":"Masrik",
    "wof:placetype":"locality"
},
  "geometry": {"coordinates":[46.3501,39.05011],"type":"Point"}
}