{
  "type": "Feature",
  "properties": {
    "gn:admin1_code":"7.0",
    "gn:asciiname":"Marmasheni",
    "gn:country_code":"AM",
    "gn:dem":2079,
    "gn:feature_class":"P",
    "gn:feature_code":"PPL",
    "gn:name":"Marmasheni",
    "gn:population":0,
    "gn:timezone":"Asia/Yerevan",
    "iso:country":"AM",
    "name:hye_x_preferred":[
        "Marmasheni"
    ],
    "name:hye_x_variant":[
        "\u0544\u0561\u0580\u0574\u0561\u0577\u0565\u0576\u056b"
    ],
    "wof:name":"Marmasheni",
    "wof:placetype":"locality"
},
  "geometry": {"coordinates":[43.84448,40.99731],"type":"Point"}
}