{
  "type": "Feature",
  "properties": {
    "gn:admin1_code":"1.0",
    "gn:asciiname":"Aniavan",
    "gn:country_code":"AM",
    "gn:dem":1411,
    "gn:feature_class":"P",
    "gn:feature_code":"PPL",
    "gn:name":"Aniavan",
    "gn:population":0,
    "gn:timezone":"Asia/Yerevan",
    "iso:country":"AM",
    "name:hye_x_preferred":[
        "Aniavan"
    ],
    "name:hye_x_variant":[
        "\u0531\u0576\u056b\u0561\u057e\u0561\u0576"
    ],
    "wof:name":"Aniavan",
    "wof:placetype":"locality"
},
  "geometry": {"coordinates":[43.64587,40.46393],"type":"Point"}
}