{
  "type": "Feature",
  "properties": {
    "gn:admin1_code":"1.0",
    "gn:asciiname":"Aniavan",
    "gn:country_code":"AM",
    "gn:dem":1411,
    "gn:feature_class":"P",
    "gn:feature_code":"PPL",
    "gn:name":"Aniavan",
    "gn:population":0,
    "gn:timezone":"Asia/Yerevan",
    "iso:country":"AM",
    "name:bul_x_preferred":[
        "\u0410\u043d\u0438\u0430\u0432\u0430\u043d"
    ],
    "name:fas_x_preferred":[
        "\u0622\u0646\u06cc\u0627\u0648\u0627\u0646"
    ],
    "name:fra_x_preferred":[
        "Aniavan"
    ],
    "name:hye_x_preferred":[
        "Aniavan"
    ],
    "name:hye_x_variant":[
        "\u0531\u0576\u056b\u0561\u057e\u0561\u0576"
    ],
    "name:ita_x_preferred":[
        "Aniavan"
    ],
    "name:kat_x_preferred":[
        "\u10d0\u10dc\u10d8\u10d0\u10d5\u10d0\u10dc\u10d8"
    ],
    "name:msa_x_preferred":[
        "Ani kayarani"
    ],
    "name:rus_x_preferred":[
        "\u0410\u043d\u0438\u0430\u0432\u0430\u043d"
    ],
    "name:sco_x_preferred":[
        "Aniavan"
    ],
    "name:spa_x_preferred":[
        "Aniavan"
    ],
    "name:vie_x_preferred":[
        "Aniavan"
    ],
    "wof:name":"Aniavan",
    "wof:placetype":"locality"
},
  "geometry": {"coordinates":[43.64587,40.46393],"type":"Point"}
}