{
  "type": "Feature",
  "properties": {
    "gn:admin1_code":"4.0",
    "gn:asciiname":"Tigranakert",
    "gn:country_code":"AM",
    "gn:dem":2178,
    "gn:feature_class":"P",
    "gn:feature_code":"PPL",
    "gn:name":"Tigranakert",
    "gn:population":0,
    "gn:timezone":"Asia/Yerevan",
    "iso:country":"AM",
    "name:deu_x_preferred":[
        "Tigranakert"
    ],
    "name:hye_x_preferred":[
        "Tigranakert"
    ],
    "name:hye_x_variant":[
        "\u054f\u056b\u0563\u0580\u0561\u0576\u0561\u056f\u0565\u0580\u057f"
    ],
    "name:nld_x_preferred":[
        "Tigranakert"
    ],
    "name:rus_x_preferred":[
        "\u0422\u0438\u0433\u0440\u0430\u043d\u0430\u043a\u0435\u0440\u0442"
    ],
    "name:spa_x_preferred":[
        "Tigranakert"
    ],
    "name:swe_x_preferred":[
        "Tigranakert"
    ],
    "name:ukr_x_preferred":[
        "\u0422\u0438\u0433\u0440\u0430\u043d\u0430\u043a\u0435\u0440\u0442"
    ],
    "wof:name":"Tigranakert",
    "wof:placetype":"locality"
},
  "geometry": {"coordinates":[45.80829,40.2807],"type":"Point"}
}