{
  "type": "Feature",
  "properties": {
    "gn:admin1_code":"4.0",
    "gn:asciiname":"Mets Shen",
    "gn:country_code":"AM",
    "gn:dem":2942,
    "gn:feature_class":"P",
    "gn:feature_code":"PPL",
    "gn:name":"Mets Shen",
    "gn:population":0,
    "gn:timezone":"Asia/Yerevan",
    "iso:country":"AM",
    "name:hye_x_preferred":[
        "Mets Shen"
    ],
    "name:hye_x_variant":[
        "\u0544\u0565\u056e \u0547\u0565\u0576"
    ],
    "wof:name":"Mets Shen",
    "wof:placetype":"locality"
},
  "geometry": {"coordinates":[45.02789,40.20831],"type":"Point"}
}