{
  "type": "Feature",
  "properties": {
    "gn:admin1_code":"8.0",
    "gn:asciiname":"Sarrents' Surb",
    "gn:country_code":"AM",
    "gn:dem":1874,
    "gn:feature_class":"P",
    "gn:feature_code":"PPL",
    "gn:name":"Sarrents\u2019 Surb",
    "gn:population":0,
    "gn:timezone":"Asia/Yerevan",
    "iso:country":"AM",
    "name:hye_x_preferred":[
        "Sarrents\u2019 Surb"
    ],
    "name:hye_x_variant":[
        "\u054d\u0561\u057c\u0565\u0576\u0581 \u054d\u0578\u0582\u0580\u0562"
    ],
    "wof:name":"Sarrents' Surb",
    "wof:placetype":"locality"
},
  "geometry": {"coordinates":[45.94873,39.57233],"type":"Point"}
}