{
  "type": "Feature",
  "properties": {
    "gn:admin1_code":"4.0",
    "gn:asciiname":"Mishoyi",
    "gn:country_code":"AM",
    "gn:dem":1970,
    "gn:feature_class":"P",
    "gn:feature_code":"PPL",
    "gn:name":"Mishoyi",
    "gn:population":0,
    "gn:timezone":"Asia/Yerevan",
    "iso:country":"AM",
    "name:hye_x_preferred":[
        "Mishoyi"
    ],
    "name:hye_x_variant":[
        "\u0544\u056b\u0577\u0578\u0575\u056b"
    ],
    "wof:name":"Mishoyi",
    "wof:placetype":"locality"
},
  "geometry": {"coordinates":[45.12512,40.58472],"type":"Point"}
}