{
  "type": "Feature",
  "properties": {
    "gn:admin1_code":"8.0",
    "gn:asciiname":"Berdatak",
    "gn:country_code":"AM",
    "gn:dem":1843,
    "gn:feature_class":"P",
    "gn:feature_code":"PPL",
    "gn:name":"Berdatak",
    "gn:population":0,
    "gn:timezone":"Asia/Yerevan",
    "iso:country":"AM",
    "name:hye_x_preferred":[
        "Berdatak"
    ],
    "name:hye_x_variant":[
        "\u0532\u0565\u0580\u0564\u0561\u057f\u0561\u056f"
    ],
    "wof:name":"Berdatak",
    "wof:placetype":"locality"
},
  "geometry": {"coordinates":[45.87793,39.62512],"type":"Point"}
}