{
  "type": "Feature",
  "properties": {
    "gn:admin1_code":"9.0",
    "gn:asciiname":"Nahatak",
    "gn:country_code":"AM",
    "gn:dem":753,
    "gn:feature_class":"P",
    "gn:feature_code":"PPL",
    "gn:name":"Nahatak",
    "gn:population":0,
    "gn:timezone":"Asia/Yerevan",
    "iso:country":"AM",
    "name:hye_x_preferred":[
        "Nahatak"
    ],
    "name:hye_x_variant":[
        "\u0546\u0561\u0570\u0561\u057f\u0561\u056f"
    ],
    "wof:name":"Nahatak",
    "wof:placetype":"locality"
},
  "geometry": {"coordinates":[45.16669,41.00708],"type":"Point"}
}