{
  "type": "Feature",
  "properties": {
    "gn:admin1_code":"10",
    "gn:asciiname":"Ararat-2",
    "gn:country_code":"AM",
    "gn:dem":2116,
    "gn:feature_class":"P",
    "gn:feature_code":"PPL",
    "gn:name":"Ararat-2",
    "gn:population":0,
    "gn:timezone":"Asia/Yerevan",
    "iso:country":"AM",
    "name:hye_x_preferred":[
        "Ararat-2"
    ],
    "name:hye_x_variant":[
        "\u0531\u0580\u0561\u0580\u0561\u057f-2"
    ],
    "wof:name":"Ararat-2",
    "wof:placetype":"locality"
},
  "geometry": {"coordinates":[45.67792,39.84168],"type":"Point"}
}