{
  "type": "Feature",
  "properties": {
    "gn:admin1_code":"01",
    "gn:asciiname":"Kotor",
    "gn:country_code":"AM",
    "gn:dem":1816,
    "gn:feature_class":"P",
    "gn:feature_code":"PPL",
    "gn:name":"Kotor",
    "gn:population":0,
    "gn:timezone":"Asia/Yerevan",
    "iso:country":"AM",
    "name:hye_x_preferred":[
        "Kotor"
    ],
    "name:hye_x_variant":[
        "\u053f\u0578\u057f\u0578\u0580"
    ],
    "name:und_x_variant":[
        "Razvaliny Koytur",
        "Koytur"
    ],
    "wof:name":"Kotor",
    "wof:placetype":"locality"
},
  "geometry": {"coordinates":[44.37372,40.41809],"type":"Point"}
}