{
  "type": "Feature",
  "properties": {
    "gn:admin1_code":"8.0",
    "gn:asciiname":"Krp'adzor",
    "gn:country_code":"AM",
    "gn:dem":1923,
    "gn:feature_class":"P",
    "gn:feature_code":"PPL",
    "gn:name":"Krp\u2019adzor",
    "gn:population":0,
    "gn:timezone":"Asia/Yerevan",
    "iso:country":"AM",
    "name:hye_x_preferred":[
        "Krp\u2019adzor"
    ],
    "name:hye_x_variant":[
        "\u053f\u0580\u0583\u0561\u0571\u0578\u0580"
    ],
    "wof:name":"Krp'adzor",
    "wof:placetype":"locality"
},
  "geometry": {"coordinates":[45.94031,39.49591],"type":"Point"}
}