{
  "type": "Feature",
  "properties": {
    "gn:admin1_code":"4.0",
    "gn:asciiname":"Anmerr",
    "gn:country_code":"AM",
    "gn:dem":2071,
    "gn:feature_class":"P",
    "gn:feature_code":"PPL",
    "gn:name":"Anmerr",
    "gn:population":0,
    "gn:timezone":"Asia/Yerevan",
    "iso:country":"AM",
    "name:hye_x_preferred":[
        "Anmerr"
    ],
    "name:hye_x_variant":[
        "\u0531\u0576\u0574\u0565\u057c"
    ],
    "wof:name":"Anmerr",
    "wof:placetype":"locality"
},
  "geometry": {"coordinates":[45.51111,40.13208],"type":"Point"}
}