{
  "type": "Feature",
  "properties": {
    "gn:admin1_code":"10.0",
    "gn:asciiname":"Zarrit'ap'i",
    "gn:country_code":"AM",
    "gn:dem":1588,
    "gn:feature_class":"P",
    "gn:feature_code":"PPL",
    "gn:name":"Zarrit\u2019ap\u2019i",
    "gn:population":0,
    "gn:timezone":"Asia/Yerevan",
    "iso:country":"AM",
    "name:hye_x_preferred":[
        "Zarrit\u2019ap\u2019i"
    ],
    "name:hye_x_variant":[
        "\u0536\u0561\u057c\u056b\u0569\u0561\u0583\u056b"
    ],
    "wof:name":"Zarrit'ap'i",
    "wof:placetype":"locality"
},
  "geometry": {"coordinates":[45.52796,39.65833],"type":"Point"}
}