{
  "type": "Feature",
  "properties": {
    "gn:admin1_code":"6.0",
    "gn:asciiname":"Khach'idurr",
    "gn:country_code":"AM",
    "gn:dem":1783,
    "gn:feature_class":"P",
    "gn:feature_code":"PPL",
    "gn:name":"Khach\u2019idurr",
    "gn:population":0,
    "gn:timezone":"Asia/Yerevan",
    "iso:country":"AM",
    "name:hye_x_preferred":[
        "Khach\u2019idurr"
    ],
    "name:hye_x_variant":[
        "\u053d\u0561\u0579\u056b\u0564\u0578\u0582\u057c"
    ],
    "wof:name":"Khach'idurr",
    "wof:placetype":"locality"
},
  "geometry": {"coordinates":[44.75848,41.05829],"type":"Point"}
}