{
  "type": "Feature",
  "properties": {
    "gn:admin1_code":"2.0",
    "gn:asciiname":"Jermatun",
    "gn:country_code":"AM",
    "gn:dem":2216,
    "gn:feature_class":"P",
    "gn:feature_code":"PPL",
    "gn:name":"Jermatun",
    "gn:population":0,
    "gn:timezone":"Asia/Yerevan",
    "iso:country":"AM",
    "name:hye_x_preferred":[
        "Jermatun"
    ],
    "name:hye_x_variant":[
        "\u054b\u0565\u0580\u0574\u0561\u057f\u0578\u0582\u0576"
    ],
    "wof:name":"Jermatun",
    "wof:placetype":"locality"
},
  "geometry": {"coordinates":[45.01947,40.03332],"type":"Point"}
}