{
  "type": "Feature",
  "properties": {
    "gn:admin1_code":"09",
    "gn:asciiname":"Tandzut",
    "gn:country_code":"AM",
    "gn:dem":1625,
    "gn:feature_class":"P",
    "gn:feature_code":"PPL",
    "gn:name":"Tandzut",
    "gn:population":0,
    "gn:timezone":"Asia/Yerevan",
    "iso:country":"AM",
    "name:fas_x_preferred":[
        "\u062a\u0627\u0646\u062f\u0632\u0648\u062a"
    ],
    "wof:name":"Tandzut",
    "wof:placetype":"locality"
},
  "geometry": {"coordinates":[44.96667,40.86667],"type":"Point"}
}