{
  "type": "Feature",
  "properties": {
    "gn:admin1_code":"1.0",
    "gn:asciiname":"T'ukh Manuk",
    "gn:country_code":"AM",
    "gn:dem":1941,
    "gn:feature_class":"P",
    "gn:feature_code":"PPL",
    "gn:name":"T\u2019ukh Manuk",
    "gn:population":0,
    "gn:timezone":"Asia/Yerevan",
    "iso:country":"AM",
    "name:hye_x_preferred":[
        "T\u2019ukh Manuk"
    ],
    "name:hye_x_variant":[
        "\u0539\u0578\u0582\u056d \u0544\u0561\u0576\u0578\u0582\u056f"
    ],
    "wof:name":"T'ukh Manuk",
    "wof:placetype":"locality"
},
  "geometry": {"coordinates":[44.41809,40.58209],"type":"Point"}
}