{
  "type": "Feature",
  "properties": {
    "gn:admin1_code":"6.0",
    "gn:asciiname":"At'orrik",
    "gn:country_code":"AM",
    "gn:dem":941,
    "gn:feature_class":"P",
    "gn:feature_code":"PPL",
    "gn:name":"At\u2019orrik",
    "gn:population":0,
    "gn:timezone":"Asia/Yerevan",
    "iso:country":"AM",
    "name:hye_x_preferred":[
        "At\u2019orrik"
    ],
    "name:hye_x_variant":[
        "\u0531\u0569\u0578\u057c\u056b\u056f"
    ],
    "wof:name":"At'orrik",
    "wof:placetype":"locality"
},
  "geometry": {"coordinates":[44.6875,41.08472],"type":"Point"}
}