{
  "type": "Feature",
  "properties": {
    "gn:admin1_code":"8.0",
    "gn:asciiname":"Maragyugh",
    "gn:country_code":"AM",
    "gn:dem":1351,
    "gn:feature_class":"P",
    "gn:feature_code":"PPL",
    "gn:name":"Maragyugh",
    "gn:population":0,
    "gn:timezone":"Asia/Yerevan",
    "iso:country":"AM",
    "name:hye_x_preferred":[
        "Maragyugh"
    ],
    "name:hye_x_variant":[
        "\u0544\u0561\u0580\u0561\u0563\u0575\u0578\u0582\u0572"
    ],
    "wof:name":"Maragyugh",
    "wof:placetype":"locality"
},
  "geometry": {"coordinates":[46.18048,38.94873],"type":"Point"}
}