{
  "type": "Feature",
  "properties": {
    "gn:admin1_code":"02",
    "gn:asciiname":"Dastakert",
    "gn:country_code":"AM",
    "gn:dem":2551,
    "gn:feature_class":"P",
    "gn:feature_code":"PPL",
    "gn:name":"Dastakert",
    "gn:population":0,
    "gn:timezone":"Asia/Yerevan",
    "iso:country":"AM",
    "name:hye_x_preferred":[
        "Dastakert"
    ],
    "name:hye_x_variant":[
        "\u0534\u0561\u057d\u057f\u0561\u056f\u0565\u0580\u057f - 1"
    ],
    "wof:name":"Dastakert",
    "wof:placetype":"locality"
},
  "geometry": {"coordinates":[45.08472,39.9903],"type":"Point"}
}