{
  "type": "Feature",
  "properties": {
    "gn:admin1_code":"02",
    "gn:asciiname":"Dastakert",
    "gn:country_code":"AM",
    "gn:dem":2551,
    "gn:feature_class":"P",
    "gn:feature_code":"PPL",
    "gn:name":"Dastakert",
    "gn:population":0,
    "gn:timezone":"Asia/Yerevan",
    "iso:country":"AM",
    "name:ara_x_preferred":[
        "\u062f\u0627\u0633\u062a\u0627\u0643\u0631\u062a"
    ],
    "name:azb_x_preferred":[
        "\u062f\u0627\u0633\u062a\u0627\u06a9\u0631\u062a"
    ],
    "name:aze_x_preferred":[
        "D\u0259st\u0259gird"
    ],
    "name:bel_x_preferred":[
        "\u0414\u0430\u0441\u0442\u0430\u043a\u0435\u0440\u0442"
    ],
    "name:bul_x_preferred":[
        "\u0414\u0430\u0441\u0442\u0430\u043a\u0435\u0440\u0442"
    ],
    "name:che_x_preferred":[
        "\u0414\u0430\u0441\u0442\u0430\u043a\u0435\u0440\u0442"
    ],
    "name:deu_x_preferred":[
        "Dastakert"
    ],
    "name:ell_x_preferred":[
        "\u039d\u03c4\u03b1\u03c3\u03c4\u03b1\u03ba\u03ad\u03c1\u03c4"
    ],
    "name:epo_x_preferred":[
        "Dastakert"
    ],
    "name:fas_x_preferred":[
        "\u062f\u0627\u0633\u062a\u0627\u06a9\u0631\u062a"
    ],
    "name:fra_x_preferred":[
        "Dastakert"
    ],
    "name:hsb_x_preferred":[
        "Dastakert"
    ],
    "name:hye_x_preferred":[
        "Dastakert"
    ],
    "name:hye_x_variant":[
        "\u0534\u0561\u057d\u057f\u0561\u056f\u0565\u0580\u057f - 1",
        "\u0534\u0561\u057d\u057f\u0561\u056f\u0565\u0580\u057f"
    ],
    "name:ind_x_preferred":[
        "Dastakert"
    ],
    "name:ita_x_preferred":[
        "Dastakert"
    ],
    "name:kat_x_preferred":[
        "\u10d3\u10d0\u10e1\u10e2\u10d0\u10d9\u10d4\u10e0\u10e2\u10d8"
    ],
    "name:lit_x_preferred":[
        "Dastakertas"
    ],
    "name:msa_x_preferred":[
        "Dastakert"
    ],
    "name:mzn_x_preferred":[
        "\u062f\u0627\u0633\u062a\u0627\u06a9\u0631\u062a"
    ],
    "name:nld_x_preferred":[
        "Dastakert"
    ],
    "name:pol_x_preferred":[
        "Dastakert"
    ],
    "name:ron_x_preferred":[
        "Dastakert"
    ],
    "name:rus_x_preferred":[
        "\u0414\u0430\u0441\u0442\u0430\u043a\u0435\u0440\u0442"
    ],
    "name:sco_x_preferred":[
        "Dastakert"
    ],
    "name:spa_x_preferred":[
        "Dastakert"
    ],
    "name:srp_x_preferred":[
        "\u0414\u0430\u0441\u0442\u0430\u043a\u0435\u0440\u0442"
    ],
    "name:swa_x_preferred":[
        "Dastakert"
    ],
    "name:ukr_x_preferred":[
        "\u0414\u0430\u0441\u0442\u0430\u043a\u0435\u0440\u0442"
    ],
    "name:vie_x_preferred":[
        "Dastakert"
    ],
    "name:zho_x_preferred":[
        "\u9054\u65af\u5854\u51f1\u7279"
    ],
    "wof:name":"Dastakert",
    "wof:placetype":"locality"
},
  "geometry": {"coordinates":[45.08472,39.9903],"type":"Point"}
}