{
  "type": "Feature",
  "properties": {
    "gn:admin1_code":"1.0",
    "gn:asciiname":"Tonoyi",
    "gn:country_code":"AM",
    "gn:dem":1309,
    "gn:feature_class":"P",
    "gn:feature_code":"PPL",
    "gn:name":"Tonoyi",
    "gn:population":0,
    "gn:timezone":"Asia/Yerevan",
    "iso:country":"AM",
    "name:hye_x_preferred":[
        "Tonoyi"
    ],
    "name:hye_x_variant":[
        "\u054f\u0578\u0576\u0578\u0575\u056b"
    ],
    "wof:name":"Tonoyi",
    "wof:placetype":"locality"
},
  "geometry": {"coordinates":[43.99872,40.2959],"type":"Point"}
}