{
  "type": "Feature",
  "properties": {
    "gn:admin1_code":"4.0",
    "gn:asciiname":"Vernaberd",
    "gn:country_code":"AM",
    "gn:dem":2094,
    "gn:feature_class":"P",
    "gn:feature_code":"PPL",
    "gn:name":"Vernaberd",
    "gn:population":0,
    "gn:timezone":"Asia/Yerevan",
    "iso:country":"AM",
    "name:hye_x_preferred":[
        "Vernaberd"
    ],
    "name:hye_x_variant":[
        "\u054e\u0565\u0580\u0576\u0561\u0562\u0565\u0580\u0564"
    ],
    "wof:name":"Vernaberd",
    "wof:placetype":"locality"
},
  "geometry": {"coordinates":[45.22229,40.71393],"type":"Point"}
}