{
  "type": "Feature",
  "properties": {
    "iso:country":"AM",
    "qs:gn_pop":0,
    "qs:name":"Martuni Shrjan",
    "qs:name_adm0":"Armenia",
    "qs:name_adm1":"Geghark'unik'",
    "qs:photos":65,
    "qs:photos_1k":13,
    "qs:photos_9k":1,
    "qs:photos_9r":2,
    "qs:photos_all":65,
    "qs:photos_sr":2,
    "qs:placetype":"County",
    "qs:pop_sr":"0",
    "qs:woe_adm0":23424743,
    "wof:name":"Martuni Shrjan",
    "wof:placetype":"county"
},
  "geometry": {"coordinates":[45.243072,39.981855],"type":"Point"}
}