{
  "type": "Feature",
  "properties": {
    "iso:country":"AM",
    "label:eng_x_preferred_longname":[
        "Martuni Shrjan"
    ],
    "label:eng_x_preferred_placetype":[
        "shrjan"
    ],
    "name:aze_x_preferred":[
        "Martuni"
    ],
    "name:ceb_x_preferred":[
        "Martuni"
    ],
    "name:deu_x_preferred":[
        "Martuni"
    ],
    "name:eng_x_preferred":[
        "Martuni"
    ],
    "name:eng_x_variant":[
        "Martuni Shrjan"
    ],
    "name:fra_x_preferred":[
        "Martouni"
    ],
    "name:hsb_x_preferred":[
        "Martuni"
    ],
    "name:hye_x_preferred":[
        "\u0544\u0561\u0580\u057f\u0578\u0582\u0576\u056b"
    ],
    "name:ita_x_preferred":[
        "Martuni"
    ],
    "name:kat_x_preferred":[
        "\u10db\u10d0\u10e0\u10e2\u10e3\u10dc\u10d8"
    ],
    "name:rus_x_preferred":[
        "\u041c\u0430\u0440\u0442\u0443\u043d\u0438"
    ],
    "name:srp_x_preferred":[
        "\u041c\u0430\u0440\u0442\u0443\u043d\u0438"
    ],
    "name:swe_x_preferred":[
        "Martuni"
    ],
    "name:ukr_x_preferred":[
        "\u041c\u0430\u0440\u0442\u0443\u043d\u0456"
    ],
    "qs:gn_pop":0,
    "qs:name":"Martuni Shrjan",
    "qs:name_adm0":"Armenia",
    "qs:name_adm1":"Geghark'unik'",
    "qs:photos":65,
    "qs:photos_1k":13,
    "qs:photos_9k":1,
    "qs:photos_9r":2,
    "qs:photos_all":65,
    "qs:photos_sr":2,
    "qs:placetype":"County",
    "qs:pop_sr":"0",
    "qs:woe_adm0":23424743,
    "wof:name":"Martuni",
    "wof:placetype":"county",
    "wof:placetype_local":"shrjan"
},
  "geometry": {"coordinates":[45.243072,39.981855],"type":"Point"}
}