{
  "type": "Feature",
  "properties": {
    "gn:admin1_code":"7.0",
    "gn:asciiname":"Abrahami",
    "gn:country_code":"AM",
    "gn:dem":1624,
    "gn:feature_class":"P",
    "gn:feature_code":"PPL",
    "gn:name":"Abrahami",
    "gn:population":0,
    "gn:timezone":"Asia/Yerevan",
    "iso:country":"AM",
    "name:hye_x_preferred":[
        "Abrahami"
    ],
    "name:hye_x_variant":[
        "\u0531\u0562\u0580\u0561\u0570\u0561\u0574\u056b"
    ],
    "wof:name":"Abrahami",
    "wof:placetype":"locality"
},
  "geometry": {"coordinates":[43.97089,40.71393],"type":"Point"}
}