{
  "type": "Feature",
  "properties": {
    "gn:admin1_code":"4.0",
    "gn:asciiname":"K'och'at'agh",
    "gn:country_code":"AM",
    "gn:dem":1956,
    "gn:feature_class":"P",
    "gn:feature_code":"PPL",
    "gn:name":"K\u2019och\u2019at\u2019agh",
    "gn:population":0,
    "gn:timezone":"Asia/Yerevan",
    "iso:country":"AM",
    "name:hye_x_preferred":[
        "K\u2019och\u2019at\u2019agh"
    ],
    "name:hye_x_variant":[
        "\u0554\u0578\u0579\u0561\u0569\u0561\u0572"
    ],
    "wof:name":"K'och'at'agh",
    "wof:placetype":"locality"
},
  "geometry": {"coordinates":[45.19733,40.70569],"type":"Point"}
}