{
  "type": "Feature",
  "properties": {
    "gn:admin1_code":"4.0",
    "gn:asciiname":"Shlorabak",
    "gn:country_code":"AM",
    "gn:dem":1945,
    "gn:feature_class":"P",
    "gn:feature_code":"PPL",
    "gn:name":"Shlorabak",
    "gn:population":0,
    "gn:timezone":"Asia/Yerevan",
    "iso:country":"AM",
    "name:hye_x_preferred":[
        "Shlorabak"
    ],
    "name:hye_x_variant":[
        "\u0547\u056c\u0578\u0580\u0561\u0562\u0561\u056f"
    ],
    "wof:name":"Shlorabak",
    "wof:placetype":"locality"
},
  "geometry": {"coordinates":[45.23889000000001,40.6557],"type":"Point"}
}