{
  "type": "Feature",
  "properties": {
    "gn:admin1_code":"09",
    "gn:asciiname":"Isharandi",
    "gn:country_code":"AM",
    "gn:dem":1249,
    "gn:feature_class":"P",
    "gn:feature_code":"PPL",
    "gn:name":"Isharandi",
    "gn:population":0,
    "gn:timezone":"Asia/Yerevan",
    "iso:country":"AM",
    "wof:name":"Isharandi",
    "wof:placetype":"locality"
},
  "geometry": {"coordinates":[45.07713,40.91198],"type":"Point"}
}