{
  "type": "Feature",
  "properties": {
    "gn:admin1_code":"6.0",
    "gn:asciiname":"Kapuyt",
    "gn:country_code":"AM",
    "gn:dem":2267,
    "gn:feature_class":"P",
    "gn:feature_code":"PPL",
    "gn:name":"Kapuyt",
    "gn:population":0,
    "gn:timezone":"Asia/Yerevan",
    "iso:country":"AM",
    "name:hye_x_preferred":[
        "Kapuyt"
    ],
    "name:hye_x_variant":[
        "\u053f\u0561\u057a\u0578\u0582\u0575\u057f"
    ],
    "wof:name":"Kapuyt",
    "wof:placetype":"locality"
},
  "geometry": {"coordinates":[44.65692,40.80011],"type":"Point"}
}