{
  "type": "Feature",
  "properties": {
    "gn:admin1_code":"6.0",
    "gn:asciiname":"Kapuyt",
    "gn:country_code":"AM",
    "gn:dem":2267,
    "gn:feature_class":"P",
    "gn:feature_code":"PPL",
    "gn:name":"Kapuyt",
    "gn:population":0,
    "gn:timezone":"Asia/Yerevan",
    "iso:country":"AM",
    "name:aze_x_preferred":[
        "Gabud"
    ],
    "name:fas_x_preferred":[
        "\u06a9\u0627\u067e\u0648\u06cc\u062a"
    ],
    "name:hye_x_preferred":[
        "Kapuyt"
    ],
    "name:hye_x_variant":[
        "\u053f\u0561\u057a\u0578\u0582\u0575\u057f"
    ],
    "name:kat_x_preferred":[
        "\u10d9\u10d0\u10de\u10e3\u10d8\u10e2\u10d8"
    ],
    "name:sco_x_preferred":[
        "Kapuyt"
    ],
    "name:spa_x_preferred":[
        "Kapuyt"
    ],
    "wof:name":"Kapuyt",
    "wof:placetype":"locality"
},
  "geometry": {"coordinates":[44.65692,40.80011],"type":"Point"}
}