{
  "type": "Feature",
  "properties": {
    "gn:admin1_code":"04",
    "gn:asciiname":"Asoyi",
    "gn:country_code":"AM",
    "gn:dem":2711,
    "gn:feature_class":"P",
    "gn:feature_code":"PPL",
    "gn:name":"Asoyi",
    "gn:population":0,
    "gn:timezone":"Asia/Yerevan",
    "iso:country":"AM",
    "name:hye_x_preferred":[
        "Asoyi"
    ],
    "name:hye_x_variant":[
        "\u0531\u057d\u0578\u0575\u056b"
    ],
    "wof:name":"Asoyi",
    "wof:placetype":"locality"
},
  "geometry": {"coordinates":[45.41107,40.05292],"type":"Point"}
}