{
  "type": "Feature",
  "properties": {
    "iso:country":"AM",
    "name:arm_x_preferred":[
        "\u054d\u0587\u0561\u0576"
    ],
    "name:aze_x_preferred":[
        "Yelenovka"
    ],
    "name:bel_x_preferred":[
        "\u0413\u043e\u0440\u0430\u0434 \u0421\u0435\u0432\u0430\u043d"
    ],
    "name:bul_x_preferred":[
        "\u0421\u0435\u0432\u0430\u043d"
    ],
    "name:cat_x_preferred":[
        "Sevan"
    ],
    "name:ceb_x_preferred":[
        "Sevan"
    ],
    "name:ces_x_preferred":[
        "Sevan"
    ],
    "name:che_x_preferred":[
        "\u0421\u0435\u0432\u0430\u043d"
    ],
    "name:chi_x_preferred":[
        "\u585e\u51e1"
    ],
    "name:cze_x_preferred":[
        "Sevan"
    ],
    "name:deu_x_preferred":[
        "Sewan"
    ],
    "name:dut_x_preferred":[
        "Sevan"
    ],
    "name:eng_x_preferred":[
        "Sevan"
    ],
    "name:epo_x_preferred":[
        "Sevan"
    ],
    "name:est_x_preferred":[
        "Sevan"
    ],
    "name:fas_x_preferred":[
        "\u0633\u0648\u0627\u0646"
    ],
    "name:fin_x_preferred":[
        "Sevan"
    ],
    "name:fra_x_preferred":[
        "Sevan"
    ],
    "name:fre_x_preferred":[
        "Sevan"
    ],
    "name:geo_x_preferred":[
        "\u10e1\u10d4\u10d5\u10d0\u10dc\u10d8"
    ],
    "name:ger_x_preferred":[
        "Sewan"
    ],
    "name:hye_x_preferred":[
        "\u054d\u0587\u0561\u0576"
    ],
    "name:ind_x_preferred":[
        "Sevan"
    ],
    "name:ita_x_preferred":[
        "Sevan"
    ],
    "name:kat_x_preferred":[
        "\u10e1\u10d4\u10d5\u10d0\u10dc\u10d8"
    ],
    "name:lit_x_preferred":[
        "Sevanas"
    ],
    "name:may_x_preferred":[
        "Sevan"
    ],
    "name:msa_x_preferred":[
        "Sevan"
    ],
    "name:mzn_x_preferred":[
        "\u0633\u0648\u0627\u0646"
    ],
    "name:nan_x_preferred":[
        "Sevan"
    ],
    "name:nld_x_preferred":[
        "Sevan"
    ],
    "name:oci_x_preferred":[
        "Sevan"
    ],
    "name:per_x_preferred":[
        "\u0633\u0648\u0627\u0646"
    ],
    "name:pol_x_preferred":[
        "Sewan"
    ],
    "name:por_x_preferred":[
        "Sevan"
    ],
    "name:ron_x_preferred":[
        "Sevan"
    ],
    "name:rum_x_preferred":[
        "Sevan"
    ],
    "name:rus_x_preferred":[
        "\u0421\u0435\u0432\u0430\u043d"
    ],
    "name:sco_x_preferred":[
        "Sevan"
    ],
    "name:spa_x_preferred":[
        "Sevan"
    ],
    "name:srp_x_preferred":[
        "\u0421\u0435\u0432\u0430\u043d"
    ],
    "name:swe_x_preferred":[
        "Sevan"
    ],
    "name:tam_x_preferred":[
        "\u0b9a\u0bc6\u0bb5\u0bbe\u0ba9\u0bcd"
    ],
    "name:tur_x_preferred":[
        "Sevan"
    ],
    "name:ukr_x_preferred":[
        "\u0421\u0435\u0432\u0430\u043d"
    ],
    "name:unk_x_variant":[
        "Yelenovka"
    ],
    "name:zho_min_nan_x_preferred":[
        "Sevan"
    ],
    "name:zho_x_preferred":[
        "\u585e\u51e1"
    ],
    "qs:gn_country":"AM",
    "qs:gn_fcode":"PPL",
    "qs:gn_pop":17083,
    "qs:name":"Sevan",
    "qs:name_adm0":"Armenia",
    "qs:name_adm1":"Geghark'unik'",
    "qs:photos":866,
    "qs:photos_1k":175,
    "qs:photos_9k":4,
    "qs:photos_9r":6,
    "qs:photos_all":866,
    "qs:photos_sr":10,
    "qs:placetype":"Town",
    "qs:pop_sr":"6",
    "qs:woe_adm0":23424743,
    "wd:wordcount":1131,
    "wof:name":"Sevan",
    "wof:placetype":"locality",
    "wof:population":17083
},
  "geometry": {"coordinates":[44.94868,40.5484],"type":"Point"}
}