{
  "type": "Feature",
  "properties": {
    "gn:admin1_code":"4.0",
    "gn:asciiname":"Lerrnants'k'i Averakner",
    "gn:country_code":"AM",
    "gn:dem":2327,
    "gn:feature_class":"P",
    "gn:feature_code":"PPL",
    "gn:name":"Lerrnants\u2019k\u2019i Averakner",
    "gn:population":0,
    "gn:timezone":"Asia/Yerevan",
    "iso:country":"AM",
    "name:hye_x_preferred":[
        "Lerrnants\u2019k\u2019i Averakner"
    ],
    "name:hye_x_variant":[
        "\u053c\u0565\u057c\u0576\u0561\u0576\u0581\u0584\u056b \u0531\u057e\u0565\u0580\u0531\u056f\u0576\u0565\u0580"
    ],
    "wof:name":"Lerrnants'k'i Averakner",
    "wof:placetype":"locality"
},
  "geometry": {"coordinates":[45.44873,40.07233],"type":"Point"}
}