{
  "type": "Feature",
  "properties": {
    "gn:admin1_code":"6.0",
    "gn:asciiname":"Lalvar",
    "gn:country_code":"AM",
    "gn:dem":2112,
    "gn:feature_class":"P",
    "gn:feature_code":"PPL",
    "gn:name":"Lalvar",
    "gn:population":0,
    "gn:timezone":"Asia/Yerevan",
    "iso:country":"AM",
    "name:hye_x_preferred":[
        "Lalvar"
    ],
    "name:hye_x_variant":[
        "\u053c\u0561\u056c\u057e\u0561\u0580"
    ],
    "wof:name":"Lalvar",
    "wof:placetype":"locality"
},
  "geometry": {"coordinates":[44.58069,41.14313],"type":"Point"}
}