{
  "type": "Feature",
  "properties": {
    "gn:admin1_code":"4.0",
    "gn:asciiname":"Aghak'ari",
    "gn:country_code":"AM",
    "gn:dem":2075,
    "gn:feature_class":"P",
    "gn:feature_code":"PPL",
    "gn:name":"Aghak\u2019ari",
    "gn:population":0,
    "gn:timezone":"Asia/Yerevan",
    "iso:country":"AM",
    "name:hye_x_preferred":[
        "Aghak\u2019ari"
    ],
    "name:hye_x_variant":[
        "\u0531\u0572\u0561\u0584\u0561\u0580\u056b"
    ],
    "wof:name":"Aghak'ari",
    "wof:placetype":"locality"
},
  "geometry": {"coordinates":[45.31671,40.51392],"type":"Point"}
}