{
  "type": "Feature",
  "properties": {
    "gn:admin1_code":"1.0",
    "gn:asciiname":"Sharrl Aznavuri",
    "gn:country_code":"AM",
    "gn:dem":1878,
    "gn:feature_class":"P",
    "gn:feature_code":"PPL",
    "gn:name":"Sharrl Aznavuri",
    "gn:population":0,
    "gn:timezone":"Asia/Yerevan",
    "iso:country":"AM",
    "name:hye_x_preferred":[
        "Sharrl Aznavuri"
    ],
    "name:hye_x_variant":[
        "\u0547\u0561\u057c\u056c \u0531\u0566\u0576\u0561\u057e\u0578\u0582\u0580\u056b"
    ],
    "wof:name":"Sharrl Aznavuri",
    "wof:placetype":"locality"
},
  "geometry": {"coordinates":[44.40149,40.4779],"type":"Point"}
}