{
  "type": "Feature",
  "properties": {
    "gn:admin1_code":"8.0",
    "gn:asciiname":"Kotrats Ekeghets'i",
    "gn:country_code":"AM",
    "gn:dem":1168,
    "gn:feature_class":"P",
    "gn:feature_code":"PPL",
    "gn:name":"Kotrats Ekeghets\u2019i",
    "gn:population":0,
    "gn:timezone":"Asia/Yerevan",
    "iso:country":"AM",
    "name:hye_x_preferred":[
        "Kotrats Ekeghets\u2019i"
    ],
    "name:hye_x_variant":[
        "\u053f\u0578\u057f\u0580\u0561\u056e \u0565\u056f\u0565\u0572\u0565\u0581\u056b"
    ],
    "wof:name":"Kotrats Ekeghets'i",
    "wof:placetype":"locality"
},
  "geometry": {"coordinates":[46.35828,39.26947],"type":"Point"}
}