{
  "type": "Feature",
  "properties": {
    "gn:admin1_code":"6.0",
    "gn:asciiname":"Shnogh",
    "gn:country_code":"AM",
    "gn:dem":2265,
    "gn:feature_class":"P",
    "gn:feature_code":"PPL",
    "gn:name":"Shnogh",
    "gn:population":0,
    "gn:timezone":"Asia/Yerevan",
    "iso:country":"AM",
    "name:hye_x_preferred":[
        "Shnogh"
    ],
    "name:hye_x_variant":[
        "\u0547\u0576\u0578\u0572"
    ],
    "wof:name":"Shnogh",
    "wof:placetype":"locality"
},
  "geometry": {"coordinates":[44.83209,40.84168],"type":"Point"}
}