{
  "type": "Feature",
  "properties": {
    "gn:admin1_code":"6.0",
    "gn:asciiname":"Shnogh",
    "gn:country_code":"AM",
    "gn:dem":2265,
    "gn:feature_class":"P",
    "gn:feature_code":"PPL",
    "gn:name":"Shnogh",
    "gn:population":0,
    "gn:timezone":"Asia/Yerevan",
    "iso:country":"AM",
    "name:aze_x_preferred":[
        "\u015e\u0131n\u0131x"
    ],
    "name:ceb_x_preferred":[
        "Shnogh"
    ],
    "name:fas_x_preferred":[
        "\u0634\u0646\u0648\u063a"
    ],
    "name:fra_x_preferred":[
        "Shnogh"
    ],
    "name:hye_x_preferred":[
        "Shnogh"
    ],
    "name:hye_x_variant":[
        "\u0547\u0576\u0578\u0572"
    ],
    "name:ita_x_preferred":[
        "Shnogh"
    ],
    "name:kat_x_preferred":[
        "\u10e8\u10dc\u10dd\u10e6\u10d8"
    ],
    "name:msa_x_preferred":[
        "Shnogh"
    ],
    "name:rus_x_preferred":[
        "\u0428\u043d\u043e\u0445"
    ],
    "name:spa_x_preferred":[
        "Shnogh"
    ],
    "name:swe_x_preferred":[
        "Shnogh"
    ],
    "name:vie_x_preferred":[
        "Shnogh"
    ],
    "wof:name":"Shnogh",
    "wof:placetype":"locality"
},
  "geometry": {"coordinates":[44.83209,40.84168],"type":"Point"}
}