{
  "type": "Feature",
  "properties": {
    "iso:country":"AM",
    "name:aze_x_preferred":[
        "C\u0259f\u0259rabad"
    ],
    "name:che_x_preferred":[
        "\u0413\u0435\u0442\u0430\u0448\u0435\u043d"
    ],
    "name:ell_x_preferred":[
        "\u0393\u03ba\u03b5\u03c4\u03b1\u03c3\u03ad\u03bd"
    ],
    "name:eng_x_preferred":[
        "Getashen"
    ],
    "name:fas_x_preferred":[
        "\u06af\u062a\u0627\u0634\u0646"
    ],
    "name:fra_x_preferred":[
        "Getashen"
    ],
    "name:hye_x_preferred":[
        "\u0533\u0565\u057f\u0561\u0577\u0565\u0576"
    ],
    "name:ita_x_preferred":[
        "Getashen"
    ],
    "name:kat_x_preferred":[
        "\u10d2\u10d4\u10e2\u10d0\u10e8\u10d4\u10dc\u10d8"
    ],
    "name:msa_x_preferred":[
        "Getashen"
    ],
    "name:nan_x_preferred":[
        "Getashen"
    ],
    "name:nld_x_preferred":[
        "Getashen"
    ],
    "name:pol_x_preferred":[
        "Getaszen"
    ],
    "name:rus_x_preferred":[
        "\u0413\u0435\u0442\u0430\u0448\u0435\u043d"
    ],
    "name:sco_x_preferred":[
        "Getashen"
    ],
    "name:spa_x_preferred":[
        "Getashen"
    ],
    "name:swe_x_preferred":[
        "Getasjen"
    ],
    "name:ukr_x_preferred":[
        "\u0490\u0435\u0442\u0430\u0448\u0435\u043d"
    ],
    "name:und_x_variant":[
        "Kalagar"
    ],
    "name:uzb_x_preferred":[
        "Getashen"
    ],
    "name:vie_x_preferred":[
        "Getashen"
    ],
    "name:zho_min_nan_x_preferred":[
        "Getashen"
    ],
    "qs:gn_country":"AM",
    "qs:gn_fcode":"PPL",
    "qs:gn_pop":2114,
    "qs:name":"Getashen",
    "qs:name_adm0":"Armenia",
    "qs:name_adm1":"Armavir",
    "qs:photos":0,
    "qs:photos_1k":0,
    "qs:photos_9k":0,
    "qs:photos_9r":0,
    "qs:photos_all":0,
    "qs:photos_sr":0,
    "qs:placetype":"Town",
    "qs:pop_sr":"4",
    "qs:woe_adm0":23424743,
    "wd:wordcount":107,
    "wof:name":"Getashen",
    "wof:placetype":"locality",
    "wof:population":2114
},
  "geometry": {"coordinates":[43.94203,40.04405],"type":"Point"}
}