{
  "type": "Feature",
  "properties": {
    "gn:admin1_code":"1.0",
    "gn:asciiname":"Goghkut'en",
    "gn:country_code":"AM",
    "gn:dem":1298,
    "gn:feature_class":"P",
    "gn:feature_code":"PPL",
    "gn:name":"Goghkut\u2019en",
    "gn:population":0,
    "gn:timezone":"Asia/Yerevan",
    "iso:country":"AM",
    "name:hye_x_preferred":[
        "Goghkut\u2019en"
    ],
    "name:hye_x_variant":[
        "\u0533\u0578\u0572\u056f\u0578\u0582\u0569\u0565\u0576"
    ],
    "wof:name":"Goghkut'en",
    "wof:placetype":"locality"
},
  "geometry": {"coordinates":[44.2279,40.3125],"type":"Point"}
}