{
  "type": "Feature",
  "properties": {
    "gn:admin1_code":"4.0",
    "gn:asciiname":"Gomeri Zham",
    "gn:country_code":"AM",
    "gn:dem":2304,
    "gn:feature_class":"P",
    "gn:feature_code":"PPL",
    "gn:name":"Gomeri Zham",
    "gn:population":0,
    "gn:timezone":"Asia/Yerevan",
    "iso:country":"AM",
    "name:hye_x_preferred":[
        "Gomeri Zham"
    ],
    "name:hye_x_variant":[
        "\u0533\u0578\u0574\u0565\u0580\u056b \u056a\u0561\u0574"
    ],
    "wof:name":"Gomeri Zham",
    "wof:placetype":"locality"
},
  "geometry": {"coordinates":[45.15008,40.19311],"type":"Point"}
}