{
  "type": "Feature",
  "properties": {
    "gn:admin1_code":"7.0",
    "gn:asciiname":"Khach'i Sar",
    "gn:country_code":"AM",
    "gn:dem":1667,
    "gn:feature_class":"P",
    "gn:feature_code":"PPL",
    "gn:name":"Khach\u2019i Sar",
    "gn:population":0,
    "gn:timezone":"Asia/Yerevan",
    "iso:country":"AM",
    "name:hye_x_preferred":[
        "Khach\u2019i Sar"
    ],
    "name:hye_x_variant":[
        "\u053d\u0561\u0579\u056b \u057d\u0561\u0580"
    ],
    "wof:name":"Khach'i Sar",
    "wof:placetype":"locality"
},
  "geometry": {"coordinates":[43.89313,40.84729],"type":"Point"}
}