{
  "type": "Feature",
  "properties": {
    "gn:admin1_code":"08",
    "gn:asciiname":"Sukhan",
    "gn:country_code":"AM",
    "gn:dem":1538,
    "gn:feature_class":"P",
    "gn:feature_code":"PPL",
    "gn:name":"Sukhan",
    "gn:population":0,
    "gn:timezone":"Asia/Yerevan",
    "iso:country":"AM",
    "name:hye_x_preferred":[
        "Sukhan"
    ],
    "name:hye_x_variant":[
        "\u054d\u0578\u0582\u056d\u0561\u0576"
    ],
    "wof:name":"Sukhan",
    "wof:placetype":"locality"
},
  "geometry": {"coordinates":[46.20569,39.2279],"type":"Point"}
}