{
  "type": "Feature",
  "properties": {
    "gn:admin1_code":"04",
    "gn:asciiname":"Kat'an",
    "gn:country_code":"AM",
    "gn:dem":2170,
    "gn:feature_class":"P",
    "gn:feature_code":"PPL",
    "gn:name":"Kat\u2019an",
    "gn:population":0,
    "gn:timezone":"Asia/Yerevan",
    "iso:country":"AM",
    "name:hye_x_preferred":[
        "Kat\u2019an"
    ],
    "name:hye_x_variant":[
        "\u053f\u0561\u0569\u0561\u0576"
    ],
    "wof:name":"Kat'an",
    "wof:placetype":"locality"
},
  "geometry": {"coordinates":[45.2959,40.07928],"type":"Point"}
}