{
  "type": "Feature",
  "properties": {
    "gn:admin1_code":"11.0",
    "gn:asciiname":"Khaldi",
    "gn:country_code":"AM",
    "gn:dem":1029,
    "gn:feature_class":"P",
    "gn:feature_code":"PPL",
    "gn:name":"Khaldi",
    "gn:population":0,
    "gn:timezone":"Asia/Yerevan",
    "iso:country":"AM",
    "name:hye_x_preferred":[
        "Khaldi"
    ],
    "name:hye_x_variant":[
        "\u053d\u0561\u056c\u0564\u056b"
    ],
    "name:rus_x_preferred":[
        "\u0425\u0430\u043b\u0434\u0438"
    ],
    "wof:name":"Khaldi",
    "wof:placetype":"locality"
},
  "geometry": {"coordinates":[44.53888,40.14172],"type":"Point"}
}