{
  "type": "Feature",
  "properties": {
    "gn:admin1_code":"6.0",
    "gn:asciiname":"Patvar Dambaranadasht",
    "gn:country_code":"AM",
    "gn:dem":1395,
    "gn:feature_class":"P",
    "gn:feature_code":"PPL",
    "gn:name":"Patvar Dambaranadasht",
    "gn:population":0,
    "gn:timezone":"Asia/Yerevan",
    "iso:country":"AM",
    "name:hye_x_preferred":[
        "Patvar Dambaranadasht"
    ],
    "name:hye_x_variant":[
        "\u054a\u0561\u057f\u057e\u0561\u0580 \u0564\u0561\u0574\u0562\u0561\u0580\u0561\u0576\u0561\u0564\u0561\u0577\u057f"
    ],
    "wof:name":"Patvar Dambaranadasht",
    "wof:placetype":"locality"
},
  "geometry": {"coordinates":[44.73328,41.13751],"type":"Point"}
}