{
  "type": "Feature",
  "properties": {
    "gn:admin1_code":"03",
    "gn:asciiname":"Jrarrat",
    "gn:country_code":"AM",
    "gn:dem":840,
    "gn:feature_class":"P",
    "gn:feature_code":"PPL",
    "gn:name":"Jrarrat",
    "gn:population":0,
    "gn:timezone":"Asia/Yerevan",
    "iso:country":"AM",
    "name:fas_x_preferred":[
        "\u062c\u0631\u0627\u0631\u0627\u062a"
    ],
    "name:fra_x_preferred":[
        "Jrarat"
    ],
    "name:hye_x_preferred":[
        "Jrarrat"
    ],
    "name:hye_x_variant":[
        "\u054b\u0580\u0561\u057c\u0561\u057f"
    ],
    "name:ita_x_preferred":[
        "Jrarat"
    ],
    "name:kat_x_preferred":[
        "\u10ef\u10e0\u10d0\u10e0\u10d0\u10e2\u10d8"
    ],
    "name:msa_x_preferred":[
        "Jrarat"
    ],
    "name:sco_x_preferred":[
        "Jrarat"
    ],
    "name:spa_x_preferred":[
        "Jrarat"
    ],
    "name:ukr_x_preferred":[
        "\u0414\u0436\u0440\u0430\u0440\u0430\u0442"
    ],
    "name:und_x_variant":[
        "Verkhniy Karkhun",
        "Dzhrarat",
        "Verin Karkhun",
        "Karkhun"
    ],
    "name:vie_x_preferred":[
        "Jrarat"
    ],
    "wof:name":"Jrarrat",
    "wof:placetype":"locality"
},
  "geometry": {"coordinates":[44.26392,40.07233],"type":"Point"}
}