{
  "type": "Feature",
  "properties": {
    "gn:admin1_code":"03",
    "gn:asciiname":"Jrarrat",
    "gn:country_code":"AM",
    "gn:dem":840,
    "gn:feature_class":"P",
    "gn:feature_code":"PPL",
    "gn:name":"Jrarrat",
    "gn:population":0,
    "gn:timezone":"Asia/Yerevan",
    "iso:country":"AM",
    "name:hye_x_preferred":[
        "Jrarrat"
    ],
    "name:hye_x_variant":[
        "\u054b\u0580\u0561\u057c\u0561\u057f"
    ],
    "name:und_x_variant":[
        "Verkhniy Karkhun",
        "Dzhrarat",
        "Jrarat",
        "Verin Karkhun",
        "Karkhun"
    ],
    "wof:name":"Jrarrat",
    "wof:placetype":"locality"
},
  "geometry": {"coordinates":[44.26392,40.07233],"type":"Point"}
}