{
  "type": "Feature",
  "properties": {
    "gn:admin1_code":"1.0",
    "gn:asciiname":"Mankanots'",
    "gn:country_code":"AM",
    "gn:dem":1047,
    "gn:feature_class":"P",
    "gn:feature_code":"PPL",
    "gn:name":"Mankanots\u2019",
    "gn:population":0,
    "gn:timezone":"Asia/Yerevan",
    "iso:country":"AM",
    "name:hye_x_preferred":[
        "Mankanots\u2019"
    ],
    "name:hye_x_variant":[
        "\u0544\u0561\u0576\u056f\u0561\u0576\u0578\u0581"
    ],
    "wof:name":"Mankanots'",
    "wof:placetype":"locality"
},
  "geometry": {"coordinates":[44.31952,40.27228],"type":"Point"}
}