{
  "type": "Feature",
  "properties": {
    "gn:admin1_code":"2.0",
    "gn:asciiname":"T'arrnis",
    "gn:country_code":"AM",
    "gn:dem":2221,
    "gn:feature_class":"P",
    "gn:feature_code":"PPL",
    "gn:name":"T\u2019arrnis",
    "gn:population":0,
    "gn:timezone":"Asia/Yerevan",
    "iso:country":"AM",
    "name:hye_x_preferred":[
        "T\u2019arrnis"
    ],
    "name:hye_x_variant":[
        "\u0539\u0561\u057c\u0576\u056b\u057d"
    ],
    "wof:name":"T'arrnis",
    "wof:placetype":"locality"
},
  "geometry": {"coordinates":[44.90289,40.05548],"type":"Point"}
}