{
  "type": "Feature",
  "properties": {
    "gn:admin1_code":"1.0",
    "gn:asciiname":"Khach'avank'",
    "gn:country_code":"AM",
    "gn:dem":1443,
    "gn:feature_class":"P",
    "gn:feature_code":"PPL",
    "gn:name":"Khach\u2019avank\u2019",
    "gn:population":0,
    "gn:timezone":"Asia/Yerevan",
    "iso:country":"AM",
    "name:hye_x_preferred":[
        "Khach\u2019avank\u2019"
    ],
    "name:hye_x_variant":[
        "\u053d\u0561\u0579\u0561\u057e\u0561\u0576\u0584"
    ],
    "wof:name":"Khach'avank'",
    "wof:placetype":"locality"
},
  "geometry": {"coordinates":[44.27128,40.33501],"type":"Point"}
}