{
  "type": "Feature",
  "properties": {
    "gn:country":"AM",
    "gn:fcode":"PPL",
    "gn:population":18911,
    "iso:country":"AM",
    "name:aze_x_preferred":[
        "Masis"
    ],
    "name:deu_x_preferred":[
        "Masis"
    ],
    "name:eng_x_preferred":[
        "Masis"
    ],
    "name:fra_x_preferred":[
        "Massis"
    ],
    "name:hye_x_preferred":[
        "Masis"
    ],
    "name:hye_x_variant":[
        "\u0544\u0561\u057d\u056b\u057d"
    ],
    "name:ita_x_preferred":[
        "Masis"
    ],
    "name:nld_x_preferred":[
        "Masis"
    ],
    "name:rus_x_preferred":[
        "\u041c\u0430\u0441\u0438\u0441"
    ],
    "name:sco_x_preferred":[
        "Masis"
    ],
    "name:und_x_variant":[
        "Tokhanshalu"
    ],
    "name:vie_x_preferred":[
        "Masis"
    ],
    "qs:name":"Masis",
    "qs:photos_9r":0,
    "qs:photos_sr":0,
    "qs:pop_sr":"6",
    "wd:wordcount":134,
    "wof:name":"Masis",
    "wof:placetype":"locality",
    "wof:population":18911
},
  "geometry": {"coordinates":[44.43591,40.06762],"type":"Point"}
}