{
  "type": "Feature",
  "properties": {
    "gn:admin1_code":"06",
    "gn:asciiname":"Amoj",
    "gn:country_code":"AM",
    "gn:dem":1174,
    "gn:feature_class":"P",
    "gn:feature_code":"PPL",
    "gn:name":"Amoj",
    "gn:population":0,
    "gn:timezone":"Asia/Yerevan",
    "iso:country":"AM",
    "name:hye_x_preferred":[
        "Amoj"
    ],
    "name:hye_x_variant":[
        "\u0531\u0574\u0578\u057b"
    ],
    "name:und_x_variant":[
        "Amodzh"
    ],
    "wof:name":"Amoj",
    "wof:placetype":"locality"
},
  "geometry": {"coordinates":[44.59669,41.05934],"type":"Point"}
}