{
  "type": "Feature",
  "properties": {
    "iso:country":"AM",
    "name:azb_x_preferred":[
        "\u0646\u0648\u0631 \u0622\u0631\u0645\u0627\u0648\u06cc\u0631"
    ],
    "name:aze_x_preferred":[
        "Yeni Armavir"
    ],
    "name:ceb_x_preferred":[
        "Nor Armavir"
    ],
    "name:che_x_preferred":[
        "\u041d\u043e\u0440 \u0410\u0440\u043c\u0430\u0432\u0438\u0440"
    ],
    "name:ell_x_preferred":[
        "\u039d\u03bf\u03c1 \u0391\u03c1\u03bc\u03b1\u03b2\u03af\u03c1"
    ],
    "name:eng_x_preferred":[
        "Nor Armavir"
    ],
    "name:fas_x_preferred":[
        "\u0646\u0648\u0631 \u0622\u0631\u0645\u0627\u0648\u06cc\u0631"
    ],
    "name:fra_x_preferred":[
        "Nor Armavir"
    ],
    "name:hye_x_preferred":[
        "\u0546\u0578\u0580 \u0531\u0580\u0574\u0561\u057e\u056b\u0580"
    ],
    "name:ita_x_preferred":[
        "Nor Armavir"
    ],
    "name:kat_x_preferred":[
        "\u10dc\u10dd\u10e0-\u10d0\u10e0\u10db\u10d0\u10d5\u10d8\u10e0\u10d8"
    ],
    "name:msa_x_preferred":[
        "Nor Armavir"
    ],
    "name:nan_x_preferred":[
        "Nor Armavir"
    ],
    "name:nld_x_preferred":[
        "Nor Armavir"
    ],
    "name:pol_x_preferred":[
        "Nor Armawir"
    ],
    "name:rus_x_preferred":[
        "\u041d\u043e\u0440 \u0410\u0440\u043c\u0430\u0432\u0438\u0440"
    ],
    "name:rus_x_variant":[
        "\u041d\u043e\u0440-\u0410\u0440\u043c\u0430\u0432\u0438\u0440"
    ],
    "name:sco_x_preferred":[
        "Nor Armavir"
    ],
    "name:spa_x_preferred":[
        "Nor Armavir"
    ],
    "name:swe_x_preferred":[
        "Nor Armavir"
    ],
    "name:ukr_x_preferred":[
        "\u041d\u043e\u0440-\u0410\u0440\u043c\u0430\u0432\u0456\u0440"
    ],
    "name:uzb_x_preferred":[
        "Nor Armavir"
    ],
    "name:vie_x_preferred":[
        "Nor Armavir"
    ],
    "name:vie_x_variant":[
        "Echmiadzin"
    ],
    "name:zho_min_nan_x_preferred":[
        "Nor Armavir"
    ],
    "qs:gn_country":"AM",
    "qs:gn_fcode":"PPL",
    "qs:gn_pop":1597,
    "qs:name":"Nor Armavir",
    "qs:name_adm0":"Armenia",
    "qs:name_adm1":"Armavir",
    "qs:photos":0,
    "qs:photos_1k":0,
    "qs:photos_9k":1,
    "qs:photos_9r":1,
    "qs:photos_all":1,
    "qs:photos_sr":0,
    "qs:placetype":"Town",
    "qs:pop_sr":"3",
    "qs:woe_adm0":23424743,
    "wd:wordcount":144,
    "wof:name":"Nor Armavir",
    "wof:placetype":"locality",
    "wof:population":1597
},
  "geometry": {"coordinates":[43.99242,40.08563],"type":"Point"}
}