{
  "type": "Feature",
  "properties": {
    "gn:admin1_code":"5.0",
    "gn:asciiname":"Bardzradir",
    "gn:country_code":"AM",
    "gn:dem":2118,
    "gn:feature_class":"P",
    "gn:feature_code":"PPL",
    "gn:name":"Bardzradir",
    "gn:population":0,
    "gn:timezone":"Asia/Yerevan",
    "iso:country":"AM",
    "name:hye_x_preferred":[
        "Bardzradir"
    ],
    "name:hye_x_variant":[
        "\u0532\u0561\u0580\u0571\u0580\u0561\u0564\u056b\u0580"
    ],
    "wof:name":"Bardzradir",
    "wof:placetype":"locality"
},
  "geometry": {"coordinates":[44.78332,40.20831],"type":"Point"}
}