{
  "type": "Feature",
  "properties": {
    "gn:admin1_code":"9.0",
    "gn:asciiname":"Gmbet'",
    "gn:country_code":"AM",
    "gn:dem":1225,
    "gn:feature_class":"P",
    "gn:feature_code":"PPL",
    "gn:name":"Gmbet\u2019",
    "gn:population":0,
    "gn:timezone":"Asia/Yerevan",
    "iso:country":"AM",
    "name:hye_x_preferred":[
        "Gmbet\u2019"
    ],
    "name:hye_x_variant":[
        "\u0533\u0574\u0562\u0565\u0569"
    ],
    "wof:name":"Gmbet'",
    "wof:placetype":"locality"
},
  "geometry": {"coordinates":[45.13348,40.7973],"type":"Point"}
}