{
  "type": "Feature",
  "properties": {
    "iso:country":"AM",
    "name:ceb_x_preferred":[
        "Lernavan"
    ],
    "name:eng_x_preferred":[
        "Lernavan"
    ],
    "name:fas_x_preferred":[
        "\u0644\u0631\u0646\u0627\u0648\u0627\u0646"
    ],
    "name:fra_x_preferred":[
        "Lernavan"
    ],
    "name:hye_x_preferred":[
        "\u053c\u0565\u057c\u0576\u0561\u057e\u0561\u0576"
    ],
    "name:hye_x_variant":[
        "Lerrnavan"
    ],
    "name:ita_x_preferred":[
        "Lernavan"
    ],
    "name:kat_x_preferred":[
        "\u10da\u10d4\u10e0\u10dc\u10d0\u10d5\u10d0\u10dc\u10d8"
    ],
    "name:msa_x_preferred":[
        "Lernavan"
    ],
    "name:nan_x_preferred":[
        "Lernavan"
    ],
    "name:nld_x_preferred":[
        "Lernavan"
    ],
    "name:rus_x_preferred":[
        "\u041b\u0435\u0440\u043d\u0430\u0432\u0430\u043d"
    ],
    "name:spa_x_preferred":[
        "Lernavan"
    ],
    "name:swe_x_preferred":[
        "Lernavan"
    ],
    "name:unk_x_variant":[
        "Kachagan"
    ],
    "name:vie_x_preferred":[
        "Lernavan"
    ],
    "name:zho_min_nan_x_preferred":[
        "Lernavan"
    ],
    "qs:gn_country":"AM",
    "qs:gn_fcode":"PPL",
    "qs:gn_pop":1517,
    "qs:name":"Lernavan",
    "qs:name_adm0":"Armenia",
    "qs:name_adm1":"Lorri",
    "qs:photos":0,
    "qs:photos_1k":0,
    "qs:photos_9k":0,
    "qs:photos_9r":0,
    "qs:photos_all":0,
    "qs:photos_sr":0,
    "qs:placetype":"Town",
    "qs:pop_sr":"3",
    "qs:woe_adm0":23424743,
    "wd:wordcount":61,
    "wof:name":"Lernavan",
    "wof:placetype":"locality",
    "wof:population":1517
},
  "geometry": {"coordinates":[44.16024,40.7882],"type":"Point"}
}