{
  "type": "Feature",
  "properties": {
    "gn:admin1_code":"1.0",
    "gn:asciiname":"Oski Kogh",
    "gn:country_code":"AM",
    "gn:dem":2060,
    "gn:feature_class":"P",
    "gn:feature_code":"PPL",
    "gn:name":"Oski Kogh",
    "gn:population":0,
    "gn:timezone":"Asia/Yerevan",
    "iso:country":"AM",
    "name:hye_x_preferred":[
        "Oski Kogh"
    ],
    "name:hye_x_variant":[
        "\u0548\u057d\u056f\u056b \u056f\u0578\u0572"
    ],
    "wof:name":"Oski Kogh",
    "wof:placetype":"locality"
},
  "geometry": {"coordinates":[44.39868,40.6001],"type":"Point"}
}