{
  "type": "Feature",
  "properties": {
    "iso:country":"AM",
    "name:ara_x_preferred":[
        "\u063a\u064a\u063a\u0627\u0646\u064a\u0633\u062a"
    ],
    "name:aze_x_preferred":[
        "G\u00f6yk\u00fcmb\u0259t"
    ],
    "name:ceb_x_preferred":[
        "Geghanist"
    ],
    "name:che_x_preferred":[
        "\u0413\u0435\u0445\u0430\u043d\u0438\u0441\u0442"
    ],
    "name:eng_x_preferred":[
        "Geghanist"
    ],
    "name:fas_x_preferred":[
        "\u06af\u063a\u0627\u0646\u06cc\u0633\u062a\u060c \u0622\u0631\u0627\u0631\u0627\u062a"
    ],
    "name:fas_x_variant":[
        "\u06af\u063a\u0627\u0646\u06cc\u0633\u062a"
    ],
    "name:fra_x_preferred":[
        "Geghanist"
    ],
    "name:hye_x_preferred":[
        "\u0533\u0565\u0572\u0561\u0576\u056b\u057d\u057f"
    ],
    "name:hye_x_variant":[
        "Geghanist"
    ],
    "name:ita_x_preferred":[
        "Geghanist"
    ],
    "name:kat_x_preferred":[
        "\u10d2\u10d4\u10e6\u10d0\u10dc\u10d8\u10e1\u10e2\u10d8"
    ],
    "name:msa_x_preferred":[
        "Geghanist"
    ],
    "name:nan_x_preferred":[
        "Geghanist"
    ],
    "name:nld_x_preferred":[
        "Geghanist"
    ],
    "name:pol_x_preferred":[
        "Geghanist"
    ],
    "name:rus_x_preferred":[
        "\u0413\u0435\u0445\u0430\u043d\u0438\u0441\u0442"
    ],
    "name:rus_x_variant":[
        "\u0413\u0435\u0433\u0430\u043d\u0438\u0441\u0442"
    ],
    "name:sco_x_preferred":[
        "Geghanist"
    ],
    "name:spa_x_preferred":[
        "Geghanist"
    ],
    "name:swe_x_preferred":[
        "Geghanist"
    ],
    "name:ukr_x_preferred":[
        "\u0490\u0435\u0445\u0430\u043d\u0456\u0441\u0442"
    ],
    "name:und_x_variant":[
        "Gekhanist"
    ],
    "name:uzb_x_preferred":[
        "Geghanist"
    ],
    "name:vie_x_preferred":[
        "Geghanist"
    ],
    "name:zho_min_nan_x_preferred":[
        "Geghanist"
    ],
    "qs:gn_country":"AM",
    "qs:gn_fcode":"PPL",
    "qs:gn_pop":2409,
    "qs:name":"Geghanist",
    "qs:name_adm0":"Armenia",
    "qs:name_adm1":"Armavir",
    "qs:photos":227,
    "qs:photos_1k":46,
    "qs:photos_9k":1,
    "qs:photos_9r":4,
    "qs:photos_all":227,
    "qs:photos_sr":4,
    "qs:placetype":"Town",
    "qs:pop_sr":"4",
    "qs:woe_adm0":23424743,
    "wd:wordcount":68,
    "wof:name":"Geghanist",
    "wof:placetype":"locality",
    "wof:population":2409
},
  "geometry": {"coordinates":[44.43054,40.14493],"type":"Point"}
}