{
  "type": "Feature",
  "properties": {
    "gn:admin1_code":"7.0",
    "gn:asciiname":"Gorshaberd",
    "gn:country_code":"AM",
    "gn:dem":1998,
    "gn:feature_class":"P",
    "gn:feature_code":"PPL",
    "gn:name":"Gorshaberd",
    "gn:population":0,
    "gn:timezone":"Asia/Yerevan",
    "iso:country":"AM",
    "name:hye_x_preferred":[
        "Gorshaberd"
    ],
    "name:hye_x_variant":[
        "\u0533\u0578\u0580\u0577\u0561\u0562\u0565\u0580\u0564"
    ],
    "wof:name":"Gorshaberd",
    "wof:placetype":"locality"
},
  "geometry": {"coordinates":[43.77649,41.01532],"type":"Point"}
}