{
  "type": "Feature",
  "properties": {
    "gn:admin1_code":"1.0",
    "gn:asciiname":"Glkhavor",
    "gn:country_code":"AM",
    "gn:dem":1586,
    "gn:feature_class":"P",
    "gn:feature_code":"PPL",
    "gn:name":"Glkhavor",
    "gn:population":0,
    "gn:timezone":"Asia/Yerevan",
    "iso:country":"AM",
    "name:hye_x_preferred":[
        "Glkhavor"
    ],
    "name:hye_x_variant":[
        "\u0533\u056c\u056d\u0561\u057e\u0578\u0580"
    ],
    "wof:name":"Glkhavor",
    "wof:placetype":"locality"
},
  "geometry": {"coordinates":[43.78607,40.44733],"type":"Point"}
}