{
  "type": "Feature",
  "properties": {
    "gn:admin1_code":"10",
    "gn:asciiname":"Guteni",
    "gn:country_code":"AM",
    "gn:dem":2027,
    "gn:feature_class":"P",
    "gn:feature_code":"PPL",
    "gn:name":"Guteni",
    "gn:population":0,
    "gn:timezone":"Asia/Yerevan",
    "iso:country":"AM",
    "name:hye_x_preferred":[
        "Guteni"
    ],
    "name:hye_x_variant":[
        "\u0533\u0578\u0582\u057f\u0565\u0576\u056b"
    ],
    "wof:name":"Guteni",
    "wof:placetype":"locality"
},
  "geometry": {"coordinates":[45.53748,39.80548],"type":"Point"}
}