{
  "type": "Feature",
  "properties": {
    "gn:admin1_code":"04",
    "gn:asciiname":"Inakdag",
    "gn:country_code":"AM",
    "gn:dem":2107,
    "gn:feature_class":"P",
    "gn:feature_code":"PPL",
    "gn:name":"Inakdag",
    "gn:population":0,
    "gn:timezone":"Asia/Yerevan",
    "iso:country":"AM",
    "wof:name":"Inakdag",
    "wof:placetype":"locality"
},
  "geometry": {"coordinates":[45.85,40.23333],"type":"Point"}
}