{
  "type": "Feature",
  "properties": {
    "iso:country":"AM",
    "name:azb_x_preferred":[
        "\u0642\u0627\u0642\u0627\u0631\u06cc\u0646"
    ],
    "name:aze_x_preferred":[
        "Qaqarin"
    ],
    "name:ceb_x_preferred":[
        "Gagarin"
    ],
    "name:che_x_preferred":[
        "\u0413\u0430\u0433\u0430\u0440\u0438\u043d"
    ],
    "name:eng_x_preferred":[
        "Gagarin"
    ],
    "name:fas_x_preferred":[
        "\u06af\u0627\u06af\u0627\u0631\u06cc\u0646\u060c \u0627\u0631\u0645\u0646\u0633\u062a\u0627\u0646"
    ],
    "name:fas_x_variant":[
        "\u06af\u0627\u06af\u0627\u0631\u06cc\u0646"
    ],
    "name:hye_x_preferred":[
        "\u0533\u0561\u0563\u0561\u0580\u056b\u0576"
    ],
    "name:jpn_x_preferred":[
        "\u30ac\u30ac\u30fc\u30ea\u30f3"
    ],
    "name:kat_x_preferred":[
        "\u10d2\u10d0\u10d2\u10d0\u10e0\u10d8\u10dc\u10d8"
    ],
    "name:nld_x_preferred":[
        "Gagarin"
    ],
    "name:pol_x_preferred":[
        "Gagarin"
    ],
    "name:rus_x_preferred":[
        "\u0413\u0430\u0433\u0430\u0440\u0438\u043d"
    ],
    "name:spa_x_preferred":[
        "Gagarin"
    ],
    "name:swe_x_preferred":[
        "Gagarin"
    ],
    "name:ukr_x_preferred":[
        "\u0413\u0430\u0433\u0430\u0440\u0456\u043d"
    ],
    "name:uzb_x_preferred":[
        "Gagarin"
    ],
    "name:zho_x_preferred":[
        "\u52a0\u52a0\u6797 \uff08\u4e9e\u7f8e\u5c3c\u4e9e\uff09"
    ],
    "qs:gn_country":"AM",
    "qs:gn_fcode":"PPL",
    "qs:gn_pop":1305,
    "qs:name":"Gagarin",
    "qs:name_adm0":"Armenia",
    "qs:name_adm1":"Kotayk'",
    "qs:photos":0,
    "qs:photos_1k":0,
    "qs:photos_9k":1,
    "qs:photos_9r":1,
    "qs:photos_all":4,
    "qs:photos_sr":0,
    "qs:placetype":"Town",
    "qs:pop_sr":"3",
    "qs:woe_adm0":23424743,
    "wd:wordcount":93,
    "wof:name":"Gagarin",
    "wof:placetype":"locality",
    "wof:population":1305
},
  "geometry": {"coordinates":[44.86918,40.54031],"type":"Point"}
}