{
  "type": "Feature",
  "properties": {
    "gn:admin1_code":"02",
    "gn:asciiname":"Sip'anik",
    "gn:country_code":"AM",
    "gn:dem":831,
    "gn:feature_class":"P",
    "gn:feature_code":"PPL",
    "gn:name":"Sip\u2019anik",
    "gn:population":0,
    "gn:timezone":"Asia/Yerevan",
    "iso:country":"AM",
    "name:hye_x_preferred":[
        "Sip\u2019anik"
    ],
    "name:hye_x_variant":[
        "\u054d\u056b\u0583\u0561\u0576\u056b\u056f"
    ],
    "wof:name":"Sip'anik",
    "wof:placetype":"locality"
},
  "geometry": {"coordinates":[44.36249,40.08331],"type":"Point"}
}