{
  "type": "Feature",
  "properties": {
    "gn:admin1_code":"6.0",
    "gn:asciiname":"K'och'ei Surb",
    "gn:country_code":"AM",
    "gn:dem":1800,
    "gn:feature_class":"P",
    "gn:feature_code":"PPL",
    "gn:name":"K\u2019och\u2019ei Surb",
    "gn:population":0,
    "gn:timezone":"Asia/Yerevan",
    "iso:country":"AM",
    "name:hye_x_preferred":[
        "K\u2019och\u2019ei Surb"
    ],
    "name:hye_x_variant":[
        "\u0554\u0578\u0579\u0565\u056b \u054d\u0578\u0582\u0580\u0562"
    ],
    "wof:name":"K'och'ei Surb",
    "wof:placetype":"locality"
},
  "geometry": {"coordinates":[44.21393,40.77789],"type":"Point"}
}