{
  "type": "Feature",
  "properties": {
    "gn:admin1_code":"7.0",
    "gn:asciiname":"Hin Gyughategh",
    "gn:country_code":"AM",
    "gn:dem":1788,
    "gn:feature_class":"P",
    "gn:feature_code":"PPL",
    "gn:name":"Hin Gyughategh",
    "gn:population":0,
    "gn:timezone":"Asia/Yerevan",
    "iso:country":"AM",
    "name:hye_x_preferred":[
        "Hin Gyughategh"
    ],
    "name:hye_x_variant":[
        "\u0540\u056b\u0576 \u0563\u0575\u0578\u0582\u0572\u0561\u057f\u0565\u0572"
    ],
    "wof:name":"Hin Gyughategh",
    "wof:placetype":"locality"
},
  "geometry": {"coordinates":[43.68469,40.85968],"type":"Point"}
}