{
  "type": "Feature",
  "properties": {
    "gn:admin1_code":"1.0",
    "gn:asciiname":"Khnusik",
    "gn:country_code":"AM",
    "gn:dem":1977,
    "gn:feature_class":"P",
    "gn:feature_code":"PPL",
    "gn:name":"Khnusik",
    "gn:population":0,
    "gn:timezone":"Asia/Yerevan",
    "iso:country":"AM",
    "name:hye_x_preferred":[
        "Khnusik"
    ],
    "name:hye_x_variant":[
        "\u053d\u0576\u0578\u0582\u057d\u056b\u056f"
    ],
    "wof:name":"Khnusik",
    "wof:placetype":"locality"
},
  "geometry": {"coordinates":[44.18329,40.3501],"type":"Point"}
}