{
  "type": "Feature",
  "properties": {
    "gn:admin1_code":"1.0",
    "gn:asciiname":"Khnusik",
    "gn:country_code":"AM",
    "gn:dem":1977,
    "gn:feature_class":"P",
    "gn:feature_code":"PPL",
    "gn:name":"Khnusik",
    "gn:population":0,
    "gn:timezone":"Asia/Yerevan",
    "iso:country":"AM",
    "name:fas_x_preferred":[
        "\u062e\u0646\u0648\u0633\u06cc\u06a9"
    ],
    "name:hye_x_preferred":[
        "Khnusik"
    ],
    "name:hye_x_variant":[
        "\u053d\u0576\u0578\u0582\u057d\u056b\u056f"
    ],
    "name:kat_x_preferred":[
        "\u10ee\u10dc\u10e3\u10e1\u10d8\u10d9\u10d8"
    ],
    "name:spa_x_preferred":[
        "Khnusik"
    ],
    "name:ukr_x_preferred":[
        "\u0425\u043d\u0443\u0441\u0456\u043a"
    ],
    "wof:name":"Khnusik",
    "wof:placetype":"locality"
},
  "geometry": {"coordinates":[44.18329,40.3501],"type":"Point"}
}