{
  "type": "Feature",
  "properties": {
    "gn:admin1_code":"7.0",
    "gn:asciiname":"Gtasheni Hin",
    "gn:country_code":"AM",
    "gn:dem":2150,
    "gn:feature_class":"P",
    "gn:feature_code":"PPL",
    "gn:name":"Gtasheni Hin",
    "gn:population":0,
    "gn:timezone":"Asia/Yerevan",
    "iso:country":"AM",
    "name:hye_x_preferred":[
        "Gtasheni Hin"
    ],
    "name:hye_x_variant":[
        "\u0533\u057f\u0561\u0577\u0565\u0576\u056b \u0570\u056b\u0576"
    ],
    "wof:name":"Gtasheni Hin",
    "wof:placetype":"locality"
},
  "geometry": {"coordinates":[43.6861,40.93469],"type":"Point"}
}