{
  "type": "Feature",
  "properties": {
    "gn:admin1_code":"9.0",
    "gn:asciiname":"Yeghts'adzor",
    "gn:country_code":"AM",
    "gn:dem":1246,
    "gn:feature_class":"P",
    "gn:feature_code":"PPL",
    "gn:name":"Yeghts\u2019adzor",
    "gn:population":0,
    "gn:timezone":"Asia/Yerevan",
    "iso:country":"AM",
    "name:hye_x_preferred":[
        "Yeghts\u2019adzor"
    ],
    "name:hye_x_variant":[
        "\u0535\u0572\u0581\u0561\u0571\u0578\u0580"
    ],
    "wof:name":"Yeghts'adzor",
    "wof:placetype":"locality"
},
  "geometry": {"coordinates":[45.4751,40.83752],"type":"Point"}
}