{
  "type": "Feature",
  "properties": {
    "gn:admin1_code":"9.0",
    "gn:asciiname":"Kapuytlerr",
    "gn:country_code":"AM",
    "gn:dem":2157,
    "gn:feature_class":"P",
    "gn:feature_code":"PPL",
    "gn:name":"Kapuytlerr",
    "gn:population":0,
    "gn:timezone":"Asia/Yerevan",
    "iso:country":"AM",
    "name:hye_x_preferred":[
        "Kapuytlerr"
    ],
    "name:hye_x_variant":[
        "\u053f\u0561\u057a\u0578\u0582\u0575\u057f\u056c\u0565\u057c"
    ],
    "wof:name":"Kapuytlerr",
    "wof:placetype":"locality"
},
  "geometry": {"coordinates":[44.9043,40.72369000000001],"type":"Point"}
}