{
  "type": "Feature",
  "properties": {
    "gn:admin1_code":"6.0",
    "gn:asciiname":"K'ober Kayaranin Kits'",
    "gn:country_code":"AM",
    "gn:dem":822,
    "gn:feature_class":"P",
    "gn:feature_code":"PPL",
    "gn:name":"K\u2019ober Kayaranin Kits\u2019",
    "gn:population":0,
    "gn:timezone":"Asia/Yerevan",
    "iso:country":"AM",
    "name:hye_x_preferred":[
        "K\u2019ober Kayaranin Kits\u2019"
    ],
    "name:hye_x_variant":[
        "\u0554\u0578\u0562\u0565\u0580 \u056f\u0561\u0575\u0561\u0580\u0561\u0576\u056b\u0576 \u056f\u056b\u0581"
    ],
    "wof:name":"K'ober Kayaranin Kits'",
    "wof:placetype":"locality"
},
  "geometry": {"coordinates":[44.63751,41.00568],"type":"Point"}
}