{
  "type": "Feature",
  "properties": {
    "gn:admin1_code":"5.0",
    "gn:asciiname":"Alagyaz",
    "gn:country_code":"AM",
    "gn:dem":2651,
    "gn:feature_class":"P",
    "gn:feature_code":"PPL",
    "gn:name":"Alagyaz",
    "gn:population":0,
    "gn:timezone":"Asia/Yerevan",
    "iso:country":"AM",
    "name:ara_x_preferred":[
        "\u0623\u0644\u0627\u063a\u064a\u0627\u0632"
    ],
    "name:aze_x_preferred":[
        "Alag\u00f6z"
    ],
    "name:bel_x_preferred":[
        "\u0410\u043b\u0430\u0433\u044f\u0437"
    ],
    "name:che_x_preferred":[
        "\u0410\u043b\u0430\u0433\u044f\u0437"
    ],
    "name:deu_x_preferred":[
        "Alagyaz"
    ],
    "name:fas_x_preferred":[
        "\u0622\u0644\u0627\u06af\u06cc\u0627\u0632"
    ],
    "name:fra_x_preferred":[
        "Alagyaz"
    ],
    "name:hye_x_preferred":[
        "Alagyaz"
    ],
    "name:hye_x_variant":[
        "\u0531\u056c\u0561\u0563\u0575\u0561\u0566"
    ],
    "name:ita_x_preferred":[
        "Alagyaz"
    ],
    "name:kat_x_preferred":[
        "\u10d0\u10da\u10d0\u10d2\u10d8\u10d0\u10d6\u10d8"
    ],
    "name:kur_x_preferred":[
        "Elegez"
    ],
    "name:msa_x_preferred":[
        "Alagyaz"
    ],
    "name:nld_x_preferred":[
        "Alagjaz"
    ],
    "name:rus_x_preferred":[
        "\u0410\u043b\u0430\u0433\u044f\u0437"
    ],
    "name:spa_x_preferred":[
        "Alagyaz"
    ],
    "name:ukr_x_preferred":[
        "\u0410\u043b\u0430\u0491\u044f\u0437"
    ],
    "name:vie_x_preferred":[
        "Alagyaz"
    ],
    "wof:name":"Alagyaz",
    "wof:placetype":"locality"
},
  "geometry": {"coordinates":[44.68048,40.68048],"type":"Point"}
}