{
  "type": "Feature",
  "properties": {
    "gn:admin1_code":"5.0",
    "gn:asciiname":"Alagyaz",
    "gn:country_code":"AM",
    "gn:dem":2651,
    "gn:feature_class":"P",
    "gn:feature_code":"PPL",
    "gn:name":"Alagyaz",
    "gn:population":0,
    "gn:timezone":"Asia/Yerevan",
    "iso:country":"AM",
    "name:hye_x_preferred":[
        "Alagyaz"
    ],
    "name:hye_x_variant":[
        "\u0531\u056c\u0561\u0563\u0575\u0561\u0566"
    ],
    "wof:name":"Alagyaz",
    "wof:placetype":"locality"
},
  "geometry": {"coordinates":[44.68048,40.68048],"type":"Point"}
}