{
  "type": "Feature",
  "properties": {
    "gn:admin1_code":"9.0",
    "gn:asciiname":"Astvatsatsin Surb",
    "gn:country_code":"AM",
    "gn:dem":1127,
    "gn:feature_class":"P",
    "gn:feature_code":"PPL",
    "gn:name":"Astvatsatsin Surb",
    "gn:population":0,
    "gn:timezone":"Asia/Yerevan",
    "iso:country":"AM",
    "name:hye_x_preferred":[
        "Astvatsatsin Surb"
    ],
    "name:hye_x_variant":[
        "\u0531\u057d\u057f\u057e\u0561\u056e\u0561\u056e\u056b\u0576 \u054d\u0578\u0582\u0580\u0562."
    ],
    "wof:name":"Astvatsatsin Surb",
    "wof:placetype":"locality"
},
  "geometry": {"coordinates":[45.12793,40.9751],"type":"Point"}
}