{
  "type": "Feature",
  "properties": {
    "gn:admin1_code":"1.0",
    "gn:asciiname":"Manuki",
    "gn:country_code":"AM",
    "gn:dem":2073,
    "gn:feature_class":"P",
    "gn:feature_code":"PPL",
    "gn:name":"Manuki",
    "gn:population":0,
    "gn:timezone":"Asia/Yerevan",
    "iso:country":"AM",
    "name:hye_x_preferred":[
        "Manuki"
    ],
    "name:hye_x_variant":[
        "\u0544\u0561\u0576\u0578\u0582\u056f\u056b"
    ],
    "wof:name":"Manuki",
    "wof:placetype":"locality"
},
  "geometry": {"coordinates":[44.18329,40.70569],"type":"Point"}
}