{
  "type": "Feature",
  "properties": {
    "gn:admin1_code":"7.0",
    "gn:asciiname":"Dvalner",
    "gn:country_code":"AM",
    "gn:dem":2060,
    "gn:feature_class":"P",
    "gn:feature_code":"PPL",
    "gn:name":"Dvalner",
    "gn:population":0,
    "gn:timezone":"Asia/Yerevan",
    "iso:country":"AM",
    "name:hye_x_preferred":[
        "Dvalner"
    ],
    "name:hye_x_variant":[
        "\u0534\u057e\u0561\u056c\u0576\u0565\u0580"
    ],
    "wof:name":"Dvalner",
    "wof:placetype":"locality"
},
  "geometry": {"coordinates":[43.93048,40.5293],"type":"Point"}
}