{
  "type": "Feature",
  "properties": {
    "gn:admin1_code":"0.0",
    "gn:asciiname":"Papei Mot",
    "gn:country_code":"AM",
    "gn:dem":842,
    "gn:feature_class":"P",
    "gn:feature_code":"PPL",
    "gn:name":"Papei Mot",
    "gn:population":0,
    "gn:timezone":"Asia/Yerevan",
    "iso:country":"AM",
    "name:hye_x_preferred":[
        "Papei Mot"
    ],
    "name:hye_x_variant":[
        "\u054a\u0561\u057a\u0565\u056b \u0574\u0578\u057f"
    ],
    "wof:name":"Papei Mot",
    "wof:placetype":"locality"
},
  "geometry": {"coordinates":[44.19592,40.05011],"type":"Point"}
}