{
  "type": "Feature",
  "properties": {
    "gn:admin1_code":"2.0",
    "gn:asciiname":"Hnashen",
    "gn:country_code":"AM",
    "gn:dem":1353,
    "gn:feature_class":"P",
    "gn:feature_code":"PPL",
    "gn:name":"Hnashen",
    "gn:population":0,
    "gn:timezone":"Asia/Yerevan",
    "iso:country":"AM",
    "name:hye_x_preferred":[
        "Hnashen"
    ],
    "name:hye_x_variant":[
        "\u0540\u0576\u0561\u0577\u0565\u0576"
    ],
    "wof:name":"Hnashen",
    "wof:placetype":"locality"
},
  "geometry": {"coordinates":[44.89313,39.89032],"type":"Point"}
}