{
  "type": "Feature",
  "properties": {
    "gn:admin1_code":"02",
    "gn:asciiname":"Arazdayan",
    "gn:country_code":"AM",
    "gn:dem":800,
    "gn:feature_class":"P",
    "gn:feature_code":"PPL",
    "gn:name":"Arazdayan",
    "gn:population":0,
    "gn:timezone":"Asia/Yerevan",
    "iso:country":"AM",
    "name:aze_x_colloquial":[
        "Arazd\u0259y\u0259n"
    ],
    "name:aze_x_historical":[
        "Arazd\u0259y\u0259n"
    ],
    "name:aze_x_preferred":[
        "Arazd\u0259y\u0259n"
    ],
    "name:hye_x_preferred":[
        "\u0531\u0580\u0561\u0566\u0564\u0561\u0575\u0561\u0576"
    ],
    "wof:name":"Arazdayan",
    "wof:placetype":"locality"
},
  "geometry": {"coordinates":[44.7597,39.72089],"type":"Point"}
}