{
  "type": "Feature",
  "properties": {
    "gn:admin1_code":"9.0",
    "gn:asciiname":"Khasht'arrak",
    "gn:country_code":"AM",
    "gn:dem":1393,
    "gn:feature_class":"P",
    "gn:feature_code":"PPL",
    "gn:name":"Khasht\u2019arrak",
    "gn:population":0,
    "gn:timezone":"Asia/Yerevan",
    "iso:country":"AM",
    "name:hye_x_preferred":[
        "Khasht\u2019arrak"
    ],
    "name:hye_x_variant":[
        "\u053d\u0561\u0577\u0569\u0561\u057c\u0561\u056f"
    ],
    "wof:name":"Khasht'arrak",
    "wof:placetype":"locality"
},
  "geometry": {"coordinates":[45.05548,40.89313],"type":"Point"}
}