{
  "type": "Feature",
  "properties": {
    "gn:admin1_code":"3.0",
    "gn:asciiname":"Hin Jermots'ner",
    "gn:country_code":"AM",
    "gn:dem":871,
    "gn:feature_class":"P",
    "gn:feature_code":"PPL",
    "gn:name":"Hin Jermots\u2019ner",
    "gn:population":0,
    "gn:timezone":"Asia/Yerevan",
    "iso:country":"AM",
    "name:hye_x_preferred":[
        "Hin Jermots\u2019ner"
    ],
    "name:hye_x_variant":[
        "\u0540\u056b\u0576 \u057b\u0565\u0580\u0574\u0578\u0581\u0576\u0565\u0580"
    ],
    "wof:name":"Hin Jermots'ner",
    "wof:placetype":"locality"
},
  "geometry": {"coordinates":[44.01947,40.08612],"type":"Point"}
}