{
  "type": "Feature",
  "properties": {
    "gn:admin1_code":"1.0",
    "gn:asciiname":"Kghzyak",
    "gn:country_code":"AM",
    "gn:dem":1555,
    "gn:feature_class":"P",
    "gn:feature_code":"PPL",
    "gn:name":"Kghzyak",
    "gn:population":0,
    "gn:timezone":"Asia/Yerevan",
    "iso:country":"AM",
    "name:hye_x_preferred":[
        "Kghzyak"
    ],
    "name:hye_x_variant":[
        "\u053f\u0572\u0566\u0575\u0561\u056f"
    ],
    "wof:name":"Kghzyak",
    "wof:placetype":"locality"
},
  "geometry": {"coordinates":[43.80408,40.37372],"type":"Point"}
}