{
  "type": "Feature",
  "properties": {
    "gn:admin1_code":"6.0",
    "gn:asciiname":"Ort'ategh",
    "gn:country_code":"AM",
    "gn:dem":1286,
    "gn:feature_class":"P",
    "gn:feature_code":"PPL",
    "gn:name":"Ort\u2019ategh",
    "gn:population":0,
    "gn:timezone":"Asia/Yerevan",
    "iso:country":"AM",
    "name:hye_x_preferred":[
        "Ort\u2019ategh"
    ],
    "name:hye_x_variant":[
        "\u0548\u0580\u0569\u0561\u057f\u0565\u0572"
    ],
    "wof:name":"Ort'ategh",
    "wof:placetype":"locality"
},
  "geometry": {"coordinates":[44.64172,40.89172],"type":"Point"}
}