{
  "type": "Feature",
  "properties": {
    "gn:admin1_code":"4.0",
    "gn:asciiname":"Mets Gyugh",
    "gn:country_code":"AM",
    "gn:dem":1842,
    "gn:feature_class":"P",
    "gn:feature_code":"PPL",
    "gn:name":"Mets Gyugh",
    "gn:population":0,
    "gn:timezone":"Asia/Yerevan",
    "iso:country":"AM",
    "name:hye_x_preferred":[
        "Mets Gyugh"
    ],
    "name:hye_x_variant":[
        "\u0544\u0565\u056e \u0563\u0575\u0578\u0582\u0572"
    ],
    "wof:name":"Mets Gyugh",
    "wof:placetype":"locality"
},
  "geometry": {"coordinates":[45.35828,40.67511],"type":"Point"}
}