{
  "type": "Feature",
  "properties": {
    "gn:admin1_code":"9.0",
    "gn:asciiname":"Honut",
    "gn:country_code":"AM",
    "gn:dem":873,
    "gn:feature_class":"P",
    "gn:feature_code":"PPL",
    "gn:name":"Honut",
    "gn:population":0,
    "gn:timezone":"Asia/Yerevan",
    "iso:country":"AM",
    "name:hye_x_preferred":[
        "Honut"
    ],
    "name:hye_x_variant":[
        "\u0540\u0578\u0576\u0578\u0582\u057f"
    ],
    "wof:name":"Honut",
    "wof:placetype":"locality"
},
  "geometry": {"coordinates":[45.51672,40.90008],"type":"Point"}
}