{
  "type": "Feature",
  "properties": {
    "gn:admin1_code":"7.0",
    "gn:asciiname":"Geghakhorrik",
    "gn:country_code":"AM",
    "gn:dem":2248,
    "gn:feature_class":"P",
    "gn:feature_code":"PPL",
    "gn:name":"Geghakhorrik",
    "gn:population":0,
    "gn:timezone":"Asia/Yerevan",
    "iso:country":"AM",
    "name:hye_x_preferred":[
        "Geghakhorrik"
    ],
    "name:hye_x_variant":[
        "\u0533\u0565\u0572\u0561\u056d\u0578\u057c\u056b\u056f"
    ],
    "wof:name":"Geghakhorrik",
    "wof:placetype":"locality"
},
  "geometry": {"coordinates":[43.95709,40.51392],"type":"Point"}
}