{
  "type": "Feature",
  "properties": {
    "gn:admin1_code":"1.0",
    "gn:asciiname":"Meloyi Gyugh",
    "gn:country_code":"AM",
    "gn:dem":1795,
    "gn:feature_class":"P",
    "gn:feature_code":"PPL",
    "gn:name":"Meloyi Gyugh",
    "gn:population":0,
    "gn:timezone":"Asia/Yerevan",
    "iso:country":"AM",
    "name:hye_x_preferred":[
        "Meloyi Gyugh"
    ],
    "name:hye_x_variant":[
        "\u0544\u0565\u056c\u0578\u0575\u056b \u0563\u0575\u0578\u0582\u0572"
    ],
    "wof:name":"Meloyi Gyugh",
    "wof:placetype":"locality"
},
  "geometry": {"coordinates":[44.44452,40.45709],"type":"Point"}
}