{
  "type": "Feature",
  "properties": {
    "iso:country":"AM",
    "name:ceb_x_preferred":[
        "Artsvaberd"
    ],
    "name:eng_x_preferred":[
        "Artsvaberd"
    ],
    "name:fas_x_preferred":[
        "\u0622\u0631\u062a\u0633\u0648\u0627\u0628\u0631\u062f"
    ],
    "name:fra_x_preferred":[
        "Artsvaberd"
    ],
    "name:hye_x_preferred":[
        "\u0531\u0580\u056e\u057e\u0561\u0562\u0565\u0580\u0564"
    ],
    "name:ita_x_preferred":[
        "Artsvaberd"
    ],
    "name:kat_x_preferred":[
        "\u10d0\u10e0\u10ec\u10d5\u10d0\u10d1\u10d4\u10e0\u10d3\u10d8"
    ],
    "name:msa_x_preferred":[
        "Artsvaberd"
    ],
    "name:nld_x_preferred":[
        "Artsvaberd"
    ],
    "name:rus_x_preferred":[
        "\u0410\u0440\u0446\u0432\u0430\u0431\u0435\u0440\u0434"
    ],
    "name:sco_x_preferred":[
        "Artsvaberd"
    ],
    "name:swe_x_preferred":[
        "Artsvaberd"
    ],
    "name:vie_x_preferred":[
        "Artsvaberd"
    ],
    "name:zho_min_nan_x_preferred":[
        "Artsvaberd"
    ],
    "qs:gn_country":"AM",
    "qs:gn_fcode":"PPL",
    "qs:gn_pop":3193,
    "qs:name":"Artsvaberd",
    "qs:name_adm0":"Armenia",
    "qs:name_adm1":"Tavush",
    "qs:photos":0,
    "qs:photos_1k":0,
    "qs:photos_9k":1,
    "qs:photos_9r":1,
    "qs:photos_all":1,
    "qs:photos_sr":0,
    "qs:placetype":"Town",
    "qs:pop_sr":"4",
    "qs:woe_adm0":23424743,
    "wd:wordcount":59,
    "wof:name":"Artsvaberd",
    "wof:placetype":"locality",
    "wof:population":3193
},
  "geometry": {"coordinates":[45.47111,40.83361],"type":"Point"}
}