{
  "type": "Feature",
  "properties": {
    "gn:admin1_code":"4.0",
    "gn:asciiname":"Aparank'",
    "gn:country_code":"AM",
    "gn:dem":2205,
    "gn:feature_class":"P",
    "gn:feature_code":"PPL",
    "gn:name":"Aparank\u2019",
    "gn:population":0,
    "gn:timezone":"Asia/Yerevan",
    "iso:country":"AM",
    "name:hye_x_preferred":[
        "Aparank\u2019"
    ],
    "name:hye_x_variant":[
        "\u0531\u057a\u0561\u0580\u0561\u0576\u0584"
    ],
    "wof:name":"Aparank'",
    "wof:placetype":"locality"
},
  "geometry": {"coordinates":[45.02368,40.38208],"type":"Point"}
}