{
  "type": "Feature",
  "properties": {
    "gn:admin1_code":"7.0",
    "gn:asciiname":"Aghasu Ev Gevoriki",
    "gn:country_code":"AM",
    "gn:dem":2028,
    "gn:feature_class":"P",
    "gn:feature_code":"PPL",
    "gn:name":"Aghasu Ev Gevoriki",
    "gn:population":0,
    "gn:timezone":"Asia/Yerevan",
    "iso:country":"AM",
    "name:hye_x_preferred":[
        "Aghasu Ev Gevoriki"
    ],
    "name:hye_x_variant":[
        "\u0531\u0572\u0561\u057d\u0578\u0582 \u0587 \u0533\u0587\u0578\u0580\u056b\u056f\u056b"
    ],
    "wof:name":"Aghasu Ev Gevoriki",
    "wof:placetype":"locality"
},
  "geometry": {"coordinates":[43.60968,41.07928],"type":"Point"}
}