{
  "type": "Feature",
  "properties": {
    "gn:admin1_code":"4.0",
    "gn:asciiname":"Sevani",
    "gn:country_code":"AM",
    "gn:dem":1898,
    "gn:feature_class":"P",
    "gn:feature_code":"PPL",
    "gn:name":"Sevani",
    "gn:population":0,
    "gn:timezone":"Asia/Yerevan",
    "iso:country":"AM",
    "name:hye_x_preferred":[
        "Sevani"
    ],
    "name:hye_x_variant":[
        "\u054d\u0587\u0561\u0576\u056b"
    ],
    "wof:name":"Sevani",
    "wof:placetype":"locality"
},
  "geometry": {"coordinates":[45.45007,40.33331],"type":"Point"}
}