{
  "type": "Feature",
  "properties": {
    "gn:admin1_code":"1.0",
    "gn:asciiname":"Hovaran",
    "gn:country_code":"AM",
    "gn:dem":1273,
    "gn:feature_class":"P",
    "gn:feature_code":"PPL",
    "gn:name":"Hovaran",
    "gn:population":0,
    "gn:timezone":"Asia/Yerevan",
    "iso:country":"AM",
    "name:hye_x_preferred":[
        "Hovaran"
    ],
    "name:hye_x_variant":[
        "\u0540\u0578\u057e\u0561\u0580\u0561\u0576"
    ],
    "wof:name":"Hovaran",
    "wof:placetype":"locality"
},
  "geometry": {"coordinates":[44.25153,40.31811],"type":"Point"}
}