{
  "type": "Feature",
  "properties": {
    "gn:admin1_code":"9.0",
    "gn:asciiname":"Hin Parravak'ar",
    "gn:country_code":"AM",
    "gn:dem":689,
    "gn:feature_class":"P",
    "gn:feature_code":"PPL",
    "gn:name":"Hin Parravak\u2019ar",
    "gn:population":0,
    "gn:timezone":"Asia/Yerevan",
    "iso:country":"AM",
    "name:hye_x_preferred":[
        "Hin Parravak\u2019ar"
    ],
    "name:hye_x_variant":[
        "\u0540\u056b\u0576 \u054a\u0561\u057c\u0561\u057e\u0561\u0584\u0561\u0580"
    ],
    "wof:name":"Hin Parravak'ar",
    "wof:placetype":"locality"
},
  "geometry": {"coordinates":[45.39587,40.97229],"type":"Point"}
}