{
  "type": "Feature",
  "properties": {
    "gn:admin1_code":"8.0",
    "gn:asciiname":"Pasharajur",
    "gn:country_code":"AM",
    "gn:dem":1348,
    "gn:feature_class":"P",
    "gn:feature_code":"PPL",
    "gn:name":"Pasharajur",
    "gn:population":0,
    "gn:timezone":"Asia/Yerevan",
    "iso:country":"AM",
    "name:hye_x_preferred":[
        "Pasharajur"
    ],
    "name:hye_x_variant":[
        "\u054a\u0561\u0577\u0561\u0580\u0561\u057b\u0578\u0582\u0580"
    ],
    "wof:name":"Pasharajur",
    "wof:placetype":"locality"
},
  "geometry": {"coordinates":[46.36389000000001,39.41107],"type":"Point"}
}