{
  "type": "Feature",
  "properties": {
    "gn:admin1_code":"8.0",
    "gn:asciiname":"T'akhs",
    "gn:country_code":"AM",
    "gn:dem":1320,
    "gn:feature_class":"P",
    "gn:feature_code":"PPL",
    "gn:name":"T\u2019akhs",
    "gn:population":0,
    "gn:timezone":"Asia/Yerevan",
    "iso:country":"AM",
    "name:hye_x_preferred":[
        "T\u2019akhs"
    ],
    "name:hye_x_variant":[
        "\u0539\u0561\u056d\u057d"
    ],
    "wof:name":"T'akhs",
    "wof:placetype":"locality"
},
  "geometry": {"coordinates":[46.3653,39.29309],"type":"Point"}
}