{
  "type": "Feature",
  "properties": {
    "gn:admin1_code":"10",
    "gn:asciiname":"Chrag",
    "gn:country_code":"AM",
    "gn:dem":1886,
    "gn:feature_class":"P",
    "gn:feature_code":"PPL",
    "gn:name":"Chrag",
    "gn:population":0,
    "gn:timezone":"Asia/Yerevan",
    "iso:country":"AM",
    "name:aze_x_preferred":[
        "\u00c7iraxl\u0131"
    ],
    "name:hye_x_preferred":[
        "Chrag"
    ],
    "name:hye_x_variant":[
        "\u0543\u0580\u0561\u0563"
    ],
    "name:und_x_variant":[
        "Chirakhlu"
    ],
    "wof:name":"Chrag",
    "wof:placetype":"locality"
},
  "geometry": {"coordinates":[45.60431,39.68329],"type":"Point"}
}