{
  "type": "Feature",
  "properties": {
    "gn:admin1_code":"9.0",
    "gn:asciiname":"Kochghut",
    "gn:country_code":"AM",
    "gn:dem":1383,
    "gn:feature_class":"P",
    "gn:feature_code":"PPL",
    "gn:name":"Kochghut",
    "gn:population":0,
    "gn:timezone":"Asia/Yerevan",
    "iso:country":"AM",
    "name:hye_x_preferred":[
        "Kochghut"
    ],
    "name:hye_x_variant":[
        "\u053f\u0578\u0573\u0572\u0578\u0582\u057f"
    ],
    "wof:name":"Kochghut",
    "wof:placetype":"locality"
},
  "geometry": {"coordinates":[45.37091,40.73889000000001],"type":"Point"}
}