{
  "type": "Feature",
  "properties": {
    "gn:admin1_code":"4.0",
    "gn:asciiname":"Tsaghkashen",
    "gn:country_code":"AM",
    "gn:dem":2635,
    "gn:feature_class":"P",
    "gn:feature_code":"PPL",
    "gn:name":"Tsaghkashen",
    "gn:population":0,
    "gn:timezone":"Asia/Yerevan",
    "iso:country":"AM",
    "name:hye_x_preferred":[
        "Tsaghkashen"
    ],
    "name:hye_x_variant":[
        "\u053e\u0561\u0572\u056f\u0561\u0577\u0565\u0576"
    ],
    "wof:name":"Tsaghkashen",
    "wof:placetype":"locality"
},
  "geometry": {"coordinates":[45.01111,40.27508],"type":"Point"}
}