{
  "type": "Feature",
  "properties": {
    "gn:admin1_code":"11",
    "gn:asciiname":"Kanakerr-Zeytun",
    "gn:country_code":"AM",
    "gn:dem":1280,
    "gn:feature_class":"P",
    "gn:feature_code":"PPL",
    "gn:name":"Kanakerr-Zeytun",
    "gn:population":0,
    "gn:timezone":"Asia/Yerevan",
    "iso:country":"AM",
    "wof:name":"Kanakerr-Zeytun",
    "wof:placetype":"locality"
},
  "geometry": {"coordinates":[44.53833,40.22],"type":"Point"}
}