{
  "type": "Feature",
  "properties": {
    "gn:admin1_code":"6.0",
    "gn:asciiname":"Jukhtak",
    "gn:country_code":"AM",
    "gn:dem":1743,
    "gn:feature_class":"P",
    "gn:feature_code":"PPL",
    "gn:name":"Jukhtak",
    "gn:population":0,
    "gn:timezone":"Asia/Yerevan",
    "iso:country":"AM",
    "name:hye_x_preferred":[
        "Jukhtak"
    ],
    "name:hye_x_variant":[
        "\u054b\u0578\u0582\u056d\u057f\u0561\u056f"
    ],
    "wof:name":"Jukhtak",
    "wof:placetype":"locality"
},
  "geometry": {"coordinates":[44.65008,40.8529],"type":"Point"}
}