{
  "type": "Feature",
  "properties": {
    "gn:admin1_code":"8.0",
    "gn:asciiname":"Bekhnasar",
    "gn:country_code":"AM",
    "gn:dem":1407,
    "gn:feature_class":"P",
    "gn:feature_code":"PPL",
    "gn:name":"Bekhnasar",
    "gn:population":0,
    "gn:timezone":"Asia/Yerevan",
    "iso:country":"AM",
    "name:hye_x_preferred":[
        "Bekhnasar"
    ],
    "name:hye_x_variant":[
        "\u0532\u0565\u056d\u0576\u0561\u057d\u0561\u0580"
    ],
    "wof:name":"Bekhnasar",
    "wof:placetype":"locality"
},
  "geometry": {"coordinates":[46.4931,39.11249],"type":"Point"}
}