{
  "type": "Feature",
  "properties": {
    "gn:admin1_code":"04",
    "gn:asciiname":"Kut'",
    "gn:country_code":"AM",
    "gn:dem":2159,
    "gn:feature_class":"P",
    "gn:feature_code":"PPL",
    "gn:name":"Kut\u2019",
    "gn:population":0,
    "gn:timezone":"Asia/Yerevan",
    "iso:country":"AM",
    "name:aze_x_preferred":[
        "Zark\u0259nd"
    ],
    "name:hye_x_preferred":[
        "\u053f\u0578\u0582\u0569"
    ],
    "name:und_x_variant":[
        "Zarzibil",
        "Zarkend",
        "Kut\u2019"
    ],
    "wof:name":"Kut'",
    "wof:placetype":"locality"
},
  "geometry": {"coordinates":[45.89625,40.18055],"type":"Point"}
}