{
  "type": "Feature",
  "properties": {
    "gn:admin1_code":"1.0",
    "gn:asciiname":"Gegh",
    "gn:country_code":"AM",
    "gn:dem":1522,
    "gn:feature_class":"P",
    "gn:feature_code":"PPL",
    "gn:name":"Gegh",
    "gn:population":0,
    "gn:timezone":"Asia/Yerevan",
    "iso:country":"AM",
    "name:hye_x_preferred":[
        "Gegh"
    ],
    "name:hye_x_variant":[
        "\u0533\u0565\u0572"
    ],
    "wof:name":"Gegh",
    "wof:placetype":"locality"
},
  "geometry": {"coordinates":[43.69452,40.48328],"type":"Point"}
}