{
  "type": "Feature",
  "properties": {
    "gn:admin1_code":"05",
    "gn:asciiname":"Sotsgyukh",
    "gn:country_code":"AM",
    "gn:dem":1431,
    "gn:feature_class":"P",
    "gn:feature_code":"PPL",
    "gn:name":"Sotsgyukh",
    "gn:population":0,
    "gn:timezone":"Asia/Yerevan",
    "iso:country":"AM",
    "wof:name":"Sotsgyukh",
    "wof:placetype":"locality"
},
  "geometry": {"coordinates":[44.67806,40.12944],"type":"Point"}
}