{
  "type": "Feature",
  "properties": {
    "gn:admin1_code":"6.0",
    "gn:asciiname":"Gaz",
    "gn:country_code":"AM",
    "gn:dem":2013,
    "gn:feature_class":"P",
    "gn:feature_code":"PPL",
    "gn:name":"Gaz",
    "gn:population":0,
    "gn:timezone":"Asia/Yerevan",
    "iso:country":"AM",
    "name:hye_x_preferred":[
        "Gaz"
    ],
    "name:hye_x_variant":[
        "\u0533\u0561\u0566"
    ],
    "wof:name":"Gaz",
    "wof:placetype":"locality"
},
  "geometry": {"coordinates":[44.85687,40.88751],"type":"Point"}
}