{
  "type": "Feature",
  "properties": {
    "gn:admin1_code":"6.0",
    "gn:asciiname":"Gaz",
    "gn:country_code":"AM",
    "gn:dem":2013,
    "gn:feature_class":"P",
    "gn:feature_code":"PPL",
    "gn:name":"Gaz",
    "gn:population":0,
    "gn:timezone":"Asia/Yerevan",
    "iso:country":"AM",
    "name:aze_x_preferred":[
        "Qaz"
    ],
    "name:ceb_x_preferred":[
        "Gaz"
    ],
    "name:fra_x_preferred":[
        "Gaz"
    ],
    "name:hrv_x_preferred":[
        "Gaz"
    ],
    "name:hye_x_preferred":[
        "Gaz"
    ],
    "name:hye_x_variant":[
        "\u0533\u0561\u0566"
    ],
    "name:pol_x_preferred":[
        "Gaz"
    ],
    "name:ron_x_preferred":[
        "Gaz"
    ],
    "name:slv_x_preferred":[
        "Gaz"
    ],
    "name:swe_x_preferred":[
        "Gaz"
    ],
    "name:uzb_x_preferred":[
        "Gaz"
    ],
    "name:vep_x_preferred":[
        "Gaz"
    ],
    "wof:name":"Gaz",
    "wof:placetype":"locality"
},
  "geometry": {"coordinates":[44.85687,40.88751],"type":"Point"}
}