{
  "type": "Feature",
  "properties": {
    "gn:admin1_code":"9.0",
    "gn:asciiname":"T'it'eghots'",
    "gn:country_code":"AM",
    "gn:dem":1589,
    "gn:feature_class":"P",
    "gn:feature_code":"PPL",
    "gn:name":"T\u2019it\u2019eghots\u2019",
    "gn:population":0,
    "gn:timezone":"Asia/Yerevan",
    "iso:country":"AM",
    "name:hye_x_preferred":[
        "T\u2019it\u2019eghots\u2019"
    ],
    "name:hye_x_variant":[
        "\u0539\u056b\u0569\u0565\u0572\u0578\u0581"
    ],
    "wof:name":"T'it'eghots'",
    "wof:placetype":"locality"
},
  "geometry": {"coordinates":[45.32373,40.75293],"type":"Point"}
}