{
  "type": "Feature",
  "properties": {
    "gn:admin1_code":"6.0",
    "gn:asciiname":"Kuboyi Hogher",
    "gn:country_code":"AM",
    "gn:dem":1342,
    "gn:feature_class":"P",
    "gn:feature_code":"PPL",
    "gn:name":"Kuboyi Hogher",
    "gn:population":0,
    "gn:timezone":"Asia/Yerevan",
    "iso:country":"AM",
    "name:hye_x_preferred":[
        "Kuboyi Hogher"
    ],
    "name:hye_x_variant":[
        "\u053f\u0578\u0582\u0562\u0578\u0575\u056b \u0570\u0578\u0572\u0565\u0580"
    ],
    "wof:name":"Kuboyi Hogher",
    "wof:placetype":"locality"
},
  "geometry": {"coordinates":[44.56671,40.98187],"type":"Point"}
}