{
  "type": "Feature",
  "properties": {
    "gn:admin1_code":"7.0",
    "gn:asciiname":"T'orosi Tsarrner",
    "gn:country_code":"AM",
    "gn:dem":1830,
    "gn:feature_class":"P",
    "gn:feature_code":"PPL",
    "gn:name":"T\u2019orosi Tsarrner",
    "gn:population":0,
    "gn:timezone":"Asia/Yerevan",
    "iso:country":"AM",
    "name:hye_x_preferred":[
        "T\u2019orosi Tsarrner"
    ],
    "name:hye_x_variant":[
        "\u0539\u0578\u0580\u0578\u057d\u056b \u056e\u0561\u057c\u0576\u0565\u0580"
    ],
    "wof:name":"T'orosi Tsarrner",
    "wof:placetype":"locality"
},
  "geometry": {"coordinates":[43.85828,40.92511],"type":"Point"}
}