{
  "type": "Feature",
  "properties": {
    "gn:admin1_code":"1.0",
    "gn:asciiname":"T'unel",
    "gn:country_code":"AM",
    "gn:dem":1741,
    "gn:feature_class":"P",
    "gn:feature_code":"PPL",
    "gn:name":"T\u2019unel",
    "gn:population":0,
    "gn:timezone":"Asia/Yerevan",
    "iso:country":"AM",
    "name:hye_x_preferred":[
        "T\u2019unel"
    ],
    "name:hye_x_variant":[
        "\u0539\u0578\u0582\u0576\u0565\u056c"
    ],
    "wof:name":"T'unel",
    "wof:placetype":"locality"
},
  "geometry": {"coordinates":[44.41669,40.43329],"type":"Point"}
}