{
  "type": "Feature",
  "properties": {
    "gn:admin1_code":"1.0",
    "gn:asciiname":"T'agavoranist K'aghak'",
    "gn:country_code":"AM",
    "gn:dem":1885,
    "gn:feature_class":"P",
    "gn:feature_code":"PPL",
    "gn:name":"T\u2019agavoranist K\u2019aghak\u2019",
    "gn:population":0,
    "gn:timezone":"Asia/Yerevan",
    "iso:country":"AM",
    "name:hye_x_preferred":[
        "T\u2019agavoranist K\u2019aghak\u2019"
    ],
    "name:hye_x_variant":[
        "\u0539\u0561\u0563\u0561\u057e\u0578\u0580\u0561\u0576\u056b\u057d\u057f \u0584\u0561\u0572\u0561\u0584"
    ],
    "wof:name":"T'agavoranist K'aghak'",
    "wof:placetype":"locality"
},
  "geometry": {"coordinates":[44.4765,40.45148],"type":"Point"}
}