{
  "type": "Feature",
  "properties": {
    "gn:admin1_code":"2.0",
    "gn:asciiname":"Yerknist",
    "gn:country_code":"AM",
    "gn:dem":1447,
    "gn:feature_class":"P",
    "gn:feature_code":"PPL",
    "gn:name":"Yerknist",
    "gn:population":0,
    "gn:timezone":"Asia/Yerevan",
    "iso:country":"AM",
    "name:hye_x_preferred":[
        "Yerknist"
    ],
    "name:hye_x_variant":[
        "\u0535\u0580\u056f\u0576\u056b\u057d\u057f"
    ],
    "wof:name":"Yerknist",
    "wof:placetype":"locality"
},
  "geometry": {"coordinates":[44.83331,39.87231],"type":"Point"}
}