{
  "type": "Feature",
  "properties": {
    "gn:admin1_code":"01",
    "gn:asciiname":"K'uch'ak",
    "gn:country_code":"AM",
    "gn:dem":1876,
    "gn:feature_class":"P",
    "gn:feature_code":"PPL",
    "gn:name":"K\u2019uch\u2019ak",
    "gn:population":0,
    "gn:timezone":"Asia/Yerevan",
    "iso:country":"AM",
    "name:eng_x_preferred":[
        "K'uch'ak"
    ],
    "name:hye_x_preferred":[
        "\u0554\u0578\u0582\u0579\u0561\u056f"
    ],
    "name:rus_x_preferred":[
        "\u041a\u0443\u0447\u0430\u043a"
    ],
    "name:und_x_variant":[
        "Krchak",
        "Alikuchak",
        "K\u2019uch\u2019ak"
    ],
    "wof:name":"K'uch'ak",
    "wof:placetype":"locality"
},
  "geometry": {"coordinates":[44.39119,40.51915],"type":"Point"}
}