{
  "type": "Feature",
  "properties": {
    "gn:admin1_code":"01",
    "gn:asciiname":"K'uch'ak",
    "gn:country_code":"AM",
    "gn:dem":1876,
    "gn:feature_class":"P",
    "gn:feature_code":"PPL",
    "gn:name":"K\u2019uch\u2019ak",
    "gn:population":0,
    "gn:timezone":"Asia/Yerevan",
    "iso:country":"AM",
    "name:ara_x_preferred":[
        "\u0643\u0648\u0634\u0627\u0643"
    ],
    "name:aze_x_preferred":[
        "\u018fliki\u00e7ik"
    ],
    "name:eng_x_preferred":[
        "K'uch'ak"
    ],
    "name:fas_x_preferred":[
        "\u06a9\u0648\u0686\u0627\u06a9"
    ],
    "name:fra_x_preferred":[
        "Kuchak"
    ],
    "name:hye_x_preferred":[
        "\u0554\u0578\u0582\u0579\u0561\u056f"
    ],
    "name:ita_x_preferred":[
        "Kuchak"
    ],
    "name:kat_x_preferred":[
        "\u10e5\u10e3\u10e9\u10d0\u10d9\u10d8"
    ],
    "name:msa_x_preferred":[
        "Kuchak"
    ],
    "name:rus_x_preferred":[
        "\u041a\u0443\u0447\u0430\u043a"
    ],
    "name:spa_x_preferred":[
        "Kuchak"
    ],
    "name:ukr_x_preferred":[
        "\u041a\u0443\u0447\u0430\u043a"
    ],
    "name:und_x_variant":[
        "Krchak",
        "Alikuchak",
        "K\u2019uch\u2019ak"
    ],
    "wof:name":"K'uch'ak",
    "wof:placetype":"locality"
},
  "geometry": {"coordinates":[44.39119,40.51915],"type":"Point"}
}