{
  "type": "Feature",
  "properties": {
    "iso:country":"AM",
    "name:arm_x_preferred":[
        "\u0544\u0565\u056e \u0544\u0561\u057d\u0580\u056b\u056f"
    ],
    "name:aze_x_preferred":[
        "B\u00f6y\u00fck M\u0259zr\u0259"
    ],
    "name:ceb_x_preferred":[
        "Mets Masrik"
    ],
    "name:dut_x_preferred":[
        "Mets Masrik"
    ],
    "name:eng_x_preferred":[
        "Mets Masrik"
    ],
    "name:fas_x_preferred":[
        "\u0645\u062a\u0633 \u0645\u0627\u0633\u0631\u06cc\u06a9"
    ],
    "name:fra_x_preferred":[
        "Mets Masrik"
    ],
    "name:fre_x_preferred":[
        "Mets Masrik"
    ],
    "name:geo_x_preferred":[
        "\u10db\u10d4\u10ec-\u10db\u10d0\u10e1\u10e0\u10d8\u10d9\u10d8"
    ],
    "name:hye_x_preferred":[
        "\u0544\u0565\u056e \u0544\u0561\u057d\u0580\u056b\u056f"
    ],
    "name:ita_x_preferred":[
        "Mets Masrik"
    ],
    "name:kat_x_preferred":[
        "\u10db\u10d4\u10ec-\u10db\u10d0\u10e1\u10e0\u10d8\u10d9\u10d8"
    ],
    "name:may_x_preferred":[
        "Mets Masrik"
    ],
    "name:msa_x_preferred":[
        "Mets Masrik"
    ],
    "name:per_x_preferred":[
        "\u0645\u062a\u0633 \u0645\u0627\u0633\u0631\u06cc\u06a9"
    ],
    "name:rus_x_preferred":[
        "\u041c\u0435\u0446 \u041c\u0430\u0437\u0440\u0430"
    ],
    "name:sco_x_preferred":[
        "Mets Masrik"
    ],
    "name:swe_x_preferred":[
        "Mets Masrik"
    ],
    "name:ukr_x_preferred":[
        "\u041c\u0435\u0446 \u041c\u0430\u0441\u0440\u0456\u043a"
    ],
    "name:unk_x_variant":[
        "Mets-Mazra"
    ],
    "name:vie_x_preferred":[
        "Mets Masrik"
    ],
    "name:zho_min_nan_x_preferred":[
        "Mets Masrik"
    ],
    "qs:gn_country":"AM",
    "qs:gn_fcode":"PPL",
    "qs:gn_pop":2570,
    "qs:name":"Mets Masrik",
    "qs:name_adm0":"Armenia",
    "qs:name_adm1":"Geghark'unik'",
    "qs:photos":0,
    "qs:photos_1k":0,
    "qs:photos_9k":0,
    "qs:photos_9r":0,
    "qs:photos_all":0,
    "qs:photos_sr":0,
    "qs:placetype":"Town",
    "qs:pop_sr":"4",
    "qs:woe_adm0":23424743,
    "wd:wordcount":149,
    "wof:name":"Mets Masrik",
    "wof:placetype":"locality",
    "wof:population":2570
},
  "geometry": {"coordinates":[45.76809,40.21825],"type":"Point"}
}