{
  "type": "Feature",
  "properties": {
    "gn:admin1_code":"06",
    "gn:asciiname":"Hart'agyugh",
    "gn:country_code":"AM",
    "gn:dem":1714,
    "gn:feature_class":"P",
    "gn:feature_code":"PPL",
    "gn:name":"Hart\u2019agyugh",
    "gn:population":0,
    "gn:timezone":"Asia/Yerevan",
    "iso:country":"AM",
    "name:hye_x_preferred":[
        "\u0540\u0561\u0580\u0569\u0561\u0563\u0575\u0578\u0582\u0572"
    ],
    "name:und_x_variant":[
        "Artagyukh",
        "Kaltakhchi",
        "Hart\u2019agyugh"
    ],
    "wof:name":"Hart'agyugh",
    "wof:placetype":"locality"
},
  "geometry": {"coordinates":[44.04614,40.8346],"type":"Point"}
}