{
  "type": "Feature",
  "properties": {
    "gn:admin1_code":"1.0",
    "gn:asciiname":"Gyughategh",
    "gn:country_code":"AM",
    "gn:dem":1746,
    "gn:feature_class":"P",
    "gn:feature_code":"PPL",
    "gn:name":"Gyughategh",
    "gn:population":0,
    "gn:timezone":"Asia/Yerevan",
    "iso:country":"AM",
    "name:hye_x_preferred":[
        "Gyughategh"
    ],
    "name:hye_x_variant":[
        "\u0533\u0575\u0578\u0582\u0572\u0561\u057f\u0565\u0572"
    ],
    "wof:name":"Gyughategh",
    "wof:placetype":"locality"
},
  "geometry": {"coordinates":[44.35431,40.39172],"type":"Point"}
}