{
  "type": "Feature",
  "properties": {
    "gn:admin1_code":"6.0",
    "gn:asciiname":"Zhangot",
    "gn:country_code":"AM",
    "gn:dem":1975,
    "gn:feature_class":"P",
    "gn:feature_code":"PPL",
    "gn:name":"Zhangot",
    "gn:population":0,
    "gn:timezone":"Asia/Yerevan",
    "iso:country":"AM",
    "name:hye_x_preferred":[
        "Zhangot"
    ],
    "name:hye_x_variant":[
        "\u053a\u0561\u0576\u0563\u0578\u057f"
    ],
    "wof:name":"Zhangot",
    "wof:placetype":"locality"
},
  "geometry": {"coordinates":[44.82788,40.85553],"type":"Point"}
}