{
  "type": "Feature",
  "properties": {
    "gn:admin1_code":"02",
    "gn:asciiname":"Nerkin Nedzhirlu",
    "gn:country_code":"AM",
    "gn:dem":831,
    "gn:feature_class":"P",
    "gn:feature_code":"PPL",
    "gn:name":"Nerkin Nedzhirlu",
    "gn:population":0,
    "gn:timezone":"Asia/Yerevan",
    "iso:country":"AM",
    "name:und_x_variant":[
        "Nedzhirlu",
        "Nizhneye Nedzhirlu",
        "Nerkin Nedzhirlu"
    ],
    "wof:name":"Nerkin Nedzhirlu",
    "wof:placetype":"locality"
},
  "geometry": {"coordinates":[44.3925,40.07722],"type":"Point"}
}