{
  "type": "Feature",
  "properties": {
    "gn:admin1_code":"07",
    "gn:asciiname":"Art'ik",
    "gn:country_code":"AM",
    "gn:dem":1782,
    "gn:feature_class":"P",
    "gn:feature_code":"PPL",
    "gn:name":"Art\u2019ik",
    "gn:population":0,
    "gn:timezone":"Asia/Yerevan",
    "iso:country":"AM",
    "name:ara_x_preferred":[
        "\u0622\u0631\u062a\u064a\u0643"
    ],
    "name:azb_x_preferred":[
        "\u0622\u0631\u062a\u06cc\u06a9"
    ],
    "name:aze_x_preferred":[
        "\u018frtik"
    ],
    "name:bel_x_preferred":[
        "\u0410\u0440\u0442\u044b\u043a"
    ],
    "name:bul_x_preferred":[
        "\u0410\u0440\u0442\u0438\u043a"
    ],
    "name:che_x_preferred":[
        "\u0410\u0440\u0442\u0438\u043a"
    ],
    "name:deu_x_preferred":[
        "Artik"
    ],
    "name:ell_x_preferred":[
        "\u0391\u03c1\u03c4\u03af\u03ba"
    ],
    "name:eng_x_preferred":[
        "Art'ik"
    ],
    "name:epo_x_preferred":[
        "Artik"
    ],
    "name:est_x_preferred":[
        "Arthik"
    ],
    "name:fas_x_preferred":[
        "\u0622\u0631\u062a\u06cc\u06a9"
    ],
    "name:fra_x_preferred":[
        "Artik"
    ],
    "name:hsb_x_preferred":[
        "Artik"
    ],
    "name:hye_x_preferred":[
        "\u0531\u0580\u0569\u056b\u056f"
    ],
    "name:hyw_x_preferred":[
        "\u0531\u0580\u0569\u056b\u056f"
    ],
    "name:ind_x_preferred":[
        "Artik"
    ],
    "name:ita_x_preferred":[
        "Artik"
    ],
    "name:kat_x_preferred":[
        "\u10d0\u10e0\u10d7\u10d8\u10d9\u10d8"
    ],
    "name:lit_x_preferred":[
        "Artikas"
    ],
    "name:msa_x_preferred":[
        "Artik"
    ],
    "name:mzn_x_preferred":[
        "\u0622\u0631\u062a\u06cc\u06a9"
    ],
    "name:nld_x_preferred":[
        "Artik"
    ],
    "name:pol_x_preferred":[
        "Artik"
    ],
    "name:ron_x_preferred":[
        "Artik"
    ],
    "name:rus_x_preferred":[
        "\u0410\u0440\u0442\u0438\u043a"
    ],
    "name:sco_x_preferred":[
        "Artik"
    ],
    "name:spa_x_preferred":[
        "Artik"
    ],
    "name:srp_x_preferred":[
        "\u0410\u0440\u0442\u0438\u043a"
    ],
    "name:swa_x_preferred":[
        "Artik"
    ],
    "name:swe_x_preferred":[
        "Artik"
    ],
    "name:tur_x_preferred":[
        "Artik"
    ],
    "name:ukr_x_preferred":[
        "\u0410\u0440\u0442\u0456\u043a"
    ],
    "name:und_x_variant":[
        "Art\u2019ik"
    ],
    "name:vie_x_preferred":[
        "Artik"
    ],
    "wof:name":"Art'ik",
    "wof:placetype":"locality"
},
  "geometry": {"coordinates":[43.97207,40.61918],"type":"Point"}
}