{
  "type": "Feature",
  "properties": {
    "gn:admin1_code":"07",
    "gn:asciiname":"Art'ik",
    "gn:country_code":"AM",
    "gn:dem":1782,
    "gn:feature_class":"P",
    "gn:feature_code":"PPL",
    "gn:name":"Art\u2019ik",
    "gn:population":0,
    "gn:timezone":"Asia/Yerevan",
    "iso:country":"AM",
    "name:eng_x_preferred":[
        "Art'ik"
    ],
    "name:hye_x_preferred":[
        "\u0531\u0580\u0569\u056b\u056f"
    ],
    "name:rus_x_preferred":[
        "\u0410\u0440\u0442\u0438\u043a"
    ],
    "name:und_x_variant":[
        "Art\u2019ik"
    ],
    "wof:name":"Art'ik",
    "wof:placetype":"locality"
},
  "geometry": {"coordinates":[43.97207,40.61918],"type":"Point"}
}