{
  "type": "Feature",
  "properties": {
    "gn:admin1_code":"08",
    "gn:asciiname":"Verin Vach'agan",
    "gn:country_code":"AM",
    "gn:dem":1188,
    "gn:feature_class":"P",
    "gn:feature_code":"PPL",
    "gn:name":"Verin Vach\u2019agan",
    "gn:population":0,
    "gn:timezone":"Asia/Yerevan",
    "iso:country":"AM",
    "name:fas_x_preferred":[
        "\u0648\u0631\u06cc\u0646 \u0648\u0627\u0686\u0627\u06af\u0627\u0646"
    ],
    "name:hye_x_preferred":[
        "Verin Vach\u2019agan"
    ],
    "name:hye_x_variant":[
        "\u054e\u0565\u0580\u056b\u0576 \u054e\u0561\u0579\u0561\u0563\u0561\u0576"
    ],
    "name:und_x_variant":[
        "Verkhniy Vachagan",
        "Verin Vachagan"
    ],
    "wof:name":"Verin Vach'agan",
    "wof:placetype":"locality"
},
  "geometry": {"coordinates":[46.37506,39.18141],"type":"Point"}
}