{
  "type": "Feature",
  "properties": {
    "gn:admin1_code":"1.0",
    "gn:asciiname":"Mosei Surb",
    "gn:country_code":"AM",
    "gn:dem":1821,
    "gn:feature_class":"P",
    "gn:feature_code":"PPL",
    "gn:name":"Mosei Surb",
    "gn:population":0,
    "gn:timezone":"Asia/Yerevan",
    "iso:country":"AM",
    "name:hye_x_preferred":[
        "Mosei Surb"
    ],
    "name:hye_x_variant":[
        "\u0544\u0578\u057d\u0565\u056b \u054d\u0578\u0582\u0580\u0562"
    ],
    "wof:name":"Mosei Surb",
    "wof:placetype":"locality"
},
  "geometry": {"coordinates":[44.39447,40.4389],"type":"Point"}
}