{
  "type": "Feature",
  "properties": {
    "gn:admin1_code":"01",
    "gn:asciiname":"Aghdzk'",
    "gn:country_code":"AM",
    "gn:dem":1255,
    "gn:feature_class":"P",
    "gn:feature_code":"PPL",
    "gn:name":"Aghdzk\u2019",
    "gn:population":0,
    "gn:timezone":"Asia/Yerevan",
    "iso:country":"AM",
    "name:hye_x_preferred":[
        "Aghts\u2019k\u2019"
    ],
    "name:hye_x_variant":[
        "Aghdzk\u2019",
        "\u0531\u0572\u0571\u0584"
    ],
    "name:und_x_variant":[
        "Akhs",
        "Dzorap"
    ],
    "wof:name":"Aghdzk'",
    "wof:placetype":"locality"
},
  "geometry": {"coordinates":[44.25568,40.3139],"type":"Point"}
}