{
  "type": "Feature",
  "properties": {
    "gn:admin1_code":"8.0",
    "gn:asciiname":"Aygegortsakan Tntesut'yun",
    "gn:country_code":"AM",
    "gn:dem":1662,
    "gn:feature_class":"P",
    "gn:feature_code":"PPL",
    "gn:name":"Aygegortsakan Tntesut\u2019yun",
    "gn:population":0,
    "gn:timezone":"Asia/Yerevan",
    "iso:country":"AM",
    "name:hye_x_preferred":[
        "Aygegortsakan Tntesut\u2019yun"
    ],
    "name:hye_x_variant":[
        "\u0531\u0575\u0563\u0565\u0563\u0578\u0580\u056e\u0561\u056f\u0561\u0576 \u054f\u0576\u057f\u0565\u057d\u0578\u0582\u0569\u0575\u0578\u0582\u0576"
    ],
    "wof:name":"Aygegortsakan Tntesut'yun",
    "wof:placetype":"locality"
},
  "geometry": {"coordinates":[46.04169,39.53192],"type":"Point"}
}