{
  "type": "Feature",
  "properties": {
    "gn:admin1_code":"7.0",
    "gn:asciiname":"K'arot",
    "gn:country_code":"AM",
    "gn:dem":1727,
    "gn:feature_class":"P",
    "gn:feature_code":"PPL",
    "gn:name":"K\u2019arot",
    "gn:population":0,
    "gn:timezone":"Asia/Yerevan",
    "iso:country":"AM",
    "name:hye_x_preferred":[
        "K\u2019arot"
    ],
    "name:hye_x_variant":[
        "\u0554\u0561\u0580\u0578\u057f"
    ],
    "wof:name":"K'arot",
    "wof:placetype":"locality"
},
  "geometry": {"coordinates":[43.97229,40.79871],"type":"Point"}
}