{
  "type": "Feature",
  "properties": {
    "gn:admin1_code":"1.0",
    "gn:asciiname":"Ts'its'k'ar",
    "gn:country_code":"AM",
    "gn:dem":2343,
    "gn:feature_class":"P",
    "gn:feature_code":"PPL",
    "gn:name":"Ts\u2019its\u2019k\u2019ar",
    "gn:population":0,
    "gn:timezone":"Asia/Yerevan",
    "iso:country":"AM",
    "name:hye_x_preferred":[
        "Ts\u2019its\u2019k\u2019ar"
    ],
    "name:hye_x_variant":[
        "\u0551\u056b\u0581\u0584\u0561\u0580"
    ],
    "wof:name":"Ts'its'k'ar",
    "wof:placetype":"locality"
},
  "geometry": {"coordinates":[44.50848,40.56671],"type":"Point"}
}