{
  "type": "Feature",
  "properties": {
    "gn:admin1_code":"6.0",
    "gn:asciiname":"Kaputik",
    "gn:country_code":"AM",
    "gn:dem":2563,
    "gn:feature_class":"P",
    "gn:feature_code":"PPL",
    "gn:name":"Kaputik",
    "gn:population":0,
    "gn:timezone":"Asia/Yerevan",
    "iso:country":"AM",
    "name:hye_x_preferred":[
        "Kaputik"
    ],
    "name:hye_x_variant":[
        "\u053f\u0561\u057a\u0578\u0582\u057f\u056b\u056f"
    ],
    "wof:name":"Kaputik",
    "wof:placetype":"locality"
},
  "geometry": {"coordinates":[44.66107,40.78332],"type":"Point"}
}