{
  "type": "Feature",
  "properties": {
    "gn:admin1_code":"1.0",
    "gn:asciiname":"Averi Darer",
    "gn:country_code":"AM",
    "gn:dem":1833,
    "gn:feature_class":"P",
    "gn:feature_code":"PPL",
    "gn:name":"Averi Darer",
    "gn:population":0,
    "gn:timezone":"Asia/Yerevan",
    "iso:country":"AM",
    "name:hye_x_preferred":[
        "Averi Darer"
    ],
    "name:hye_x_variant":[
        "\u0531\u057e\u0565\u0580\u056b \u0564\u0561\u0580\u0565\u0580"
    ],
    "wof:name":"Averi Darer",
    "wof:placetype":"locality"
},
  "geometry": {"coordinates":[44.4223,40.45148],"type":"Point"}
}