{
  "type": "Feature",
  "properties": {
    "gn:admin1_code":"9.0",
    "gn:asciiname":"Berdadzori",
    "gn:country_code":"AM",
    "gn:dem":823,
    "gn:feature_class":"P",
    "gn:feature_code":"PPL",
    "gn:name":"Berdadzori",
    "gn:population":0,
    "gn:timezone":"Asia/Yerevan",
    "iso:country":"AM",
    "name:hye_x_preferred":[
        "Berdadzori"
    ],
    "name:hye_x_variant":[
        "\u0532\u0565\u0580\u0564\u0561\u0571\u0578\u0580\u056b"
    ],
    "wof:name":"Berdadzori",
    "wof:placetype":"locality"
},
  "geometry": {"coordinates":[45.4361,40.90832],"type":"Point"}
}