{
  "type": "Feature",
  "properties": {
    "gn:admin1_code":"7.0",
    "gn:asciiname":"Khamvari",
    "gn:country_code":"AM",
    "gn:dem":2252,
    "gn:feature_class":"P",
    "gn:feature_code":"PPL",
    "gn:name":"Khamvari",
    "gn:population":0,
    "gn:timezone":"Asia/Yerevan",
    "iso:country":"AM",
    "name:hye_x_preferred":[
        "Khamvari"
    ],
    "name:hye_x_variant":[
        "\u053d\u0561\u0574\u057e\u0561\u0580\u056b"
    ],
    "wof:name":"Khamvari",
    "wof:placetype":"locality"
},
  "geometry": {"coordinates":[44.07788,40.74872],"type":"Point"}
}