{
  "type": "Feature",
  "properties": {
    "gn:admin1_code":"6.0",
    "gn:asciiname":"Nerk'in Hats'ut",
    "gn:country_code":"AM",
    "gn:dem":1551,
    "gn:feature_class":"P",
    "gn:feature_code":"PPL",
    "gn:name":"Nerk\u2019in Hats\u2019ut",
    "gn:population":0,
    "gn:timezone":"Asia/Yerevan",
    "iso:country":"AM",
    "name:hye_x_preferred":[
        "Nerk\u2019in Hats\u2019ut"
    ],
    "name:hye_x_variant":[
        "\u0546\u0565\u0580\u0584\u056b\u0576 \u0540\u0561\u0581\u0578\u0582\u057f"
    ],
    "wof:name":"Nerk'in Hats'ut",
    "wof:placetype":"locality"
},
  "geometry": {"coordinates":[44.54449,41.04169],"type":"Point"}
}