{
  "type": "Feature",
  "properties": {
    "gn:admin1_code":"8.0",
    "gn:asciiname":"P'oser",
    "gn:country_code":"AM",
    "gn:dem":2369,
    "gn:feature_class":"P",
    "gn:feature_code":"PPL",
    "gn:name":"P\u2019oser",
    "gn:population":0,
    "gn:timezone":"Asia/Yerevan",
    "iso:country":"AM",
    "name:hye_x_preferred":[
        "P\u2019oser"
    ],
    "name:hye_x_variant":[
        "\u0553\u0578\u057d\u0565\u0580"
    ],
    "wof:name":"P'oser",
    "wof:placetype":"locality"
},
  "geometry": {"coordinates":[46.23889000000001,39.25568],"type":"Point"}
}