{
  "type": "Feature",
  "properties": {
    "gn:gn_country":"AM",
    "gn:gn_fcode":"PPL",
    "gn:gn_pop":3472,
    "gn:population":3472,
    "iso:country":"AM",
    "name:ara_x_preferred":[
        "\u0647\u0648\u0641\u0627\u062a\u0627\u0634\u0627\u062a\u060c \u0623\u0631\u0627\u0631\u0627\u062a"
    ],
    "name:arm_x_preferred":[
        "\u0540\u0578\u057e\u057f\u0561\u0577\u0561\u057f"
    ],
    "name:bel_x_preferred":[
        "\u0421\u044f\u043b\u043e \u0410\u045e\u0442\u0430\u0448\u0430\u0442"
    ],
    "name:dut_x_preferred":[
        "Hovtashat"
    ],
    "name:eng_x_preferred":[
        "Hovtashat"
    ],
    "name:fre_x_preferred":[
        "Hovtashat"
    ],
    "name:geo_x_preferred":[
        "\u10dd\u10d5\u10e2\u10d0\u10e8\u10d0\u10e2\u10d8"
    ],
    "name:hye_x_preferred":[
        "Hovtashat"
    ],
    "name:hye_x_variant":[
        "\u0540\u0578\u057e\u057f\u0561\u0577\u0561\u057f"
    ],
    "name:ita_x_preferred":[
        "Hovta\u0161at"
    ],
    "name:may_x_preferred":[
        "Hovtashat"
    ],
    "name:nan_x_preferred":[
        "Hovtashat"
    ],
    "name:per_x_preferred":[
        "\u0647\u0648\u0648\u062a\u0627\u0634\u0627\u062a"
    ],
    "name:rus_x_preferred":[
        "\u041e\u0432\u0442\u0430\u0448\u0430\u0442"
    ],
    "name:swe_x_preferred":[
        "Hovtashat"
    ],
    "name:ukr_x_preferred":[
        "\u041e\u0432\u0442\u0430\u0448\u0430\u0442"
    ],
    "name:unk_x_variant":[
        "Ovtashat"
    ],
    "name:vie_x_preferred":[
        "Hovtashat"
    ],
    "qs_pg:aaroncc":"AM",
    "qs_pg:gn_country":"AM",
    "qs_pg:gn_fcode":"PPL",
    "qs_pg:gn_pop":3472,
    "qs_pg:name":"Hovtashat",
    "qs_pg:photos_9r":0,
    "qs_pg:photos_sr":0,
    "qs_pg:pop_sr":4,
    "qs_pg:qs_pg_placetype":"locality",
    "wof:name":"Hovtashat",
    "wof:placetype":"locality",
    "wof:population":3472
},
  "geometry": {"coordinates":[44.33891,40.10328],"type":"Point"}
}