{
  "type": "Feature",
  "properties": {
    "gn:admin1_code":"3.0",
    "gn:asciiname":"Khach'k'ar",
    "gn:country_code":"AM",
    "gn:dem":857,
    "gn:feature_class":"P",
    "gn:feature_code":"PPL",
    "gn:name":"Khach\u2019k\u2019ar",
    "gn:population":0,
    "gn:timezone":"Asia/Yerevan",
    "iso:country":"AM",
    "name:hye_x_preferred":[
        "Khach\u2019k\u2019ar"
    ],
    "name:hye_x_variant":[
        "\u053d\u0561\u0579\u0584\u0561\u0580"
    ],
    "wof:name":"Khach'k'ar",
    "wof:placetype":"locality"
},
  "geometry": {"coordinates":[44.06531,40.05548],"type":"Point"}
}