{
  "type": "Feature",
  "properties": {
    "gn:admin1_code":"02",
    "gn:asciiname":"Shoghakan",
    "gn:country_code":"AM",
    "gn:dem":825,
    "gn:feature_class":"P",
    "gn:feature_code":"PPL",
    "gn:name":"Shoghakan",
    "gn:population":0,
    "gn:timezone":"Asia/Yerevan",
    "iso:country":"AM",
    "name:hye_x_preferred":[
        "Shoghakan"
    ],
    "name:hye_x_variant":[
        "\u0547\u0578\u0572\u0561\u056f\u0561\u0576"
    ],
    "name:rus_x_preferred":[
        "Pos\u00eblok Imeni Kalinina"
    ],
    "wof:name":"Shoghakan",
    "wof:placetype":"locality"
},
  "geometry": {"coordinates":[44.4057,40.01111],"type":"Point"}
}