{
  "type": "Feature",
  "properties": {
    "gn:asciiname":"Kentron",
    "gn:country_code":"AM",
    "gn:dem":997,
    "gn:feature_class":"P",
    "gn:feature_code":"PPL",
    "gn:name":"Kentron",
    "gn:population":0,
    "gn:timezone":"Asia/Yerevan",
    "iso:country":"AM",
    "name:eng_x_preferred":[
        "Kentron District"
    ],
    "name:epo_x_preferred":[
        "Kentrono"
    ],
    "name:fas_x_preferred":[
        "\u0646\u0627\u062d\u06cc\u0647 \u06a9\u0646\u062a\u0631\u0648\u0646"
    ],
    "name:hye_x_preferred":[
        "\u053f\u0565\u0576\u057f\u0580\u0578\u0576"
    ],
    "name:kat_x_preferred":[
        "\u10d9\u10d4\u10dc\u10e2\u10e0\u10dd\u10dc\u10d8\u10e1 \u10e0\u10d0\u10d8\u10dd\u10dc\u10d8"
    ],
    "wof:name":"Kentron",
    "wof:placetype":"locality"
},
  "geometry": {"coordinates":[44.51303,40.17806],"type":"Point"}
}