{
  "type": "Feature",
  "properties": {
    "gn:asciiname":"Kentron",
    "gn:country_code":"AM",
    "gn:dem":997,
    "gn:feature_class":"P",
    "gn:feature_code":"PPL",
    "gn:name":"Kentron",
    "gn:population":0,
    "gn:timezone":"Asia/Yerevan",
    "iso:country":"AM",
    "name:ara_x_preferred":[
        "\u0645\u0642\u0627\u0637\u0639\u0629 \u0643\u064a\u0646\u062a\u0631\u0648\u0646"
    ],
    "name:deu_x_preferred":[
        "Kentron"
    ],
    "name:eng_x_preferred":[
        "Kentron District"
    ],
    "name:epo_x_preferred":[
        "Kentrono"
    ],
    "name:fas_x_preferred":[
        "\u0646\u0627\u062d\u06cc\u0647 \u06a9\u0646\u062a\u0631\u0648\u0646"
    ],
    "name:fra_x_preferred":[
        "Kentron"
    ],
    "name:hye_x_preferred":[
        "\u053f\u0565\u0576\u057f\u0580\u0578\u0576"
    ],
    "name:hyw_x_preferred":[
        "\u053f\u0565\u0564\u0580\u0578\u0576"
    ],
    "name:ita_x_preferred":[
        "Kentron"
    ],
    "name:kat_x_preferred":[
        "\u10d9\u10d4\u10dc\u10e2\u10e0\u10dd\u10dc\u10d8\u10e1 \u10e0\u10d0\u10d8\u10dd\u10dc\u10d8"
    ],
    "name:nld_x_preferred":[
        "Kentron"
    ],
    "name:rus_x_preferred":[
        "\u041a\u0435\u043d\u0442\u0440\u043e\u043d"
    ],
    "name:sco_x_preferred":[
        "Kentron"
    ],
    "name:swe_x_preferred":[
        "Kentron"
    ],
    "name:tel_x_preferred":[
        "\u0c15\u0c46\u0c02\u0c1f\u0c4d\u0c30\u0c3e\u0c28\u0c4d \u0c1c\u0c3f\u0c32\u0c4d\u0c32\u0c3e"
    ],
    "name:tur_x_preferred":[
        "Kentron"
    ],
    "wof:name":"Kentron",
    "wof:placetype":"locality"
},
  "geometry": {"coordinates":[44.51303,40.17806],"type":"Point"}
}