{
  "type": "Feature",
  "properties": {
    "gn:admin1_code":"6.0",
    "gn:asciiname":"Bover",
    "gn:country_code":"AM",
    "gn:dem":881,
    "gn:feature_class":"P",
    "gn:feature_code":"PPL",
    "gn:name":"Bover",
    "gn:population":0,
    "gn:timezone":"Asia/Yerevan",
    "iso:country":"AM",
    "name:hye_x_preferred":[
        "Bover"
    ],
    "name:hye_x_variant":[
        "\u0532\u0578\u057e\u0565\u0580"
    ],
    "wof:name":"Bover",
    "wof:placetype":"locality"
},
  "geometry": {"coordinates":[44.82788,41.10828],"type":"Point"}
}