{
  "type": "Feature",
  "properties": {
    "gn:admin1_code":"2.0",
    "gn:asciiname":"Moshaghbyur",
    "gn:country_code":"AM",
    "gn:dem":1915,
    "gn:feature_class":"P",
    "gn:feature_code":"PPL",
    "gn:name":"Moshaghbyur",
    "gn:population":0,
    "gn:timezone":"Asia/Yerevan",
    "iso:country":"AM",
    "name:hye_x_preferred":[
        "Moshaghbyur"
    ],
    "name:hye_x_variant":[
        "\u0544\u0578\u0577\u0561\u0572\u0562\u0575\u0578\u0582\u0580"
    ],
    "wof:name":"Moshaghbyur",
    "wof:placetype":"locality"
},
  "geometry": {"coordinates":[44.91388,39.83612],"type":"Point"}
}