{
  "type": "Feature",
  "properties": {
    "gn:admin1_code":"6.0",
    "gn:asciiname":"Chghut",
    "gn:country_code":"AM",
    "gn:dem":1303,
    "gn:feature_class":"P",
    "gn:feature_code":"PPL",
    "gn:name":"Chghut",
    "gn:population":0,
    "gn:timezone":"Asia/Yerevan",
    "iso:country":"AM",
    "name:hye_x_preferred":[
        "Chghut"
    ],
    "name:hye_x_variant":[
        "\u0543\u0572\u0578\u0582\u057f"
    ],
    "wof:name":"Chghut",
    "wof:placetype":"locality"
},
  "geometry": {"coordinates":[44.73053,40.93048],"type":"Point"}
}