{
  "type": "Feature",
  "properties": {
    "gn:admin1_code":"11.0",
    "gn:asciiname":"Azatamartik Harut'yunin",
    "gn:country_code":"AM",
    "gn:dem":1216,
    "gn:feature_class":"P",
    "gn:feature_code":"PPL",
    "gn:name":"Azatamartik Harut\u2019yunin",
    "gn:population":0,
    "gn:timezone":"Asia/Yerevan",
    "iso:country":"AM",
    "name:hye_x_preferred":[
        "Azatamartik Harut\u2019yunin"
    ],
    "name:hye_x_variant":[
        "\u0531\u0566\u0561\u057f\u0561\u0574\u0561\u0580\u057f\u056b\u056f \u0540\u0561\u0580\u0578\u0582\u0569\u0575\u0578\u0582\u0576\u056b\u0576"
    ],
    "wof:name":"Azatamartik Harut'yunin",
    "wof:placetype":"locality"
},
  "geometry": {"coordinates":[44.53332,40.20288],"type":"Point"}
}