{
  "type": "Feature",
  "properties": {
    "gn:admin1_code":"6.0",
    "gn:asciiname":"Tlot",
    "gn:country_code":"AM",
    "gn:dem":1885,
    "gn:feature_class":"P",
    "gn:feature_code":"PPL",
    "gn:name":"Tlot",
    "gn:population":0,
    "gn:timezone":"Asia/Yerevan",
    "iso:country":"AM",
    "name:hye_x_preferred":[
        "Tlot"
    ],
    "name:hye_x_variant":[
        "\u054f\u056c\u0578\u057f"
    ],
    "wof:name":"Tlot",
    "wof:placetype":"locality"
},
  "geometry": {"coordinates":[44.64447,40.84589],"type":"Point"}
}