{
  "type": "Feature",
  "properties": {
    "gn:admin1_code":"2.0",
    "gn:asciiname":"Avanik",
    "gn:country_code":"AM",
    "gn:dem":1558,
    "gn:feature_class":"P",
    "gn:feature_code":"PPL",
    "gn:name":"Avanik",
    "gn:population":0,
    "gn:timezone":"Asia/Yerevan",
    "iso:country":"AM",
    "name:hye_x_preferred":[
        "Avanik"
    ],
    "name:hye_x_variant":[
        "\u0531\u057e\u0561\u0576\u056b\u056f"
    ],
    "wof:name":"Avanik",
    "wof:placetype":"locality"
},
  "geometry": {"coordinates":[44.83612,40.07233],"type":"Point"}
}