{
  "type": "Feature",
  "properties": {
    "gn:admin1_code":"03",
    "gn:asciiname":"Azatavan",
    "gn:country_code":"AM",
    "gn:dem":851,
    "gn:feature_class":"P",
    "gn:feature_code":"PPL",
    "gn:name":"Azatavan",
    "gn:population":0,
    "gn:timezone":"Asia/Yerevan",
    "iso:country":"AM",
    "name:fas_x_preferred":[
        "\u0622\u0632\u0627\u062a\u0627\u0648\u0627\u0646"
    ],
    "name:hye_x_preferred":[
        "\u0531\u0566\u0561\u057f\u0561\u057e\u0561\u0576"
    ],
    "wof:name":"Azatavan",
    "wof:placetype":"locality"
},
  "geometry": {"coordinates":[44.07788,40.13611],"type":"Point"}
}