{
  "type": "Feature",
  "properties": {
    "gn:admin1_code":"00",
    "gn:asciiname":"Sokhgom",
    "gn:country_code":"AM",
    "gn:dem":2673,
    "gn:feature_class":"P",
    "gn:feature_code":"PPL",
    "gn:name":"Sokhgom",
    "gn:population":0,
    "gn:timezone":"Asia/Yerevan",
    "iso:country":"AM",
    "name:hye_x_preferred":[
        "Sokhgom"
    ],
    "name:hye_x_variant":[
        "\u054d\u0578\u056d\u0563\u0578\u0574"
    ],
    "wof:name":"Sokhgom",
    "wof:placetype":"locality"
},
  "geometry": {"coordinates":[45.51392,39.96948],"type":"Point"}
}