{
  "type": "Feature",
  "properties": {
    "gn:admin1_code":"8.0",
    "gn:asciiname":"K'ari Glukh",
    "gn:country_code":"AM",
    "gn:dem":1865,
    "gn:feature_class":"P",
    "gn:feature_code":"PPL",
    "gn:name":"K\u2019ari Glukh",
    "gn:population":0,
    "gn:timezone":"Asia/Yerevan",
    "iso:country":"AM",
    "name:hye_x_preferred":[
        "K\u2019ari Glukh"
    ],
    "name:hye_x_variant":[
        "\u0554\u0561\u0580\u056b \u0563\u056c\u0578\u0582\u056d"
    ],
    "wof:name":"K'ari Glukh",
    "wof:placetype":"locality"
},
  "geometry": {"coordinates":[46.16107,38.91388],"type":"Point"}
}