{
  "type": "Feature",
  "properties": {
    "gn:admin1_code":"9.0",
    "gn:asciiname":"T'agher",
    "gn:country_code":"AM",
    "gn:dem":1687,
    "gn:feature_class":"P",
    "gn:feature_code":"PPL",
    "gn:name":"T\u2019agher",
    "gn:population":0,
    "gn:timezone":"Asia/Yerevan",
    "iso:country":"AM",
    "name:hye_x_preferred":[
        "T\u2019agher"
    ],
    "name:hye_x_variant":[
        "\u0539\u0561\u0572\u0565\u0580"
    ],
    "wof:name":"T'agher",
    "wof:placetype":"locality"
},
  "geometry": {"coordinates":[45.40692,40.75153],"type":"Point"}
}