{
  "type": "Feature",
  "properties": {
    "gn:admin1_code":"07",
    "gn:asciiname":"Paghakn",
    "gn:country_code":"AM",
    "gn:dem":2033,
    "gn:feature_class":"P",
    "gn:feature_code":"PPL",
    "gn:name":"Paghakn",
    "gn:population":0,
    "gn:timezone":"Asia/Yerevan",
    "iso:country":"AM",
    "name:hye_x_preferred":[
        "\u054a\u0561\u0572\u0561\u056f\u0576"
    ],
    "name:und_x_variant":[
        "Shurabad",
        "Pahakn",
        "Sultanabad",
        "Paghakn"
    ],
    "wof:name":"Paghakn",
    "wof:placetype":"locality"
},
  "geometry": {"coordinates":[43.65299,41.06454],"type":"Point"}
}