{
  "type": "Feature",
  "properties": {
    "iso:country":"AM",
    "name:aze_x_preferred":[
        "Marqara"
    ],
    "name:ceb_x_preferred":[
        "Margara"
    ],
    "name:eng_x_preferred":[
        "Margara"
    ],
    "name:fas_x_preferred":[
        "\u0645\u0627\u0631\u06af\u0627\u0631\u0627"
    ],
    "name:fra_x_preferred":[
        "Margara"
    ],
    "name:hye_x_preferred":[
        "\u0544\u0561\u0580\u0563\u0561\u0580\u0561"
    ],
    "name:hye_x_variant":[
        "Margara"
    ],
    "name:ita_x_preferred":[
        "Margara"
    ],
    "name:kat_x_preferred":[
        "\u10db\u10d0\u10e0\u10d2\u10d0\u10e0\u10d0"
    ],
    "name:msa_x_preferred":[
        "Margara"
    ],
    "name:nan_x_preferred":[
        "Margara"
    ],
    "name:nld_x_preferred":[
        "Margara"
    ],
    "name:rus_x_preferred":[
        "\u041c\u0430\u0440\u043a\u0430\u0440\u0430"
    ],
    "name:rus_x_variant":[
        "\u041c\u0430\u0440\u0433\u0430\u0440\u0430"
    ],
    "name:sco_x_preferred":[
        "Margara"
    ],
    "name:spa_x_preferred":[
        "Margara"
    ],
    "name:swe_x_preferred":[
        "Margara"
    ],
    "name:ukr_x_preferred":[
        "\u041c\u0430\u0440\u0491\u0430\u0440\u0430"
    ],
    "name:vie_x_preferred":[
        "Margara"
    ],
    "name:zho_min_nan_x_preferred":[
        "Margara"
    ],
    "qs:gn_country":"AM",
    "qs:gn_fcode":"PPL",
    "qs:gn_pop":1360,
    "qs:name":"Markara",
    "qs:name_adm0":"Armenia",
    "qs:name_adm1":"Armavir",
    "qs:photos":0,
    "qs:photos_1k":0,
    "qs:photos_9k":0,
    "qs:photos_9r":0,
    "qs:photos_all":0,
    "qs:photos_sr":0,
    "qs:placetype":"Town",
    "qs:pop_sr":"3",
    "qs:woe_adm0":23424743,
    "wd:wordcount":130,
    "wof:name":"Markara",
    "wof:placetype":"locality",
    "wof:population":1360
},
  "geometry": {"coordinates":[44.17709,40.03351],"type":"Point"}
}