{
  "type": "Feature",
  "properties": {
    "gn:admin1_code":"0.0",
    "gn:asciiname":"Ayritap'",
    "gn:country_code":"AM",
    "gn:dem":1198,
    "gn:feature_class":"P",
    "gn:feature_code":"PPL",
    "gn:name":"Ayritap\u2019",
    "gn:population":0,
    "gn:timezone":"Asia/Yerevan",
    "iso:country":"AM",
    "name:hye_x_preferred":[
        "Ayritap\u2019"
    ],
    "name:hye_x_variant":[
        "\u0531\u0575\u0580\u056b\u057f\u0561\u0583"
    ],
    "wof:name":"Ayritap'",
    "wof:placetype":"locality"
},
  "geometry": {"coordinates":[43.73187,40.16107],"type":"Point"}
}