{
  "type": "Feature",
  "properties": {
    "gn:admin1_code":"4.0",
    "gn:asciiname":"Sevak'ar",
    "gn:country_code":"AM",
    "gn:dem":2002,
    "gn:feature_class":"P",
    "gn:feature_code":"PPL",
    "gn:name":"Sevak\u2019ar",
    "gn:population":0,
    "gn:timezone":"Asia/Yerevan",
    "iso:country":"AM",
    "name:hye_x_preferred":[
        "Sevak\u2019ar"
    ],
    "name:hye_x_variant":[
        "\u054d\u0587\u0561\u0584\u0561\u0580"
    ],
    "wof:name":"Sevak'ar",
    "wof:placetype":"locality"
},
  "geometry": {"coordinates":[45.09729,40.59729],"type":"Point"}
}