{
  "type": "Feature",
  "properties": {
    "gn:admin1_code":"4.0",
    "gn:asciiname":"Gevoyi Avetaran",
    "gn:country_code":"AM",
    "gn:dem":1946,
    "gn:feature_class":"P",
    "gn:feature_code":"PPL",
    "gn:name":"Gevoyi Avetaran",
    "gn:population":0,
    "gn:timezone":"Asia/Yerevan",
    "iso:country":"AM",
    "name:hye_x_preferred":[
        "Gevoyi Avetaran"
    ],
    "name:hye_x_variant":[
        "\u0533\u0587\u0578\u0575\u056b \u0531\u057e\u0565\u057f\u0561\u0580\u0561\u0576"
    ],
    "wof:name":"Gevoyi Avetaran",
    "wof:placetype":"locality"
},
  "geometry": {"coordinates":[45.50848,40.15008],"type":"Point"}
}