{
  "type": "Feature",
  "properties": {
    "gn:admin1_code":"9.0",
    "gn:asciiname":"K'aghak'ayin",
    "gn:country_code":"AM",
    "gn:dem":1261,
    "gn:feature_class":"P",
    "gn:feature_code":"PPL",
    "gn:name":"K\u2019aghak\u2019ayin",
    "gn:population":0,
    "gn:timezone":"Asia/Yerevan",
    "iso:country":"AM",
    "name:hye_x_preferred":[
        "K\u2019aghak\u2019ayin"
    ],
    "name:hye_x_variant":[
        "\u0554\u0561\u0572\u0561\u0584\u0561\u0575\u056b\u0576"
    ],
    "wof:name":"K'aghak'ayin",
    "wof:placetype":"locality"
},
  "geometry": {"coordinates":[44.8529,40.73889000000001],"type":"Point"}
}