{
  "type": "Feature",
  "properties": {
    "gn:admin1_code":"4.0",
    "gn:asciiname":"Gavarrni",
    "gn:country_code":"AM",
    "gn:dem":2029,
    "gn:feature_class":"P",
    "gn:feature_code":"PPL",
    "gn:name":"Gavarrni",
    "gn:population":0,
    "gn:timezone":"Asia/Yerevan",
    "iso:country":"AM",
    "name:hye_x_preferred":[
        "Gavarrni"
    ],
    "name:hye_x_variant":[
        "\u0533\u0561\u057e\u0561\u057c\u0576\u056b"
    ],
    "wof:name":"Gavarrni",
    "wof:placetype":"locality"
},
  "geometry": {"coordinates":[45.08472,40.32648],"type":"Point"}
}