{
  "type": "Feature",
  "properties": {
    "gn:admin1_code":"4.0",
    "gn:asciiname":"Mshaknots'",
    "gn:country_code":"AM",
    "gn:dem":2035,
    "gn:feature_class":"P",
    "gn:feature_code":"PPL",
    "gn:name":"Mshaknots\u2019",
    "gn:population":0,
    "gn:timezone":"Asia/Yerevan",
    "iso:country":"AM",
    "name:hye_x_preferred":[
        "Mshaknots\u2019"
    ],
    "name:hye_x_variant":[
        "\u0544\u0577\u0561\u056f\u0576\u0578\u0581"
    ],
    "wof:name":"Mshaknots'",
    "wof:placetype":"locality"
},
  "geometry": {"coordinates":[45.39868,40.5611],"type":"Point"}
}