{
  "type": "Feature",
  "properties": {
    "gn:admin1_code":"6.0",
    "gn:asciiname":"Shahumyan S.",
    "gn:country_code":"AM",
    "gn:dem":1405,
    "gn:feature_class":"P",
    "gn:feature_code":"PPL",
    "gn:name":"Shahumyan S.",
    "gn:population":0,
    "gn:timezone":"Asia/Yerevan",
    "iso:country":"AM",
    "name:hye_x_preferred":[
        "Shahumyan S."
    ],
    "name:hye_x_variant":[
        "\u0547\u0561\u0570\u0578\u0582\u0574\u0575\u0561\u0576 \u054d."
    ],
    "wof:name":"Shahumyan S.",
    "wof:placetype":"neighbourhood"
},
  "geometry": {"coordinates":[44.3847,41.0097],"type":"Point"}
}