{
  "type": "Feature",
  "properties": {
    "gn:admin1_code":"1.0",
    "gn:asciiname":"Davoyi",
    "gn:country_code":"AM",
    "gn:dem":1790,
    "gn:feature_class":"P",
    "gn:feature_code":"PPL",
    "gn:name":"Davoyi",
    "gn:population":0,
    "gn:timezone":"Asia/Yerevan",
    "iso:country":"AM",
    "name:hye_x_preferred":[
        "Davoyi"
    ],
    "name:hye_x_variant":[
        "\u0534\u0561\u057e\u0578\u0575\u056b"
    ],
    "wof:name":"Davoyi",
    "wof:placetype":"locality"
},
  "geometry": {"coordinates":[44.44452,40.45288],"type":"Point"}
}