{
  "type": "Feature",
  "properties": {
    "gn:admin1_code":"10",
    "gn:asciiname":"T'bghlanots'",
    "gn:country_code":"AM",
    "gn:dem":1948,
    "gn:feature_class":"P",
    "gn:feature_code":"PPL",
    "gn:name":"T\u2019bghlanots\u2019",
    "gn:population":0,
    "gn:timezone":"Asia/Yerevan",
    "iso:country":"AM",
    "name:hye_x_preferred":[
        "T\u2019bghlanots\u2019"
    ],
    "name:hye_x_variant":[
        "\u0539\u0562\u0572\u056c\u0561\u0576\u0578\u0581"
    ],
    "wof:name":"T'bghlanots'",
    "wof:placetype":"locality"
},
  "geometry": {"coordinates":[45.52789,39.79449],"type":"Point"}
}