{
  "type": "Feature",
  "properties": {
    "iso:country":"AM",
    "name:arm_x_preferred":[
        "\u0531\u056c\u0561\u0577\u056f\u0565\u0580\u057f"
    ],
    "name:aze_x_preferred":[
        "K\u0259rimarx"
    ],
    "name:bel_x_preferred":[
        "\u0421\u044f\u043b\u043e \u0410\u043b\u0430\u0448\u043a\u0435\u0440\u0442"
    ],
    "name:dut_x_preferred":[
        "Sovetakan"
    ],
    "name:eng_x_preferred":[
        "Sovetakan"
    ],
    "name:fre_x_preferred":[
        "Alashkert"
    ],
    "name:geo_x_preferred":[
        "\u10d0\u10da\u10d0\u10e8\u10d9\u10d4\u10e0\u10e2\u10d8"
    ],
    "name:hye_x_preferred":[
        "Alashkert"
    ],
    "name:hye_x_variant":[
        "\u0531\u056c\u0561\u0577\u056f\u0565\u0580\u057f"
    ],
    "name:ita_x_preferred":[
        "Alashkert"
    ],
    "name:may_x_preferred":[
        "Sovetakan"
    ],
    "name:per_x_preferred":[
        "\u0627\u0644\u0627\u0634\u06a9\u0631\u062a\u060c \u0627\u0631\u0645\u0646\u0633\u062a\u0627\u0646"
    ],
    "name:rus_x_preferred":[
        "\u0421\u043e\u0432\u0435\u0442\u0430\u043a\u0430\u043d"
    ],
    "name:sco_x_preferred":[
        "Sovetakan"
    ],
    "name:ukr_x_preferred":[
        "\u0410\u043b\u0430\u0448\u043a\u0435\u0440\u0442"
    ],
    "name:unk_x_variant":[
        "Kyarimarkh"
    ],
    "name:vie_x_preferred":[
        "Alashkert"
    ],
    "qs:gn_country":"AM",
    "qs:gn_fcode":"PPL",
    "qs:gn_pop":1613,
    "qs:name":"Sovetakan",
    "qs:name_adm0":"Armenia",
    "qs:name_adm1":"Armavir",
    "qs:photos":0,
    "qs:photos_1k":0,
    "qs:photos_9k":1,
    "qs:photos_9r":1,
    "qs:photos_all":6,
    "qs:photos_sr":0,
    "qs:placetype":"Town",
    "qs:pop_sr":"3",
    "qs:woe_adm0":23424743,
    "wof:name":"Sovetakan",
    "wof:placetype":"locality",
    "wof:population":1613
},
  "geometry": {"coordinates":[44.05108,40.10712],"type":"Point"}
}