{
  "type": "Feature",
  "properties": {
    "gn:admin1_code":"7.0",
    "gn:asciiname":"Averak",
    "gn:country_code":"AM",
    "gn:dem":2129,
    "gn:feature_class":"P",
    "gn:feature_code":"PPL",
    "gn:name":"Averak",
    "gn:population":0,
    "gn:timezone":"Asia/Yerevan",
    "iso:country":"AM",
    "name:hye_x_preferred":[
        "Averak"
    ],
    "name:hye_x_variant":[
        "\u0531\u057e\u0565\u0580\u0561\u056f"
    ],
    "wof:name":"Averak",
    "wof:placetype":"locality"
},
  "geometry": {"coordinates":[43.71527,41.01111],"type":"Point"}
}