{
  "type": "Feature",
  "properties": {
    "gn:admin1_code":"7.0",
    "gn:asciiname":"Shenaver",
    "gn:country_code":"AM",
    "gn:dem":2071,
    "gn:feature_class":"P",
    "gn:feature_code":"PPL",
    "gn:name":"Shenaver",
    "gn:population":0,
    "gn:timezone":"Asia/Yerevan",
    "iso:country":"AM",
    "name:hye_x_preferred":[
        "Shenaver"
    ],
    "name:hye_x_variant":[
        "\u0547\u0565\u0576\u0561\u057e\u0565\u0580"
    ],
    "wof:name":"Shenaver",
    "wof:placetype":"locality"
},
  "geometry": {"coordinates":[43.94452,40.95288],"type":"Point"}
}