{
  "type": "Feature",
  "properties": {
    "gn:admin1_code":"1.0",
    "gn:asciiname":"Khat'un Anahit",
    "gn:country_code":"AM",
    "gn:dem":2020,
    "gn:feature_class":"P",
    "gn:feature_code":"PPL",
    "gn:name":"Khat\u2019un Anahit",
    "gn:population":0,
    "gn:timezone":"Asia/Yerevan",
    "iso:country":"AM",
    "name:hye_x_preferred":[
        "Khat\u2019un Anahit"
    ],
    "name:hye_x_variant":[
        "\u053d\u0561\u0569\u0578\u0582\u0576 \u0531\u0576\u0561\u0570\u056b\u057f"
    ],
    "wof:name":"Khat'un Anahit",
    "wof:placetype":"locality"
},
  "geometry": {"coordinates":[44.4917,40.57507],"type":"Point"}
}