{
  "type": "Feature",
  "properties": {
    "gn:gn_country":"AM",
    "gn:gn_fcode":"PPL",
    "gn:gn_pop":1597,
    "gn:population":1597,
    "iso:country":"AM",
    "name:arm_x_preferred":[
        "\u0533\u0565\u0572\u0561\u0574\u0561\u057e\u0561\u0576"
    ],
    "name:aze_x_preferred":[
        "\u015e\u0259hriz"
    ],
    "name:dut_x_preferred":[
        "Geghamavan"
    ],
    "name:eng_x_preferred":[
        "Geghamavan"
    ],
    "name:fre_x_preferred":[
        "Geghamavan"
    ],
    "name:geo_x_preferred":[
        "\u10d2\u10d4\u10e6\u10d0\u10db\u10d0\u10d5\u10d0\u10dc\u10d8"
    ],
    "name:hye_x_preferred":[
        "\u0533\u0565\u0572\u0561\u0574\u0561\u057e\u0561\u0576"
    ],
    "name:ita_x_preferred":[
        "Geghamavan"
    ],
    "name:may_x_preferred":[
        "Geghamavan"
    ],
    "name:per_x_preferred":[
        "\u06af\u063a\u0627\u0645\u0627\u0648\u0627\u0646"
    ],
    "name:rus_x_preferred":[
        "\u0413\u0435\u0433\u0430\u043c\u0430\u0432\u0430\u043d"
    ],
    "name:sco_x_preferred":[
        "Geghamavan"
    ],
    "name:swe_x_preferred":[
        "Geghamavan"
    ],
    "name:ukr_x_preferred":[
        "\u0490\u0435\u0433\u0430\u043c\u0430\u0432\u0430\u043d"
    ],
    "name:unk_x_variant":[
        "Shagriz"
    ],
    "name:vie_x_preferred":[
        "Geghamavan"
    ],
    "qs_pg:aaroncc":"AM",
    "qs_pg:gn_country":"AM",
    "qs_pg:gn_fcode":"PPL",
    "qs_pg:gn_pop":1597,
    "qs_pg:name":"Geghamavan",
    "qs_pg:photos_9r":0,
    "qs_pg:photos_sr":0,
    "qs_pg:pop_sr":3,
    "qs_pg:qs_pg_placetype":"locality",
    "wof:name":"Geghamavan",
    "wof:placetype":"locality",
    "wof:population":1597
},
  "geometry": {"coordinates":[44.8879,40.5634],"type":"Point"}
}