{
  "type": "Feature",
  "properties": {
    "gn:admin1_code":"10",
    "gn:asciiname":"Vardablur",
    "gn:country_code":"AM",
    "gn:dem":2235,
    "gn:feature_class":"P",
    "gn:feature_code":"PPL",
    "gn:name":"Vardablur",
    "gn:population":0,
    "gn:timezone":"Asia/Yerevan",
    "iso:country":"AM",
    "name:hye_x_preferred":[
        "Vardablur"
    ],
    "name:hye_x_variant":[
        "\u054e\u0561\u0580\u0564\u0561\u0562\u056c\u0578\u0582\u0580"
    ],
    "wof:name":"Vardablur",
    "wof:placetype":"locality"
},
  "geometry": {"coordinates":[45.36249,39.66809],"type":"Point"}
}