{
  "type": "Feature",
  "properties": {
    "gn:admin1_code":"10",
    "gn:asciiname":"Vardablur",
    "gn:country_code":"AM",
    "gn:dem":2235,
    "gn:feature_class":"P",
    "gn:feature_code":"PPL",
    "gn:name":"Vardablur",
    "gn:population":0,
    "gn:timezone":"Asia/Yerevan",
    "iso:country":"AM",
    "name:ceb_x_preferred":[
        "Vardablur"
    ],
    "name:fra_x_preferred":[
        "Vardablur"
    ],
    "name:hye_x_preferred":[
        "Vardablur"
    ],
    "name:hye_x_variant":[
        "\u054e\u0561\u0580\u0564\u0561\u0562\u056c\u0578\u0582\u0580"
    ],
    "name:ita_x_preferred":[
        "Vardablur"
    ],
    "name:kat_x_preferred":[
        "\u10d5\u10d0\u10e0\u10d3\u10d0\u10d1\u10da\u10e3\u10e0\u10d8"
    ],
    "name:rus_x_preferred":[
        "\u0412\u0430\u0440\u0434\u0430\u0431\u043b\u0443\u0440"
    ],
    "name:swe_x_preferred":[
        "Vardablur"
    ],
    "name:ukr_x_preferred":[
        "\u0412\u0430\u0440\u0434\u0430\u0431\u043b\u0443\u0440"
    ],
    "wof:name":"Vardablur",
    "wof:placetype":"locality"
},
  "geometry": {"coordinates":[45.36249,39.66809],"type":"Point"}
}