{
  "type": "Feature",
  "properties": {
    "gn:admin1_code":"6.0",
    "gn:asciiname":"Kts'agomeri Mot",
    "gn:country_code":"AM",
    "gn:dem":1012,
    "gn:feature_class":"P",
    "gn:feature_code":"PPL",
    "gn:name":"Kts\u2019agomeri Mot",
    "gn:population":0,
    "gn:timezone":"Asia/Yerevan",
    "iso:country":"AM",
    "name:hye_x_preferred":[
        "Kts\u2019agomeri Mot"
    ],
    "name:hye_x_variant":[
        "\u053f\u0581\u0561\u0563\u0578\u0574\u0565\u0580\u056b \u0574\u0578\u057f"
    ],
    "wof:name":"Kts'agomeri Mot",
    "wof:placetype":"locality"
},
  "geometry": {"coordinates":[44.65008,40.99451],"type":"Point"}
}