{
  "type": "Feature",
  "properties": {
    "gn:admin1_code":"8.0",
    "gn:asciiname":"Hin T'khunis",
    "gn:country_code":"AM",
    "gn:dem":1748,
    "gn:feature_class":"P",
    "gn:feature_code":"PPL",
    "gn:name":"Hin T\u2019khunis",
    "gn:population":0,
    "gn:timezone":"Asia/Yerevan",
    "iso:country":"AM",
    "name:hye_x_preferred":[
        "Hin T\u2019khunis"
    ],
    "name:hye_x_variant":[
        "\u0540\u056b\u0576 \u0539\u056d\u0578\u0582\u0576\u056b\u057d"
    ],
    "wof:name":"Hin T'khunis",
    "wof:placetype":"locality"
},
  "geometry": {"coordinates":[46.0307,39.4361],"type":"Point"}
}