{
  "type": "Feature",
  "properties": {
    "iso:country":"AM",
    "label:eng_x_preferred_longname":[
        "Kamo Shrjan"
    ],
    "label:eng_x_preferred_placetype":[
        "shrjan"
    ],
    "name:eng_x_preferred":[
        "Kamo"
    ],
    "name:eng_x_variant":[
        "Kamo Shrjan"
    ],
    "qs:gn_pop":0,
    "qs:name":"Kamo Shrjan",
    "qs:name_adm0":"Armenia",
    "qs:name_adm1":"Geghark'unik'",
    "qs:photos":619,
    "qs:photos_1k":125,
    "qs:photos_9k":4,
    "qs:photos_9r":6,
    "qs:photos_all":838,
    "qs:photos_sr":8,
    "qs:placetype":"County",
    "qs:pop_sr":"0",
    "qs:woe_adm0":23424743,
    "wof:name":"Kamo",
    "wof:placetype":"county",
    "wof:placetype_local":"shrjan"
},
  "geometry": {"coordinates":[44.9795,40.2885],"type":"Point"}
}