{
  "type": "Feature",
  "properties": {
    "iso:country":"AM",
    "label:eng_x_preferred_longname":[
        "Kamo Shrjan"
    ],
    "label:eng_x_preferred_placetype":[
        "shrjan"
    ],
    "name:ceb_x_preferred":[
        "Kamo"
    ],
    "name:ces_x_preferred":[
        "Kamo"
    ],
    "name:deu_x_preferred":[
        "Kamo"
    ],
    "name:eng_x_preferred":[
        "Kamo"
    ],
    "name:eng_x_variant":[
        "Kamo Shrjan"
    ],
    "name:epo_x_preferred":[
        "Kamo"
    ],
    "name:est_x_preferred":[
        "Kamo"
    ],
    "name:fra_x_preferred":[
        "Kamo"
    ],
    "name:hye_x_preferred":[
        "\u053f\u0561\u0574\u0578"
    ],
    "name:ind_x_preferred":[
        "Kamo"
    ],
    "name:kat_x_preferred":[
        "\u10d9\u10d0\u10db\u10dd"
    ],
    "name:lav_x_preferred":[
        "Kamo"
    ],
    "name:mlg_x_preferred":[
        "Kamo"
    ],
    "name:nld_x_preferred":[
        "Kamo"
    ],
    "name:rus_x_preferred":[
        "\u041a\u0430\u043c\u043e"
    ],
    "name:spa_x_preferred":[
        "Kamo"
    ],
    "name:swe_x_preferred":[
        "Kamo"
    ],
    "name:ukr_x_preferred":[
        "\u041a\u0430\u043c\u043e"
    ],
    "qs:gn_pop":0,
    "qs:name":"Kamo Shrjan",
    "qs:name_adm0":"Armenia",
    "qs:name_adm1":"Geghark'unik'",
    "qs:photos":619,
    "qs:photos_1k":125,
    "qs:photos_9k":4,
    "qs:photos_9r":6,
    "qs:photos_all":838,
    "qs:photos_sr":8,
    "qs:placetype":"County",
    "qs:pop_sr":"0",
    "qs:woe_adm0":23424743,
    "wof:name":"Kamo",
    "wof:placetype":"county",
    "wof:placetype_local":"shrjan"
},
  "geometry": {"coordinates":[44.9795,40.2885],"type":"Point"}
}