{
  "type": "Feature",
  "properties": {
    "gn:admin1_code":"10",
    "gn:asciiname":"Kayalu",
    "gn:country_code":"AM",
    "gn:dem":1455,
    "gn:feature_class":"P",
    "gn:feature_code":"PPL",
    "gn:name":"Kayalu",
    "gn:population":0,
    "gn:timezone":"Asia/Yerevan",
    "iso:country":"AM",
    "wof:name":"Kayalu",
    "wof:placetype":"locality"
},
  "geometry": {"coordinates":[45.50611,39.6925],"type":"Point"}
}