{
  "type": "Feature",
  "properties": {
    "gn:admin1_code":"6.0",
    "gn:asciiname":"Berdat'agh",
    "gn:country_code":"AM",
    "gn:dem":1573,
    "gn:feature_class":"P",
    "gn:feature_code":"PPL",
    "gn:name":"Berdat\u2019agh",
    "gn:population":0,
    "gn:timezone":"Asia/Yerevan",
    "iso:country":"AM",
    "name:hye_x_preferred":[
        "Berdat\u2019agh"
    ],
    "name:hye_x_variant":[
        "\u0532\u0565\u0580\u0564\u0561\u0569\u0561\u0572"
    ],
    "wof:name":"Berdat'agh",
    "wof:placetype":"locality"
},
  "geometry": {"coordinates":[44.66107,40.89172],"type":"Point"}
}