{
  "type": "Feature",
  "properties": {
    "gn:admin1_code":"6.0",
    "gn:asciiname":"Braghdzor",
    "gn:country_code":"AM",
    "gn:dem":822,
    "gn:feature_class":"P",
    "gn:feature_code":"PPL",
    "gn:name":"Braghdzor",
    "gn:population":0,
    "gn:timezone":"Asia/Yerevan",
    "iso:country":"AM",
    "name:hye_x_preferred":[
        "Braghdzor"
    ],
    "name:hye_x_variant":[
        "\u0532\u0580\u0561\u0572\u0571\u0578\u0580"
    ],
    "wof:name":"Braghdzor",
    "wof:placetype":"locality"
},
  "geometry": {"coordinates":[44.82648,41.1167],"type":"Point"}
}