{
  "type": "Feature",
  "properties": {
    "gn:admin1_code":"8.0",
    "gn:asciiname":"Khach'er",
    "gn:country_code":"AM",
    "gn:dem":1602,
    "gn:feature_class":"P",
    "gn:feature_code":"PPL",
    "gn:name":"Khach\u2019er",
    "gn:population":0,
    "gn:timezone":"Asia/Yerevan",
    "iso:country":"AM",
    "name:hye_x_preferred":[
        "Khach\u2019er"
    ],
    "name:hye_x_variant":[
        "\u053d\u0561\u0579\u0565\u0580"
    ],
    "wof:name":"Khach'er",
    "wof:placetype":"locality"
},
  "geometry": {"coordinates":[46.40289,39.54449],"type":"Point"}
}