{
  "type": "Feature",
  "properties": {
    "gn:admin1_code":"04",
    "gn:asciiname":"Ch'kalovka",
    "gn:country_code":"AM",
    "gn:dem":1921,
    "gn:feature_class":"P",
    "gn:feature_code":"PPL",
    "gn:name":"Ch\u2019kalovka",
    "gn:population":0,
    "gn:timezone":"Asia/Yerevan",
    "iso:country":"AM",
    "name:aze_x_preferred":[
        "Zeynala\u011fal\u0131"
    ],
    "name:che_x_preferred":[
        "\u0427\u043a\u0430\u043b\u043e\u0432\u043a\u0430"
    ],
    "name:eng_x_preferred":[
        "Ch'kalovka"
    ],
    "name:fas_x_preferred":[
        "\u0686\u06a9\u0627\u0644\u0648\u0648\u06a9\u0627"
    ],
    "name:fra_x_preferred":[
        "Chkalovka"
    ],
    "name:hye_x_preferred":[
        "\u0549\u056f\u0561\u056c\u0578\u057e\u056f\u0561"
    ],
    "name:ita_x_preferred":[
        "Chkalovka"
    ],
    "name:kat_x_preferred":[
        "\u10e9\u10d9\u10d0\u10da\u10dd\u10d5\u10d9\u10d0"
    ],
    "name:msa_x_preferred":[
        "Chkalovka"
    ],
    "name:rus_x_preferred":[
        "\u0427\u043a\u0430\u043b\u043e\u0432\u043a\u0430"
    ],
    "name:sco_x_preferred":[
        "Chkalovka"
    ],
    "name:spa_x_preferred":[
        "Chkalovka"
    ],
    "name:ukr_x_preferred":[
        "\u0427\u043a\u0430\u043b\u043e\u0432\u043a\u0430"
    ],
    "name:und_x_variant":[
        "Aleksandrovka",
        "Ch\u2019kalovka"
    ],
    "name:vie_x_preferred":[
        "Chkalovka"
    ],
    "wof:name":"Ch'kalovka",
    "wof:placetype":"locality"
},
  "geometry": {"coordinates":[44.98053,40.50848],"type":"Point"}
}