{
  "type": "Feature",
  "properties": {
    "gn:admin1_code":"04",
    "gn:asciiname":"Ch'kalovka",
    "gn:country_code":"AM",
    "gn:dem":1921,
    "gn:feature_class":"P",
    "gn:feature_code":"PPL",
    "gn:name":"Ch\u2019kalovka",
    "gn:population":0,
    "gn:timezone":"Asia/Yerevan",
    "iso:country":"AM",
    "name:eng_x_preferred":[
        "Ch'kalovka"
    ],
    "name:hye_x_preferred":[
        "\u0549\u056f\u0561\u056c\u0578\u057e\u056f\u0561"
    ],
    "name:rus_x_preferred":[
        "\u0427\u043a\u0430\u043b\u043e\u0432\u043a\u0430"
    ],
    "name:und_x_variant":[
        "Aleksandrovka",
        "Ch\u2019kalovka"
    ],
    "wof:name":"Ch'kalovka",
    "wof:placetype":"locality"
},
  "geometry": {"coordinates":[44.98053,40.50848],"type":"Point"}
}