{
  "type": "Feature",
  "properties": {
    "gn:admin1_code":"07",
    "gn:asciiname":"Karrnut",
    "gn:country_code":"AM",
    "gn:dem":1583,
    "gn:feature_class":"P",
    "gn:feature_code":"PPL",
    "gn:name":"Karrnut",
    "gn:population":0,
    "gn:timezone":"Asia/Yerevan",
    "iso:country":"AM",
    "name:hye_x_preferred":[
        "\u053f\u0561\u057c\u0576\u0578\u0582\u057f"
    ],
    "name:und_x_variant":[
        "Diraklar",
        "Dirak",
        "Karnut",
        "Karrnut"
    ],
    "wof:name":"Karrnut",
    "wof:placetype":"locality"
},
  "geometry": {"coordinates":[43.95695,40.7836],"type":"Point"}
}