{
  "type": "Feature",
  "properties": {
    "gn:admin1_code":"07",
    "gn:asciiname":"Karrnut",
    "gn:country_code":"AM",
    "gn:dem":1583,
    "gn:feature_class":"P",
    "gn:feature_code":"PPL",
    "gn:name":"Karrnut",
    "gn:population":0,
    "gn:timezone":"Asia/Yerevan",
    "iso:country":"AM",
    "name:aze_x_preferred":[
        "Dir\u0259kl\u0259r"
    ],
    "name:bul_x_preferred":[
        "\u041a\u0430\u0440\u043d\u0443\u0442"
    ],
    "name:ell_x_preferred":[
        "\u039a\u03b1\u03c1\u03bd\u03bf\u03cd\u03c4"
    ],
    "name:fas_x_preferred":[
        "\u06a9\u0627\u0631\u0646\u0648\u062a"
    ],
    "name:fra_x_preferred":[
        "Karnut"
    ],
    "name:hye_x_preferred":[
        "\u053f\u0561\u057c\u0576\u0578\u0582\u057f"
    ],
    "name:ita_x_preferred":[
        "Karnut"
    ],
    "name:kat_x_preferred":[
        "\u10d9\u10d0\u10e0\u10dc\u10e3\u10e2\u10d8"
    ],
    "name:msa_x_preferred":[
        "Karnut"
    ],
    "name:sco_x_preferred":[
        "Karnut"
    ],
    "name:spa_x_preferred":[
        "Karnut"
    ],
    "name:und_x_variant":[
        "Diraklar",
        "Dirak",
        "Karnut",
        "Karrnut"
    ],
    "name:vie_x_preferred":[
        "Karnut"
    ],
    "wof:name":"Karrnut",
    "wof:placetype":"locality"
},
  "geometry": {"coordinates":[43.95695,40.7836],"type":"Point"}
}