{
  "type": "Feature",
  "properties": {
    "gn:admin1_code":"08",
    "gn:asciiname":"Tsghuk",
    "gn:country_code":"AM",
    "gn:dem":2146,
    "gn:feature_class":"P",
    "gn:feature_code":"PPL",
    "gn:name":"Tsghuk",
    "gn:population":0,
    "gn:timezone":"Asia/Yerevan",
    "iso:country":"AM",
    "name:hye_x_preferred":[
        "Tsghuk"
    ],
    "name:und_x_variant":[
        "Murkuz",
        "Borisovka"
    ],
    "wof:name":"Tsghuk",
    "wof:placetype":"locality"
},
  "geometry": {"coordinates":[45.85513,39.66723],"type":"Point"}
}