{
  "type": "Feature",
  "properties": {
    "gn:admin1_code":"08",
    "gn:asciiname":"Tsghuk",
    "gn:country_code":"AM",
    "gn:dem":2146,
    "gn:feature_class":"P",
    "gn:feature_code":"PPL",
    "gn:name":"Tsghuk",
    "gn:population":0,
    "gn:timezone":"Asia/Yerevan",
    "iso:country":"AM",
    "name:aze_x_preferred":[
        "Borisovka"
    ],
    "name:fas_x_preferred":[
        "\u062a\u0633\u063a\u0648\u06a9"
    ],
    "name:fra_x_preferred":[
        "Tsghuk"
    ],
    "name:hye_x_preferred":[
        "Tsghuk"
    ],
    "name:hye_x_variant":[
        "\u053e\u0572\u0578\u0582\u056f"
    ],
    "name:ita_x_preferred":[
        "Tsghuk"
    ],
    "name:kat_x_preferred":[
        "\u10ec\u10e6\u10e3\u10d9\u10d8"
    ],
    "name:msa_x_preferred":[
        "Tsghuk"
    ],
    "name:sco_x_preferred":[
        "Tsghuk"
    ],
    "name:spa_x_preferred":[
        "Tsghuk"
    ],
    "name:und_x_variant":[
        "Murkuz"
    ],
    "name:vie_x_preferred":[
        "Tsghuk"
    ],
    "wof:name":"Tsghuk",
    "wof:placetype":"locality"
},
  "geometry": {"coordinates":[45.85513,39.66723],"type":"Point"}
}