{
  "type": "Feature",
  "properties": {
    "gn:admin1_code":"4.0",
    "gn:asciiname":"Mayr Astvatsatsin",
    "gn:country_code":"AM",
    "gn:dem":2065,
    "gn:feature_class":"P",
    "gn:feature_code":"PPL",
    "gn:name":"Mayr Astvatsatsin",
    "gn:population":0,
    "gn:timezone":"Asia/Yerevan",
    "iso:country":"AM",
    "name:hye_x_preferred":[
        "Mayr Astvatsatsin"
    ],
    "name:hye_x_variant":[
        "\u0544\u0561\u0575\u0580 \u0531\u057d\u057f\u057e\u0561\u056e\u0561\u056e\u056b\u0576"
    ],
    "wof:name":"Mayr Astvatsatsin",
    "wof:placetype":"locality"
},
  "geometry": {"coordinates":[45.61389000000001,40.15692],"type":"Point"}
}