{
  "type": "Feature",
  "properties": {
    "gn:admin1_code":"7.0",
    "gn:asciiname":"Ukhtasar",
    "gn:country_code":"AM",
    "gn:dem":1781,
    "gn:feature_class":"P",
    "gn:feature_code":"PPL",
    "gn:name":"Ukhtasar",
    "gn:population":0,
    "gn:timezone":"Asia/Yerevan",
    "iso:country":"AM",
    "name:hye_x_preferred":[
        "Ukhtasar"
    ],
    "name:hye_x_variant":[
        "\u0548\u0552\u056d\u057f\u0561\u057d\u0561\u0580"
    ],
    "wof:name":"Ukhtasar",
    "wof:placetype":"locality"
},
  "geometry": {"coordinates":[43.84729,40.88348],"type":"Point"}
}