{
  "type": "Feature",
  "properties": {
    "gn:admin1_code":"10.0",
    "gn:asciiname":"Havu",
    "gn:country_code":"AM",
    "gn:dem":2812,
    "gn:feature_class":"P",
    "gn:feature_code":"PPL",
    "gn:name":"Havu",
    "gn:population":0,
    "gn:timezone":"Asia/Yerevan",
    "iso:country":"AM",
    "name:hye_x_preferred":[
        "Havu"
    ],
    "name:hye_x_variant":[
        "\u0540\u0561\u057e\u0578\u0582"
    ],
    "wof:name":"Havu",
    "wof:placetype":"locality"
},
  "geometry": {"coordinates":[45.39868,39.8501],"type":"Point"}
}