{
  "type": "Feature",
  "properties": {
    "iso:country":"AM",
    "name:arm_x_preferred":[
        "\u0544\u0565\u0572\u0580\u0561\u0571\u0578\u0580"
    ],
    "name:ceb_x_preferred":[
        "Meghradzor"
    ],
    "name:ces_x_preferred":[
        "Meghradzor"
    ],
    "name:cze_x_preferred":[
        "Meghradzor"
    ],
    "name:dut_x_preferred":[
        "Meghradzor"
    ],
    "name:eng_x_preferred":[
        "Meghradzor"
    ],
    "name:fas_x_preferred":[
        "\u0645\u063a\u0631\u0627\u062f\u0632\u0648\u0631"
    ],
    "name:fra_x_preferred":[
        "Meghradzor"
    ],
    "name:fre_x_preferred":[
        "Meghradzor"
    ],
    "name:geo_x_preferred":[
        "\u10db\u10d4\u10e6\u10e0\u10d0\u10eb\u10dd\u10e0\u10d8"
    ],
    "name:hye_x_preferred":[
        "\u0544\u0565\u0572\u0580\u0561\u0571\u0578\u0580"
    ],
    "name:ita_x_preferred":[
        "Meghradzor"
    ],
    "name:kat_x_preferred":[
        "\u10db\u10d4\u10e6\u10e0\u10d0\u10eb\u10dd\u10e0\u10d8"
    ],
    "name:may_x_preferred":[
        "Meghradzor"
    ],
    "name:msa_x_preferred":[
        "Meghradzor"
    ],
    "name:per_x_preferred":[
        "\u0645\u063a\u0631\u0627\u062f\u0632\u0648\u0631"
    ],
    "name:rus_x_preferred":[
        "\u041c\u0435\u0433\u0440\u0430\u0434\u0437\u043e\u0440"
    ],
    "name:sco_x_preferred":[
        "Meghradzor"
    ],
    "name:swe_x_preferred":[
        "Meghradzor"
    ],
    "name:unk_x_variant":[
        "Taycharukh"
    ],
    "name:vie_x_preferred":[
        "Meghradzor"
    ],
    "name:zho_min_nan_x_preferred":[
        "Meghradzor"
    ],
    "qs:gn_country":"AM",
    "qs:gn_fcode":"PPL",
    "qs:gn_pop":2659,
    "qs:name":"Megradzor",
    "qs:name_adm0":"Armenia",
    "qs:name_adm1":"Kotayk'",
    "qs:photos":0,
    "qs:photos_1k":0,
    "qs:photos_9k":0,
    "qs:photos_9r":0,
    "qs:photos_all":0,
    "qs:photos_sr":0,
    "qs:placetype":"Town",
    "qs:pop_sr":"4",
    "qs:woe_adm0":23424743,
    "wd:wordcount":229,
    "wof:name":"Megradzor",
    "wof:placetype":"locality",
    "wof:population":2659
},
  "geometry": {"coordinates":[44.65147,40.60611],"type":"Point"}
}