{
  "type": "Feature",
  "properties": {
    "gn:admin1_code":"0.0",
    "gn:asciiname":"T'onrasar",
    "gn:country_code":"AM",
    "gn:dem":2768,
    "gn:feature_class":"P",
    "gn:feature_code":"PPL",
    "gn:name":"T\u2019onrasar",
    "gn:population":0,
    "gn:timezone":"Asia/Yerevan",
    "iso:country":"AM",
    "name:hye_x_preferred":[
        "T\u2019onrasar"
    ],
    "name:hye_x_variant":[
        "\u0539\u0578\u0576\u0580\u0561\u057d\u0561\u0580"
    ],
    "wof:name":"T'onrasar",
    "wof:placetype":"locality"
},
  "geometry": {"coordinates":[46.16107,39.17792],"type":"Point"}
}