{
  "type": "Feature",
  "properties": {
    "gn:admin1_code":"9.0",
    "gn:asciiname":"Hyurgom",
    "gn:country_code":"AM",
    "gn:dem":701,
    "gn:feature_class":"P",
    "gn:feature_code":"PPL",
    "gn:name":"Hyurgom",
    "gn:population":0,
    "gn:timezone":"Asia/Yerevan",
    "iso:country":"AM",
    "name:hye_x_preferred":[
        "Hyurgom"
    ],
    "name:hye_x_variant":[
        "\u0540\u0575\u0578\u0582\u0580\u0563\u0578\u0574"
    ],
    "wof:name":"Hyurgom",
    "wof:placetype":"locality"
},
  "geometry": {"coordinates":[45.39313,40.96948],"type":"Point"}
}