{
  "type": "Feature",
  "properties": {
    "gn:admin1_code":"10.0",
    "gn:asciiname":"Arji Bner",
    "gn:country_code":"AM",
    "gn:dem":2636,
    "gn:feature_class":"P",
    "gn:feature_code":"PPL",
    "gn:name":"Arji Bner",
    "gn:population":0,
    "gn:timezone":"Asia/Yerevan",
    "iso:country":"AM",
    "name:hye_x_preferred":[
        "Arji Bner"
    ],
    "wof:name":"Arji Bner",
    "wof:placetype":"locality"
},
  "geometry": {"coordinates":[45.4057,39.82233],"type":"Point"}
}