{
  "type": "Feature",
  "properties": {
    "gn:admin1_code":"8.0",
    "gn:asciiname":"Kilevants'",
    "gn:country_code":"AM",
    "gn:dem":1731,
    "gn:feature_class":"P",
    "gn:feature_code":"PPL",
    "gn:name":"Kilevants\u2019",
    "gn:population":0,
    "gn:timezone":"Asia/Yerevan",
    "iso:country":"AM",
    "name:hye_x_preferred":[
        "Kilevants\u2019"
    ],
    "name:hye_x_variant":[
        "\u053f\u056b\u056c\u0587\u0561\u0576\u0581"
    ],
    "wof:name":"Kilevants'",
    "wof:placetype":"locality"
},
  "geometry": {"coordinates":[45.9765,39.5459],"type":"Point"}
}