{
  "type": "Feature",
  "properties": {
    "gn:admin1_code":"11.0",
    "gn:asciiname":"Mushakan - 2",
    "gn:country_code":"AM",
    "gn:dem":1367,
    "gn:feature_class":"P",
    "gn:feature_code":"PPL",
    "gn:name":"Mushakan - 2",
    "gn:population":0,
    "gn:timezone":"Asia/Yerevan",
    "iso:country":"AM",
    "name:hye_x_preferred":[
        "Mushakan - 2"
    ],
    "name:hye_x_variant":[
        "\u0544\u0578\u0582\u0577\u0561\u056f\u0561\u0576 - 2"
    ],
    "wof:name":"Mushakan - 2",
    "wof:placetype":"locality"
},
  "geometry": {"coordinates":[44.59729,40.12793],"type":"Point"}
}