{
  "type": "Feature",
  "properties": {
    "gn:admin1_code":"7.0",
    "gn:asciiname":"Yerkrord Ashkharhamartum Zohvatsneri",
    "gn:country_code":"AM",
    "gn:dem":1763,
    "gn:feature_class":"P",
    "gn:feature_code":"PPL",
    "gn:name":"Yerkrord Ashkharhamartum Zohvatsneri",
    "gn:population":0,
    "gn:timezone":"Asia/Yerevan",
    "iso:country":"AM",
    "name:hye_x_preferred":[
        "Yerkrord Ashkharhamartum Zohvatsneri"
    ],
    "name:hye_x_variant":[
        "\u0535\u0580\u056f\u0580\u0578\u0580\u0564 \u0561\u0577\u056d\u0561\u0580\u0570\u0561\u0574\u0561\u0580\u057f\u0578\u0582\u0574 \u0566\u0578\u0570\u057e\u0561\u056e\u0576\u0565\u0580\u056b"
    ],
    "wof:name":"Yerkrord Ashkharhamartum Zohvatsneri",
    "wof:placetype":"locality"
},
  "geometry": {"coordinates":[43.6861,40.86249],"type":"Point"}
}