{
  "type": "Feature",
  "properties": {
    "gn:admin1_code":"08",
    "gn:asciiname":"Kavshut",
    "gn:country_code":"AM",
    "gn:dem":2376,
    "gn:feature_class":"P",
    "gn:feature_code":"PPL",
    "gn:name":"Kavshut",
    "gn:population":0,
    "gn:timezone":"Asia/Yerevan",
    "iso:country":"AM",
    "name:hye_x_preferred":[
        "Kavchut"
    ],
    "name:hye_x_variant":[
        "Kavshut",
        "\u053f\u0561\u057e\u0573\u0578\u0582\u057f"
    ],
    "name:und_x_variant":[
        "Ghovshut",
        "Kovshut"
    ],
    "wof:name":"Kavshut",
    "wof:placetype":"locality"
},
  "geometry": {"coordinates":[46.21668,39.19733],"type":"Point"}
}