{
  "type": "Feature",
  "properties": {
    "gn:admin1_code":"9.0",
    "gn:asciiname":"Khndzorut",
    "gn:country_code":"AM",
    "gn:dem":916,
    "gn:feature_class":"P",
    "gn:feature_code":"PPL",
    "gn:name":"Khndzorut",
    "gn:population":0,
    "gn:timezone":"Asia/Yerevan",
    "iso:country":"AM",
    "name:aze_x_preferred":[
        "Yuxar\u0131 Mehrab"
    ],
    "name:hye_x_preferred":[
        "Khndzorut"
    ],
    "name:hye_x_variant":[
        "\u053d\u0576\u0571\u0578\u0580\u0578\u0582\u057f"
    ],
    "wof:name":"Khndzorut",
    "wof:placetype":"locality"
},
  "geometry": {"coordinates":[45.45569,40.80829],"type":"Point"}
}