{
  "type": "Feature",
  "properties": {
    "gn:admin1_code":"6.0",
    "gn:asciiname":"Aghchots' Khach'",
    "gn:country_code":"AM",
    "gn:dem":2511,
    "gn:feature_class":"P",
    "gn:feature_code":"PPL",
    "gn:name":"Aghchots\u2019 Khach\u2019",
    "gn:population":0,
    "gn:timezone":"Asia/Yerevan",
    "iso:country":"AM",
    "name:hye_x_preferred":[
        "Aghchots\u2019 Khach\u2019"
    ],
    "name:hye_x_variant":[
        "\u0531\u0572\u0573\u0578\u0581 \u053d\u0561\u0579"
    ],
    "wof:name":"Aghchots' Khach'",
    "wof:placetype":"locality"
},
  "geometry": {"coordinates":[44.6889,40.77368],"type":"Point"}
}