{
  "type": "Feature",
  "properties": {
    "gn:country":"AM",
    "gn:fcode":"PPL",
    "gn:pop":1032,
    "iso:country":"AM",
    "name:ara_x_preferred":[
        "\u062c\u0631\u0627\u0647\u0648\u0641\u064a\u062a\u060c \u0623\u0631\u0627\u0631\u0627\u062a"
    ],
    "name:aze_x_preferred":[
        "C\u0259b\u0259\u00e7ili"
    ],
    "name:eng_x_preferred":[
        "Jrahovit"
    ],
    "name:fas_x_preferred":[
        "\u062c\u0631\u0627\u0647\u0648\u0648\u06cc\u062a"
    ],
    "name:fra_x_preferred":[
        "Jrahovit"
    ],
    "name:hye_x_preferred":[
        "Jrahovit"
    ],
    "name:hye_x_variant":[
        "\u054b\u0580\u0561\u0570\u0578\u057e\u056b\u057f"
    ],
    "name:ita_x_preferred":[
        "Jrahovit"
    ],
    "name:kat_x_preferred":[
        "\u10ef\u10e0\u10d0\u10dd\u10d5\u10d8\u10e2\u10d8"
    ],
    "name:msa_x_preferred":[
        "Jrahovit"
    ],
    "name:nld_x_preferred":[
        "Jrahovit"
    ],
    "name:rus_x_preferred":[
        "\u0414\u0436\u0430\u0440\u043e\u0432\u0438\u0442"
    ],
    "name:swe_x_preferred":[
        "Jrahovit"
    ],
    "name:ukr_x_preferred":[
        "\u0414\u0436\u0440\u0430\u043e\u0432\u0456\u0442"
    ],
    "name:unk_x_variant":[
        "Dzhraovit"
    ],
    "name:vie_x_preferred":[
        "Jrahovit"
    ],
    "qs:name":"Jrahovit",
    "qs:photos_9r":0,
    "qs:photos_sr":0,
    "qs:pop_sr":"3",
    "wd:wordcount":65,
    "wof:name":"Jrahovit",
    "wof:placetype":"locality",
    "wof:population":1032
},
  "geometry": {"coordinates":[44.47372,40.04533],"type":"Point"}
}