{
  "type": "Feature",
  "properties": {
    "gn:admin1_code":"11.0",
    "gn:asciiname":"Saryan M.",
    "gn:country_code":"AM",
    "gn:dem":1008,
    "gn:feature_class":"P",
    "gn:feature_code":"PPL",
    "gn:name":"Saryan M.",
    "gn:population":0,
    "gn:timezone":"Asia/Yerevan",
    "iso:country":"AM",
    "name:hye_x_preferred":[
        "Saryan M."
    ],
    "name:hye_x_variant":[
        "\u054d\u0561\u0580\u0575\u0561\u0576 \u0544."
    ],
    "wof:name":"Saryan M.",
    "wof:placetype":"locality"
},
  "geometry": {"coordinates":[44.51031,40.1861],"type":"Point"}
}