{
  "type": "Feature",
  "properties": {
    "gn:admin1_code":"6.0",
    "gn:asciiname":"T'arrnots'",
    "gn:country_code":"AM",
    "gn:dem":2150,
    "gn:feature_class":"P",
    "gn:feature_code":"PPL",
    "gn:name":"T\u2019arrnots\u2019",
    "gn:population":0,
    "gn:timezone":"Asia/Yerevan",
    "iso:country":"AM",
    "name:hye_x_preferred":[
        "T\u2019arrnots\u2019"
    ],
    "name:hye_x_variant":[
        "\u0539\u0561\u057c\u0576\u0578\u0581"
    ],
    "wof:name":"T'arrnots'",
    "wof:placetype":"locality"
},
  "geometry": {"coordinates":[44.69733,40.76532],"type":"Point"}
}