{
  "type": "Feature",
  "properties": {
    "gn:admin1_code":"7.0",
    "gn:asciiname":"Tepoyi",
    "gn:country_code":"AM",
    "gn:dem":1876,
    "gn:feature_class":"P",
    "gn:feature_code":"PPL",
    "gn:name":"Tepoyi",
    "gn:population":0,
    "gn:timezone":"Asia/Yerevan",
    "iso:country":"AM",
    "name:hye_x_preferred":[
        "Tepoyi"
    ],
    "name:hye_x_variant":[
        "\u054f\u0565\u057a\u0578\u0575\u056b"
    ],
    "wof:name":"Tepoyi",
    "wof:placetype":"locality"
},
  "geometry": {"coordinates":[43.80829,40.52649],"type":"Point"}
}