{
  "type": "Feature",
  "properties": {
    "gn:country":"AM",
    "gn:fcode":"PPL",
    "gn:population":1874,
    "iso:country":"AM",
    "name:ceb_x_preferred":[
        "Taronik"
    ],
    "name:eng_x_preferred":[
        "Taronik"
    ],
    "name:fas_x_preferred":[
        "\u062a\u0627\u0631\u0648\u0646\u06cc\u06a9"
    ],
    "name:fra_x_preferred":[
        "Taronik"
    ],
    "name:hye_x_preferred":[
        "Taronik"
    ],
    "name:hye_x_variant":[
        "\u054f\u0561\u0580\u0578\u0576\u056b\u056f"
    ],
    "name:ita_x_preferred":[
        "Taronik"
    ],
    "name:kat_x_preferred":[
        "\u10e2\u10d0\u10e0\u10dd\u10dc\u10d8\u10d9\u10d8"
    ],
    "name:msa_x_preferred":[
        "Taronik"
    ],
    "name:nan_x_preferred":[
        "Taronik"
    ],
    "name:nld_x_preferred":[
        "Taronik"
    ],
    "name:rus_x_preferred":[
        "\u0422\u0430\u0440\u043e\u043d\u0438\u043a"
    ],
    "name:sco_x_preferred":[
        "Taronik"
    ],
    "name:spa_x_preferred":[
        "Taronik"
    ],
    "name:swe_x_preferred":[
        "Taronik"
    ],
    "name:ukr_x_preferred":[
        "\u0422\u0430\u0440\u043e\u043d\u0456\u043a"
    ],
    "name:vie_x_preferred":[
        "Taronik"
    ],
    "qs:name":"Taronik",
    "qs:photos_9r":0,
    "qs:photos_sr":0,
    "qs:pop_sr":"3",
    "wd:wordcount":220,
    "wof:name":"Taronik",
    "wof:placetype":"locality",
    "wof:population":1874
},
  "geometry": {"coordinates":[44.19957,40.13367],"type":"Point"}
}