{
  "type": "Feature",
  "properties": {
    "gn:admin1_code":"4.0",
    "gn:asciiname":"K'aravani",
    "gn:country_code":"AM",
    "gn:dem":2269,
    "gn:feature_class":"P",
    "gn:feature_code":"PPL",
    "gn:name":"K\u2019aravani",
    "gn:population":0,
    "gn:timezone":"Asia/Yerevan",
    "iso:country":"AM",
    "name:hye_x_preferred":[
        "K\u2019aravani"
    ],
    "name:hye_x_variant":[
        "\u0554\u0561\u0580\u0561\u057e\u0561\u0576\u056b"
    ],
    "wof:name":"K'aravani",
    "wof:placetype":"locality"
},
  "geometry": {"coordinates":[45.14172,40.1889],"type":"Point"}
}