{
  "type": "Feature",
  "properties": {
    "gn:admin1_code":"6.0",
    "gn:asciiname":"Saribeki Gomer",
    "gn:country_code":"AM",
    "gn:dem":1646,
    "gn:feature_class":"P",
    "gn:feature_code":"PPL",
    "gn:name":"Saribeki Gomer",
    "gn:population":0,
    "gn:timezone":"Asia/Yerevan",
    "iso:country":"AM",
    "name:hye_x_preferred":[
        "Saribeki Gomer"
    ],
    "name:hye_x_variant":[
        "\u054d\u0561\u0580\u056b\u0562\u0565\u056f\u056b \u0563\u0578\u0574\u0565\u0580"
    ],
    "wof:name":"Saribeki Gomer",
    "wof:placetype":"locality"
},
  "geometry": {"coordinates":[44.82928,41.05292],"type":"Point"}
}