{
  "type": "Feature",
  "properties": {
    "gn:admin1_code":"7.0",
    "gn:asciiname":"Ditaver",
    "gn:country_code":"AM",
    "gn:dem":2195,
    "gn:feature_class":"P",
    "gn:feature_code":"PPL",
    "gn:name":"Ditaver",
    "gn:population":0,
    "gn:timezone":"Asia/Yerevan",
    "iso:country":"AM",
    "name:hye_x_preferred":[
        "Ditaver"
    ],
    "name:hye_x_variant":[
        "\u0534\u056b\u057f\u0561\u057e\u0565\u0580"
    ],
    "wof:name":"Ditaver",
    "wof:placetype":"locality"
},
  "geometry": {"coordinates":[43.77087,41.1153],"type":"Point"}
}