{
  "type": "Feature",
  "properties": {
    "gn:admin1_code":"4.0",
    "gn:asciiname":"Hayrapeti",
    "gn:country_code":"AM",
    "gn:dem":1934,
    "gn:feature_class":"P",
    "gn:feature_code":"PPL",
    "gn:name":"Hayrapeti",
    "gn:population":0,
    "gn:timezone":"Asia/Yerevan",
    "iso:country":"AM",
    "name:hye_x_preferred":[
        "Hayrapeti"
    ],
    "name:hye_x_variant":[
        "\u0540\u0561\u0575\u0580\u0561\u057a\u0565\u057f\u056b"
    ],
    "wof:name":"Hayrapeti",
    "wof:placetype":"locality"
},
  "geometry": {"coordinates":[45.75409000000001,40.21668],"type":"Point"}
}