{
  "type": "Feature",
  "properties": {
    "gn:admin1_code":"6.0",
    "gn:asciiname":"Tsmakut",
    "gn:country_code":"AM",
    "gn:dem":1771,
    "gn:feature_class":"P",
    "gn:feature_code":"PPL",
    "gn:name":"Tsmakut",
    "gn:population":0,
    "gn:timezone":"Asia/Yerevan",
    "iso:country":"AM",
    "name:hye_x_preferred":[
        "Tsmakut"
    ],
    "name:hye_x_variant":[
        "\u053e\u0574\u0561\u056f\u0578\u0582\u057f"
    ],
    "wof:name":"Tsmakut",
    "wof:placetype":"locality"
},
  "geometry": {"coordinates":[44.50409000000001,40.89172],"type":"Point"}
}