{
  "type": "Feature",
  "properties": {
    "gn:admin1_code":"10",
    "gn:asciiname":"Arp'i",
    "gn:country_code":"AM",
    "gn:dem":1059,
    "gn:feature_class":"P",
    "gn:feature_code":"PPL",
    "gn:name":"Arp\u2019i",
    "gn:population":0,
    "gn:timezone":"Asia/Yerevan",
    "iso:country":"AM",
    "name:hye_x_preferred":[
        "Arp\u2019i"
    ],
    "name:hye_x_variant":[
        "\u0531\u0580\u0583\u056b"
    ],
    "name:und_x_variant":[
        "Arpa"
    ],
    "wof:name":"Arp'i",
    "wof:placetype":"locality"
},
  "geometry": {"coordinates":[45.26672,39.73889000000001],"type":"Point"}
}