{
  "type": "Feature",
  "properties": {
    "gn:admin1_code":"09",
    "gn:asciiname":"Sevk'ar",
    "gn:country_code":"AM",
    "gn:dem":836,
    "gn:feature_class":"P",
    "gn:feature_code":"PPL",
    "gn:name":"Sevk\u2019ar",
    "gn:population":0,
    "gn:timezone":"Asia/Yerevan",
    "iso:country":"AM",
    "name:aze_x_preferred":[
        "Qarada\u015f"
    ],
    "name:che_x_preferred":[
        "\u0421\u0435\u0432\u043a\u0430\u0440"
    ],
    "name:ell_x_preferred":[
        "\u03a3\u03b5\u03b2\u03ba\u03ac\u03c1"
    ],
    "name:eng_x_preferred":[
        "Sevk'ar"
    ],
    "name:fas_x_preferred":[
        "\u0633\u0648\u06a9\u0627\u0631"
    ],
    "name:fra_x_preferred":[
        "Sevkar"
    ],
    "name:hye_x_preferred":[
        "\u054d\u0587\u0584\u0561\u0580"
    ],
    "name:ita_x_preferred":[
        "Sevkar"
    ],
    "name:kat_x_preferred":[
        "\u10e1\u10d4\u10d5\u10e5\u10d0\u10e0\u10d8"
    ],
    "name:msa_x_preferred":[
        "Sevkar"
    ],
    "name:rus_x_preferred":[
        "\u0421\u0435\u0432\u043a\u0430\u0440"
    ],
    "name:sco_x_preferred":[
        "Sevkar"
    ],
    "name:spa_x_preferred":[
        "Sevkar"
    ],
    "name:und_x_variant":[
        "Karadash",
        "Sevk\u2019ar",
        "Sevkar"
    ],
    "name:vie_x_preferred":[
        "Sevkar"
    ],
    "wof:name":"Sevk'ar",
    "wof:placetype":"locality"
},
  "geometry": {"coordinates":[45.14185,41.01599],"type":"Point"}
}