{
  "type": "Feature",
  "properties": {
    "gn:admin1_code":"09",
    "gn:asciiname":"Sevk'ar",
    "gn:country_code":"AM",
    "gn:dem":836,
    "gn:feature_class":"P",
    "gn:feature_code":"PPL",
    "gn:name":"Sevk\u2019ar",
    "gn:population":0,
    "gn:timezone":"Asia/Yerevan",
    "iso:country":"AM",
    "name:eng_x_preferred":[
        "Sevk'ar"
    ],
    "name:hye_x_preferred":[
        "\u054d\u0587\u0584\u0561\u0580"
    ],
    "name:rus_x_preferred":[
        "\u0421\u0435\u0432\u043a\u0430\u0440"
    ],
    "name:und_x_variant":[
        "Karadash",
        "Sevk\u2019ar",
        "Sevkar"
    ],
    "wof:name":"Sevk'ar",
    "wof:placetype":"locality"
},
  "geometry": {"coordinates":[45.14185,41.01599],"type":"Point"}
}