{
  "type": "Feature",
  "properties": {
    "gn:admin1_code":"6.0",
    "gn:asciiname":"Mankuk'",
    "gn:country_code":"AM",
    "gn:dem":934,
    "gn:feature_class":"P",
    "gn:feature_code":"PPL",
    "gn:name":"Mankuk\u2019",
    "gn:population":0,
    "gn:timezone":"Asia/Tbilisi",
    "iso:country":"AM",
    "name:hye_x_preferred":[
        "Mankuk\u2019"
    ],
    "name:hye_x_variant":[
        "\u0544\u0561\u0576\u056f\u0578\u0582\u0584"
    ],
    "wof:name":"Mankuk'",
    "wof:placetype":"locality"
},
  "geometry": {"coordinates":[44.66107,41.23328],"type":"Point"}
}