{
  "type": "Feature",
  "properties": {
    "gn:admin1_code":"08",
    "gn:asciiname":"Qizilciq   az Azerbaijan",
    "gn:country_code":"AM",
    "gn:dem":1841,
    "gn:feature_class":"P",
    "gn:feature_code":"PPL",
    "gn:name":"Q\u0131z\u0131lc\u0131q   az Azerbaijan",
    "gn:population":0,
    "gn:timezone":"Asia/Yerevan",
    "iso:country":"AM",
    "name:hye_x_preferred":[
        "Ghzljugh"
    ],
    "name:und_x_variant":[
        "Ghzyljugh",
        "Ishkanasar",
        "Kyzyldzhug",
        "Kizildzhuk",
        "Kyzyldzhuk",
        "Kizildzhug"
    ],
    "wof:name":"Qizilciq  az Azerbaijan",
    "wof:placetype":"locality"
},
  "geometry": {"coordinates":[46.03784,39.57053],"type":"Point"}
}