{
  "type": "Feature",
  "properties": {
    "gn:admin1_code":"2.0",
    "gn:asciiname":"Avazani Surb",
    "gn:country_code":"AM",
    "gn:dem":1996,
    "gn:feature_class":"P",
    "gn:feature_code":"PPL",
    "gn:name":"Avazani Surb",
    "gn:population":0,
    "gn:timezone":"Asia/Yerevan",
    "iso:country":"AM",
    "name:hye_x_preferred":[
        "Avazani Surb"
    ],
    "name:hye_x_variant":[
        "\u0531\u057e\u0561\u0566\u0561\u0576\u056b \u054d\u0578\u0582\u0580\u0562"
    ],
    "wof:name":"Avazani Surb",
    "wof:placetype":"locality"
},
  "geometry": {"coordinates":[44.98187,39.8529],"type":"Point"}
}