{
  "type": "Feature",
  "properties": {
    "gn:admin1_code":"4.0",
    "gn:asciiname":"Yeghnaghbyur",
    "gn:country_code":"AM",
    "gn:dem":2500,
    "gn:feature_class":"P",
    "gn:feature_code":"PPL",
    "gn:name":"Yeghnaghbyur",
    "gn:population":0,
    "gn:timezone":"Asia/Yerevan",
    "iso:country":"AM",
    "name:hye_x_preferred":[
        "Yeghnaghbyur"
    ],
    "name:hye_x_variant":[
        "\u0535\u0572\u0576\u0561\u0572\u0562\u0575\u0578\u0582\u0580"
    ],
    "wof:name":"Yeghnaghbyur",
    "wof:placetype":"locality"
},
  "geometry": {"coordinates":[45.63208,40.35828],"type":"Point"}
}