{
  "type": "Feature",
  "properties": {
    "gn:admin1_code":"08",
    "gn:asciiname":"Kard",
    "gn:country_code":"AM",
    "gn:dem":1867,
    "gn:feature_class":"P",
    "gn:feature_code":"PPL",
    "gn:name":"Kard",
    "gn:population":0,
    "gn:timezone":"Asia/Yerevan",
    "iso:country":"AM",
    "name:bul_x_preferred":[
        "\u041a\u0430\u0440\u0434"
    ],
    "name:cat_x_preferred":[
        "K\u0101rd"
    ],
    "name:deu_x_preferred":[
        "Kard"
    ],
    "name:hye_x_preferred":[
        "Kard"
    ],
    "name:lit_x_preferred":[
        "Kardas"
    ],
    "name:pol_x_preferred":[
        "Kard"
    ],
    "name:rus_x_preferred":[
        "\u041a\u0430\u0440\u0434"
    ],
    "name:sco_x_preferred":[
        "Kard"
    ],
    "name:und_x_variant":[
        "Gyart\u2019",
        "K\u2019irt\u2019",
        "Gyard Nerk\u2019in",
        "Girt\u2019",
        "K\u2019art\u2019i",
        "Kart\u2019",
        "Kard Nerk\u2019in",
        "Gyrad",
        "Gyard"
    ],
    "wof:name":"Kard",
    "wof:placetype":"locality"
},
  "geometry": {"coordinates":[46.10553,39.24731],"type":"Point"}
}