{
  "type": "Feature",
  "properties": {
    "iso:country":"AM",
    "name:bul_x_preferred":[
        "\u0410\u043d\u0443\u0448\u0430\u0432\u0430\u043d"
    ],
    "name:ceb_x_preferred":[
        "Anushavan"
    ],
    "name:eng_x_preferred":[
        "Anushavan"
    ],
    "name:fas_x_preferred":[
        "\u0622\u0646\u0648\u0634\u0627\u0648\u0627\u0646"
    ],
    "name:fra_x_preferred":[
        "Anushavan"
    ],
    "name:hye_x_preferred":[
        "\u0531\u0576\u0578\u0582\u0577\u0561\u057e\u0561\u0576"
    ],
    "name:ita_x_preferred":[
        "Anushavan"
    ],
    "name:kat_x_preferred":[
        "\u10d0\u10dc\u10e3\u10e8\u10d0\u10d5\u10d0\u10dc\u10d8"
    ],
    "name:msa_x_preferred":[
        "Anushavan"
    ],
    "name:nld_x_preferred":[
        "Anushavan"
    ],
    "name:rus_x_preferred":[
        "\u0410\u043d\u0443\u0448\u0430\u0432\u0430\u043d"
    ],
    "name:sco_x_preferred":[
        "Anushavan"
    ],
    "name:swe_x_preferred":[
        "Anushavan"
    ],
    "name:unk_x_variant":[
        "Pokr Parni"
    ],
    "name:vie_x_preferred":[
        "Anushavan"
    ],
    "name:zho_min_nan_x_preferred":[
        "Anushavan"
    ],
    "qs:gn_country":"AM",
    "qs:gn_fcode":"PPL",
    "qs:gn_pop":1532,
    "qs:name":"Anushavan",
    "qs:name_adm0":"Armenia",
    "qs:name_adm1":"Shirak",
    "qs:photos":0,
    "qs:photos_1k":0,
    "qs:photos_9k":0,
    "qs:photos_9r":0,
    "qs:photos_all":0,
    "qs:photos_sr":0,
    "qs:placetype":"Town",
    "qs:pop_sr":"3",
    "qs:woe_adm0":23424743,
    "wd:wordcount":141,
    "wof:name":"Anushavan",
    "wof:placetype":"locality",
    "wof:population":1532
},
  "geometry": {"coordinates":[43.97756,40.65013],"type":"Point"}
}