{
  "type": "Feature",
  "properties": {
    "gn:admin1_code":"9.0",
    "gn:asciiname":"K'arkop'",
    "gn:country_code":"AM",
    "gn:dem":507,
    "gn:feature_class":"P",
    "gn:feature_code":"PPL",
    "gn:name":"K\u2019arkop\u2019",
    "gn:population":0,
    "gn:timezone":"Asia/Yerevan",
    "iso:country":"AM",
    "name:hye_x_preferred":[
        "K\u2019arkop\u2019"
    ],
    "name:hye_x_variant":[
        "\u0554\u0561\u0580\u056f\u0578\u0583"
    ],
    "wof:name":"K'arkop'",
    "wof:placetype":"locality"
},
  "geometry": {"coordinates":[44.8667,41.18329],"type":"Point"}
}