{
  "type": "Feature",
  "properties": {
    "iso:country":"AM",
    "label:eng_x_preferred_longname":[
        "Stepanavan Shrjan"
    ],
    "label:eng_x_preferred_placetype":[
        "shrjan"
    ],
    "name:eng_x_preferred":[
        "Stepanavan"
    ],
    "name:eng_x_variant":[
        "Stepanavan Shrjan"
    ],
    "qs:gn_pop":0,
    "qs:name":"Stepanavan Shrjan",
    "qs:name_adm0":"Armenia",
    "qs:name_adm1":"Lorri",
    "qs:photos":57,
    "qs:photos_1k":12,
    "qs:photos_9k":1,
    "qs:photos_9r":2,
    "qs:photos_all":68,
    "qs:photos_sr":2,
    "qs:placetype":"County",
    "qs:pop_sr":"0",
    "qs:woe_adm0":23424743,
    "wof:name":"Stepanavan",
    "wof:placetype":"county",
    "wof:placetype_local":"shrjan"
},
  "geometry": {"coordinates":[44.329833,41.062786],"type":"Point"}
}