{
  "type": "Feature",
  "properties": {
    "iso:country":"AM",
    "label:eng_x_preferred_longname":[
        "Stepanavan Shrjan"
    ],
    "label:eng_x_preferred_placetype":[
        "shrjan"
    ],
    "name:azb_x_preferred":[
        "\u0627\u0633\u062a\u067e\u0627\u0646\u0627\u0648\u0627\u0646"
    ],
    "name:aze_x_preferred":[
        "Stepanavan"
    ],
    "name:bel_x_preferred":[
        "\u0421\u0446\u0435\u043f\u0430\u043d\u0430\u0432\u0430\u043d"
    ],
    "name:bul_x_preferred":[
        "\u0421\u0442\u0435\u043f\u0430\u043d\u0430\u0432\u0430\u043d"
    ],
    "name:che_x_preferred":[
        "\u0421\u0442\u0435\u043f\u0430\u043d\u0430\u0432\u0430\u043d"
    ],
    "name:deu_x_preferred":[
        "Stepanawan"
    ],
    "name:ell_x_preferred":[
        "\u03a3\u03c4\u03b5\u03c0\u03b1\u03bd\u03b1\u03b2\u03ac\u03bd"
    ],
    "name:eng_x_preferred":[
        "Stepanavan"
    ],
    "name:eng_x_variant":[
        "Stepanavan Shrjan"
    ],
    "name:epo_x_preferred":[
        "Stepanavan"
    ],
    "name:est_x_preferred":[
        "Stephanavan"
    ],
    "name:fas_x_preferred":[
        "\u0627\u0633\u062a\u067e\u0627\u0646\u0627\u0648\u0627\u0646"
    ],
    "name:fin_x_preferred":[
        "Stepanavan"
    ],
    "name:fra_x_preferred":[
        "Stepanavan"
    ],
    "name:hsb_x_preferred":[
        "Stepanawan"
    ],
    "name:hye_x_preferred":[
        "\u054d\u057f\u0565\u0583\u0561\u0576\u0561\u057e\u0561\u0576"
    ],
    "name:ind_x_preferred":[
        "Stepanavan"
    ],
    "name:ita_x_preferred":[
        "Stepanavan"
    ],
    "name:kat_x_preferred":[
        "\u10e1\u10e2\u10d4\u10e4\u10d0\u10dc\u10d0\u10d5\u10d0\u10dc\u10d8"
    ],
    "name:lit_x_preferred":[
        "Stepanavanas"
    ],
    "name:msa_x_preferred":[
        "Stepanavan"
    ],
    "name:mzn_x_preferred":[
        "\u0627\u0633\u062a\u067e\u0627\u0646\u0627\u0648\u0627\u0646"
    ],
    "name:nld_x_preferred":[
        "Stepanavan"
    ],
    "name:pol_x_preferred":[
        "Stepanawan"
    ],
    "name:ron_x_preferred":[
        "Stepanavan"
    ],
    "name:rus_x_preferred":[
        "\u0421\u0442\u0435\u043f\u0430\u043d\u0430\u0432\u0430\u043d"
    ],
    "name:sco_x_preferred":[
        "Stepanavan"
    ],
    "name:spa_x_preferred":[
        "Estepanavan"
    ],
    "name:srp_x_preferred":[
        "\u0421\u0442\u0435\u043f\u0430\u043d\u0430\u0432\u0430\u043d"
    ],
    "name:swe_x_preferred":[
        "Stepanavan"
    ],
    "name:tur_x_preferred":[
        "Stepanavan"
    ],
    "name:ukr_x_preferred":[
        "\u0421\u0442\u0435\u043f\u0430\u043d\u0430\u0432\u0430\u043d"
    ],
    "name:vie_x_preferred":[
        "Stepanavan"
    ],
    "name:zho_x_preferred":[
        "\u65af\u6377\u6f58\u7d0d\u842c"
    ],
    "qs:gn_pop":0,
    "qs:name":"Stepanavan Shrjan",
    "qs:name_adm0":"Armenia",
    "qs:name_adm1":"Lorri",
    "qs:photos":57,
    "qs:photos_1k":12,
    "qs:photos_9k":1,
    "qs:photos_9r":2,
    "qs:photos_all":68,
    "qs:photos_sr":2,
    "qs:placetype":"County",
    "qs:pop_sr":"0",
    "qs:woe_adm0":23424743,
    "wof:name":"Stepanavan",
    "wof:placetype":"county",
    "wof:placetype_local":"shrjan"
},
  "geometry": {"coordinates":[44.329833,41.062786],"type":"Point"}
}