{
  "type": "Feature",
  "properties": {
    "gn:admin1_code":"7.0",
    "gn:asciiname":"Avdalents' Antik",
    "gn:country_code":"AM",
    "gn:dem":1887,
    "gn:feature_class":"P",
    "gn:feature_code":"PPL",
    "gn:name":"Avdalents\u2019 Antik",
    "gn:population":0,
    "gn:timezone":"Asia/Yerevan",
    "iso:country":"AM",
    "name:hye_x_preferred":[
        "Avdalents\u2019 Antik"
    ],
    "name:hye_x_variant":[
        "\u0531\u057e\u0564\u0561\u056c\u0565\u0576\u0581 \u0561\u0576\u057f\u056b\u056f"
    ],
    "wof:name":"Avdalents' Antik",
    "wof:placetype":"locality"
},
  "geometry": {"coordinates":[43.84869000000001,40.55408],"type":"Point"}
}