{
  "type": "Feature",
  "properties": {
    "gn:country":"AM",
    "gn:fcode":"PPL",
    "gn:population":1623,
    "iso:country":"AM",
    "name:aze_x_preferred":[
        "Mrqa\u015fen"
    ],
    "name:ceb_x_preferred":[
        "Mrgashen"
    ],
    "name:eng_x_preferred":[
        "Mrgashen"
    ],
    "name:fas_x_preferred":[
        "\u0645\u0631\u06af\u0627\u0634\u0646"
    ],
    "name:fra_x_preferred":[
        "Mrgashen"
    ],
    "name:hye_x_preferred":[
        "Mrgashen"
    ],
    "name:hye_x_variant":[
        "\u0544\u0580\u0563\u0561\u0577\u0565\u0576"
    ],
    "name:ita_x_preferred":[
        "Mrgashen"
    ],
    "name:kat_x_preferred":[
        "\u10db\u10e0\u10d2\u10d0\u10e8\u10d4\u10dc\u10d8"
    ],
    "name:msa_x_preferred":[
        "Mrgashen"
    ],
    "name:nan_x_preferred":[
        "Mrgashen"
    ],
    "name:nld_x_preferred":[
        "Mrgashen"
    ],
    "name:rus_x_preferred":[
        "\u041c\u0440\u0433\u0430\u0448\u0435\u043d"
    ],
    "name:sco_x_preferred":[
        "Mrgashen"
    ],
    "name:spa_x_preferred":[
        "Mrgashen"
    ],
    "name:swe_x_preferred":[
        "Mrgashen"
    ],
    "name:vie_x_preferred":[
        "Mrgashen"
    ],
    "name:vie_x_variant":[
        "Hovtashen"
    ],
    "qs:name":"Mrgashen",
    "qs:photos_9r":0,
    "qs:photos_sr":0,
    "qs:pop_sr":"3",
    "wd:wordcount":198,
    "wof:name":"Mrgashen",
    "wof:placetype":"locality",
    "wof:population":1623
},
  "geometry": {"coordinates":[44.54107,40.28523],"type":"Point"}
}