{
  "type": "Feature",
  "properties": {
    "gn:admin1_code":"11.0",
    "gn:asciiname":"Hakobyan T.",
    "gn:country_code":"AM",
    "gn:dem":1155,
    "gn:feature_class":"P",
    "gn:feature_code":"PPL",
    "gn:name":"Hakobyan T.",
    "gn:population":0,
    "gn:timezone":"Asia/Yerevan",
    "iso:country":"AM",
    "name:hye_x_preferred":[
        "Hakobyan T."
    ],
    "name:hye_x_variant":[
        "\u0540\u0561\u056f\u0578\u0562\u0575\u0561\u0576 \u054f."
    ],
    "wof:name":"Hakobyan T.",
    "wof:placetype":"locality"
},
  "geometry": {"coordinates":[44.54028,40.1875],"type":"Point"}
}