{
  "type": "Feature",
  "properties": {
    "gn:admin1_code":"9.0",
    "gn:asciiname":"Chak'ats",
    "gn:country_code":"AM",
    "gn:dem":876,
    "gn:feature_class":"P",
    "gn:feature_code":"PPL",
    "gn:name":"Chak\u2019ats",
    "gn:population":0,
    "gn:timezone":"Asia/Yerevan",
    "iso:country":"AM",
    "name:hye_x_preferred":[
        "Chak\u2019ats"
    ],
    "name:hye_x_variant":[
        "\u0543\u0561\u0584\u0561\u056e"
    ],
    "wof:name":"Chak'ats",
    "wof:placetype":"locality"
},
  "geometry": {"coordinates":[45.33893,40.9361],"type":"Point"}
}