{
  "type": "Feature",
  "properties": {
    "gn:admin1_code":"6.0",
    "gn:asciiname":"Gomer",
    "gn:country_code":"AM",
    "gn:dem":1362,
    "gn:feature_class":"P",
    "gn:feature_code":"PPL",
    "gn:name":"Gomer",
    "gn:population":0,
    "gn:timezone":"Asia/Yerevan",
    "iso:country":"AM",
    "name:amh_x_preferred":[
        "\u130b\u121c\u122d"
    ],
    "name:bod_x_preferred":[
        "\u0f42\u0f7c\u0f0b\u0f58\u0f7a\u0f62\u0f0d"
    ],
    "name:bul_x_preferred":[
        "\u0413\u043e\u043c\u0435\u0440"
    ],
    "name:cat_x_preferred":[
        "G\u00f3mer"
    ],
    "name:ces_x_preferred":[
        "Gomer"
    ],
    "name:deu_x_preferred":[
        "Gomer"
    ],
    "name:ell_x_preferred":[
        "\u0393\u03b1\u03bc\u03ad\u03c1"
    ],
    "name:fin_x_preferred":[
        "Gomer"
    ],
    "name:fra_x_preferred":[
        "Gom\u00e8re"
    ],
    "name:hye_x_preferred":[
        "Gomer"
    ],
    "name:hye_x_variant":[
        "\u0533\u0578\u0574\u0565\u0580"
    ],
    "name:ind_x_preferred":[
        "Gomer"
    ],
    "name:msa_x_preferred":[
        "Gomer"
    ],
    "name:nld_x_preferred":[
        "Gomer"
    ],
    "name:pol_x_preferred":[
        "Gomer"
    ],
    "name:ron_x_preferred":[
        "Gomer"
    ],
    "name:rus_x_preferred":[
        "\u042f\u0444\u0435\u0442\u0438\u0434\u044b#\u041f\u043e\u0442\u043e\u043c\u043a\u0438 \u0413\u043e\u043c\u0435\u0440\u0430"
    ],
    "name:ukr_x_preferred":[
        "\u0413\u043e\u043c\u0435\u0440"
    ],
    "wof:name":"Gomer",
    "wof:placetype":"locality"
},
  "geometry": {"coordinates":[44.4751,41.01392],"type":"Point"}
}