{
  "type": "Feature",
  "properties": {
    "gn:admin1_code":"6.0",
    "gn:asciiname":"Gomer",
    "gn:country_code":"AM",
    "gn:dem":1362,
    "gn:feature_class":"P",
    "gn:feature_code":"PPL",
    "gn:name":"Gomer",
    "gn:population":0,
    "gn:timezone":"Asia/Yerevan",
    "iso:country":"AM",
    "name:hye_x_preferred":[
        "Gomer"
    ],
    "name:hye_x_variant":[
        "\u0533\u0578\u0574\u0565\u0580"
    ],
    "wof:name":"Gomer",
    "wof:placetype":"locality"
},
  "geometry": {"coordinates":[44.4751,41.01392],"type":"Point"}
}