{
  "type": "Feature",
  "properties": {
    "iso:country":"AM",
    "name:ara_x_preferred":[
        "\u0646\u0648\u064a\u0627\u0643\u064a\u0631\u062a\u060c \u0623\u0631\u0627\u0631\u0627\u062a"
    ],
    "name:aze_x_preferred":[
        "Xalisa"
    ],
    "name:ceb_x_preferred":[
        "Noyakert"
    ],
    "name:eng_x_preferred":[
        "Noyakert"
    ],
    "name:fas_x_preferred":[
        "\u0646\u0648\u06cc\u0627\u06a9\u0631\u062a"
    ],
    "name:fra_x_preferred":[
        "Noyakert"
    ],
    "name:hye_x_preferred":[
        "\u0546\u0578\u0575\u0561\u056f\u0565\u0580\u057f"
    ],
    "name:ita_x_preferred":[
        "Noyakert"
    ],
    "name:kat_x_preferred":[
        "\u10dc\u10dd\u10d8\u10d0\u10d9\u10d4\u10e0\u10e2\u10d8"
    ],
    "name:msa_x_preferred":[
        "Noyakert"
    ],
    "name:nld_x_preferred":[
        "Noyakert"
    ],
    "name:rus_x_preferred":[
        "\u041d\u043e\u044f\u043a\u0435\u0440\u0442"
    ],
    "name:swe_x_preferred":[
        "Noyakert"
    ],
    "name:ukr_x_preferred":[
        "\u041d\u043e\u044f\u043a\u0435\u0440\u0442"
    ],
    "name:unk_x_variant":[
        "Khalisa"
    ],
    "name:vie_x_preferred":[
        "Noyakert"
    ],
    "name:zho_min_nan_x_preferred":[
        "Noyakert"
    ],
    "qs:gn_country":"AM",
    "qs:gn_fcode":"PPL",
    "qs:gn_pop":1751,
    "qs:name":"Noyakert",
    "qs:name_adm0":"Armenia",
    "qs:name_adm1":"Ararat",
    "qs:photos":0,
    "qs:photos_1k":0,
    "qs:photos_9k":1,
    "qs:photos_9r":1,
    "qs:photos_all":1,
    "qs:photos_sr":0,
    "qs:placetype":"Town",
    "qs:pop_sr":"3",
    "qs:woe_adm0":23424743,
    "wd:wordcount":61,
    "wof:name":"Noyakert",
    "wof:placetype":"locality",
    "wof:population":1751
},
  "geometry": {"coordinates":[44.66899,39.8312],"type":"Point"}
}