{
  "type": "Feature",
  "properties": {
    "gn:admin1_code":"10",
    "gn:asciiname":"Dghyak",
    "gn:country_code":"AM",
    "gn:dem":1550,
    "gn:feature_class":"P",
    "gn:feature_code":"PPL",
    "gn:name":"Dghyak",
    "gn:population":0,
    "gn:timezone":"Asia/Yerevan",
    "iso:country":"AM",
    "name:hye_x_preferred":[
        "Dghyak"
    ],
    "name:hye_x_variant":[
        "\u0534\u0572\u0575\u0561\u056f"
    ],
    "wof:name":"Dghyak",
    "wof:placetype":"locality"
},
  "geometry": {"coordinates":[45.4751,39.73328],"type":"Point"}
}