{
  "type": "Feature",
  "properties": {
    "gn:admin1_code":"8.0",
    "gn:asciiname":"Boghak'ar",
    "gn:country_code":"AM",
    "gn:dem":1743,
    "gn:feature_class":"P",
    "gn:feature_code":"PPL",
    "gn:name":"Boghak\u2019ar",
    "gn:population":0,
    "gn:timezone":"Asia/Yerevan",
    "iso:country":"AM",
    "name:hye_x_preferred":[
        "Boghak\u2019ar"
    ],
    "name:hye_x_variant":[
        "\u0532\u0578\u0572\u0561\u0584\u0561\u0580"
    ],
    "wof:name":"Boghak'ar",
    "wof:placetype":"locality"
},
  "geometry": {"coordinates":[46.15008,38.99451],"type":"Point"}
}