{
  "type": "Feature",
  "properties": {
    "gn:admin1_code":"10",
    "gn:asciiname":"Meghrak'ar",
    "gn:country_code":"AM",
    "gn:dem":1159,
    "gn:feature_class":"P",
    "gn:feature_code":"PPL",
    "gn:name":"Meghrak\u2019ar",
    "gn:population":0,
    "gn:timezone":"Asia/Yerevan",
    "iso:country":"AM",
    "name:hye_x_preferred":[
        "Meghrak\u2019ar"
    ],
    "name:hye_x_variant":[
        "\u0544\u0565\u0572\u0580\u0561\u0584\u0561\u0580"
    ],
    "wof:name":"Meghrak'ar",
    "wof:placetype":"locality"
},
  "geometry": {"coordinates":[45.33612,39.73468],"type":"Point"}
}