{
  "type": "Feature",
  "properties": {
    "gn:admin1_code":"11.0",
    "gn:asciiname":"Abovyan Kh.",
    "gn:country_code":"AM",
    "gn:dem":1065,
    "gn:feature_class":"P",
    "gn:feature_code":"PPL",
    "gn:name":"Abovyan Kh.",
    "gn:population":0,
    "gn:timezone":"Asia/Yerevan",
    "iso:country":"AM",
    "name:hye_x_preferred":[
        "Abovyan Kh."
    ],
    "name:hye_x_variant":[
        "\u0531\u0562\u0578\u057e\u0575\u0561\u0576 \u053d."
    ],
    "wof:name":"Abovyan Kh.",
    "wof:placetype":"locality"
},
  "geometry": {"coordinates":[44.5293,40.19171],"type":"Point"}
}