{
  "type": "Feature",
  "properties": {
    "gn:admin1_code":"4.0",
    "gn:asciiname":"Hin Gomer",
    "gn:country_code":"AM",
    "gn:dem":2127,
    "gn:feature_class":"P",
    "gn:feature_code":"PPL",
    "gn:name":"Hin Gomer",
    "gn:population":0,
    "gn:timezone":"Asia/Yerevan",
    "iso:country":"AM",
    "name:hye_x_preferred":[
        "Hin Gomer"
    ],
    "name:hye_x_variant":[
        "\u0540\u056b\u0576 \u0533\u0578\u0574\u0565\u0580"
    ],
    "wof:name":"Hin Gomer",
    "wof:placetype":"locality"
},
  "geometry": {"coordinates":[45.73328,40.13348],"type":"Point"}
}