{
  "type": "Feature",
  "properties": {
    "iso:country":"AM",
    "name:ara_x_preferred":[
        "\u062e\u0627\u0634\u062a\u0627\u0631\u0627\u0643"
    ],
    "name:arm_x_preferred":[
        "\u053d\u0561\u0577\u0569\u0561\u057c\u0561\u056f"
    ],
    "name:aze_x_preferred":[
        "H\u0259\u015ft\u0259r\u0259k"
    ],
    "name:cat_x_preferred":[
        "Khashtarak"
    ],
    "name:dut_x_preferred":[
        "Khashtarak"
    ],
    "name:eng_x_preferred":[
        "Khasht'arrak"
    ],
    "name:fas_x_preferred":[
        "\u062e\u0627\u0634\u062a\u0627\u0631\u0627\u06a9"
    ],
    "name:fra_x_preferred":[
        "Khashtarak"
    ],
    "name:fre_x_preferred":[
        "Khashtarak"
    ],
    "name:geo_x_preferred":[
        "\u10ee\u10d0\u10e8\u10d7\u10d0\u10e0\u10d0\u10d9\u10d8"
    ],
    "name:hye_x_preferred":[
        "\u053d\u0561\u0577\u0569\u0561\u057c\u0561\u056f"
    ],
    "name:ita_x_preferred":[
        "Khashtarak"
    ],
    "name:kat_x_preferred":[
        "\u10ee\u10d0\u10e8\u10d7\u10d0\u10e0\u10d0\u10d9\u10d8"
    ],
    "name:may_x_preferred":[
        "Khashtarak"
    ],
    "name:msa_x_preferred":[
        "Khashtarak"
    ],
    "name:nan_x_preferred":[
        "Khashtarak"
    ],
    "name:oci_x_preferred":[
        "Khashtarak"
    ],
    "name:per_x_preferred":[
        "\u062e\u0627\u0634\u062a\u0627\u0631\u0627\u06a9"
    ],
    "name:rus_x_preferred":[
        "\u0425\u0430\u0448\u0442\u0430\u0440\u0430\u043a"
    ],
    "name:sco_x_preferred":[
        "Khashtarak"
    ],
    "name:unk_x_variant":[
        "Khashtarak"
    ],
    "name:vie_x_preferred":[
        "Khashtarak"
    ],
    "name:zho_min_nan_x_preferred":[
        "Khashtarak"
    ],
    "qs:gn_country":"AM",
    "qs:gn_fcode":"PPL",
    "qs:gn_pop":1728,
    "qs:name":"Khasht'arrak",
    "qs:name_adm0":"Armenia",
    "qs:name_adm1":"Tavush",
    "qs:photos":0,
    "qs:photos_1k":0,
    "qs:photos_9k":1,
    "qs:photos_9r":1,
    "qs:photos_all":2,
    "qs:photos_sr":0,
    "qs:placetype":"Town",
    "qs:pop_sr":"3",
    "qs:woe_adm0":23424743,
    "wd:wordcount":129,
    "wof:name":"Khasht'arrak",
    "wof:placetype":"locality",
    "wof:population":1728
},
  "geometry": {"coordinates":[45.1821,40.93668],"type":"Point"}
}