{
  "type": "Feature",
  "properties": {
    "gn:admin1_code":"08",
    "gn:asciiname":"Zovaber",
    "gn:cc2":"AM",
    "gn:country_code":"AM",
    "gn:dem":1704,
    "gn:feature_class":"P",
    "gn:feature_code":"PPL",
    "gn:name":"Zovaber",
    "gn:population":0,
    "gn:timezone":"Asia/Yerevan",
    "iso:country":"AM",
    "name:ita_x_preferred":[
        "Zovaber"
    ],
    "name:rus_x_preferred":[
        "\u0417\u043e\u0432\u0430\u0431\u0435\u0440"
    ],
    "name:sco_x_preferred":[
        "Zovaber"
    ],
    "name:und_x_variant":[
        "Yaudzhi",
        "Yaydzhi",
        "Yayji",
        "Zovaber"
    ],
    "wof:name":"Zovaber",
    "wof:placetype":"locality"
},
  "geometry": {"coordinates":[46.23333,39.43333],"type":"Point"}
}