{
  "type": "Feature",
  "properties": {
    "gn:admin1_code":"8.0",
    "gn:asciiname":"Kroyi",
    "gn:country_code":"AM",
    "gn:dem":1712,
    "gn:feature_class":"P",
    "gn:feature_code":"PPL",
    "gn:name":"Kroyi",
    "gn:population":0,
    "gn:timezone":"Asia/Yerevan",
    "iso:country":"AM",
    "name:hye_x_preferred":[
        "Kroyi"
    ],
    "name:hye_x_variant":[
        "\u053f\u0580\u0578\u0575\u056b"
    ],
    "wof:name":"Kroyi",
    "wof:placetype":"locality"
},
  "geometry": {"coordinates":[45.96393,39.4931],"type":"Point"}
}