{
  "type": "Feature",
  "properties": {
    "gn:admin1_code":"9.0",
    "gn:asciiname":"Anahti Bats'at",
    "gn:country_code":"AM",
    "gn:dem":1558,
    "gn:feature_class":"P",
    "gn:feature_code":"PPL",
    "gn:name":"Anahti Bats\u2019at",
    "gn:population":0,
    "gn:timezone":"Asia/Yerevan",
    "iso:country":"AM",
    "name:hye_x_preferred":[
        "Anahti Bats\u2019at"
    ],
    "name:hye_x_variant":[
        "\u0531\u0576\u0561\u0570\u057f\u056b \u0562\u0561\u0581\u0561\u057f"
    ],
    "wof:name":"Anahti Bats'at",
    "wof:placetype":"locality"
},
  "geometry": {"coordinates":[45.34729,40.70569],"type":"Point"}
}