{
  "type": "Feature",
  "properties": {
    "gn:admin1_code":"5.0",
    "gn:asciiname":"Shnist",
    "gn:country_code":"AM",
    "gn:dem":1925,
    "gn:feature_class":"P",
    "gn:feature_code":"PPL",
    "gn:name":"Shnist",
    "gn:population":0,
    "gn:timezone":"Asia/Yerevan",
    "iso:country":"AM",
    "name:hye_x_preferred":[
        "Shnist"
    ],
    "name:hye_x_variant":[
        "\u0547\u0576\u056b\u057d\u057f"
    ],
    "wof:name":"Shnist",
    "wof:placetype":"locality"
},
  "geometry": {"coordinates":[44.66669,40.70709],"type":"Point"}
}