{
  "type": "Feature",
  "properties": {
    "gn:admin1_code":"6.0",
    "gn:asciiname":"Oskanadzor",
    "gn:country_code":"AM",
    "gn:dem":1877,
    "gn:feature_class":"P",
    "gn:feature_code":"PPL",
    "gn:name":"Oskanadzor",
    "gn:population":0,
    "gn:timezone":"Asia/Yerevan",
    "iso:country":"AM",
    "name:hye_x_preferred":[
        "Oskanadzor"
    ],
    "name:hye_x_variant":[
        "\u0548\u057d\u056f\u0561\u0576\u0561\u0571\u0578\u0580"
    ],
    "wof:name":"Oskanadzor",
    "wof:placetype":"locality"
},
  "geometry": {"coordinates":[44.4043,40.8681],"type":"Point"}
}