{
  "type": "Feature",
  "properties": {
    "iso:country":"AM",
    "name:ara_x_preferred":[
        "\u0628\u064a\u0648\u0631\u063a\u0627\u0648\u0627\u0646"
    ],
    "name:arm_x_preferred":[
        "\u0532\u0575\u0578\u0582\u0580\u0565\u0572\u0561\u057e\u0561\u0576"
    ],
    "name:bel_x_preferred":[
        "\u0413\u043e\u0440\u0430\u0434 \u0411\u044e\u0440\u044d\u0433\u0430\u0432\u0430\u043d"
    ],
    "name:bul_x_preferred":[
        "\u0411\u044e\u0440\u0435\u0433\u0430\u0432\u0430\u043d"
    ],
    "name:ceb_x_preferred":[
        "Byureghavan"
    ],
    "name:che_x_preferred":[
        "\u0411\u044e\u0440\u0435\u0433\u0430\u0432\u0430\u043d"
    ],
    "name:dut_x_preferred":[
        "Byureghavan"
    ],
    "name:eng_x_preferred":[
        "Byureghavan"
    ],
    "name:epo_x_preferred":[
        "Bjureghavan"
    ],
    "name:fas_x_preferred":[
        "\u0628\u06cc\u0648\u0631\u063a\u0627\u0648\u0627\u0646"
    ],
    "name:fra_x_preferred":[
        "Byureghavan"
    ],
    "name:fre_x_preferred":[
        "Byureghavan"
    ],
    "name:geo_x_preferred":[
        "\u10d1\u10d8\u10e3\u10e0\u10d4\u10d2\u10d0\u10d5\u10d0\u10dc\u10d8"
    ],
    "name:hye_x_preferred":[
        "\u0532\u0575\u0578\u0582\u0580\u0565\u0572\u0561\u057e\u0561\u0576"
    ],
    "name:hye_x_variant":[
        "Byureghavan"
    ],
    "name:ind_x_preferred":[
        "Byureghavan"
    ],
    "name:ita_x_preferred":[
        "Byureghavan"
    ],
    "name:kat_x_preferred":[
        "\u10d1\u10d8\u10e3\u10e0\u10d4\u10e6\u10d0\u10d5\u10d0\u10dc\u10d8"
    ],
    "name:lit_x_preferred":[
        "Biurehavanas"
    ],
    "name:may_x_preferred":[
        "Byureghavan"
    ],
    "name:msa_x_preferred":[
        "Byureghavan"
    ],
    "name:mzn_x_preferred":[
        "\u0628\u06cc\u0648\u0631\u063a\u0627\u0648\u0627\u0646"
    ],
    "name:nan_x_preferred":[
        "Byureghavan"
    ],
    "name:nld_x_preferred":[
        "Bjoeregavan"
    ],
    "name:per_x_preferred":[
        "\u0628\u06cc\u0648\u0631\u063a\u0627\u0648\u0627\u0646"
    ],
    "name:ron_x_preferred":[
        "Biureghavan"
    ],
    "name:rum_x_preferred":[
        "Byureghavan"
    ],
    "name:rus_x_preferred":[
        "\u0411\u044e\u0440\u0435\u0433\u0430\u0432\u0430\u043d"
    ],
    "name:sco_x_preferred":[
        "Byureghavan"
    ],
    "name:spa_x_preferred":[
        "Byureghavan"
    ],
    "name:swa_x_preferred":[
        "Byureghavan"
    ],
    "name:swe_x_preferred":[
        "Byureghavan"
    ],
    "name:ukr_x_preferred":[
        "\u0411\u044e\u0440\u0435\u0433\u0430\u0432\u0430\u043d"
    ],
    "name:unk_x_variant":[
        "Byuregavan"
    ],
    "name:vie_x_preferred":[
        "Byureghavan"
    ],
    "name:zho_min_nan_x_preferred":[
        "Byureghavan"
    ],
    "qs:gn_country":"AM",
    "qs:gn_fcode":"PPL",
    "qs:gn_pop":6972,
    "qs:name":"Byureghavan",
    "qs:name_adm0":"Armenia",
    "qs:name_adm1":"Kotayk'",
    "qs:photos":0,
    "qs:photos_1k":0,
    "qs:photos_9k":0,
    "qs:photos_9r":0,
    "qs:photos_all":0,
    "qs:photos_sr":0,
    "qs:placetype":"Town",
    "qs:pop_sr":"5",
    "qs:woe_adm0":23424743,
    "wd:wordcount":323,
    "wof:name":"Byureghavan",
    "wof:placetype":"locality",
    "wof:population":6972
},
  "geometry": {"coordinates":[44.59396,40.31485],"type":"Point"}
}